Workbook

Sheet 01_Summary
A1: ADU Materials Estimate V2 — Зведений по фазам
A3: Проєкт | B3: Garage Conversion to ADU
A4: Локація | B4: Menlo Park, California 94025
A5: Total ADU Area | B5: 315 sq ft (15' × 21')
A6: Ceiling | B6: Vaulted: 8 ft edges / 12 ft center
A7: Raised Floor | B7: 10 inches
A8: Estimate Type | B8: Materials only (no labor / fees / tax per ТЗ §32)
A9: Approach | B9: Construction phases (shell-to-finish, coробка готова)
A10: Sources | B10: Home Depot / IKEA / Best Buy / Amazon / Special Order
A11: Дата створення | B11: 2026-05-28
A12: Статус | B12: V2 Draft — phase-based, потребує заповнення цін
A15: Розподіл по construction phases
A16: # | B16: Phase / Лист | C16: Phase Label | D16: Опис | E16: Items | F16: Subtotal ($) | G16: % of Total
A17: 1 | B17: 02_Site_Exterior_Utilities | C17: Site / Trenching | D17: Phase 1 — Site & Exterior Utilities (§19) | E17: 49 | F17: ='02_Site_Exterior_Utilities'!K55 | G17: =IF($F$37=0,"",F17/$F$37)
A18: 2 | B18: 03_Raised_Floor_System | C18: Floor System | D18: Phase 2 — Raised Floor System (§17) | E18: 22 | F18: ='03_Raised_Floor_System'!K28 | G18: =IF($F$37=0,"",F18/$F$37)
A19: 3 | B19: 04_Framing | C19: Framing | D19: Phase 3 — Framing (§18) | E19: 23 | F19: ='04_Framing'!K29 | G19: =IF($F$37=0,"",F19/$F$37)
A20: 4 | B20: 05_Doors_Windows | C20: Openings | D20: Phase 4 — Doors & Windows / Openings (§25) | E20: 30 | F20: ='05_Doors_Windows'!K36 | G20: =IF($F$37=0,"",F20/$F$37)
A21: 5 | B21: 06_Plumbing_Roughin | C21: Plumbing R-I | D21: Phase 5 — Plumbing Rough-in (§20) | E21: 34 | F21: ='06_Plumbing_Roughin'!K40 | G21: =IF($F$37=0,"",F21/$F$37)
A22: 6 | B22: 07_Electrical_Roughin | C22: Electrical R-I | D22: Phase 6 — Electrical Rough-in (§21) | E22: 37 | F22: ='07_Electrical_Roughin'!K43 | G22: =IF($F$37=0,"",F22/$F$37)
A23: 7 | B23: 08_HVAC_MiniSplit | C23: HVAC | D23: Phase 7 — HVAC Mini-Split (§22) | E23: 24 | F23: ='08_HVAC_MiniSplit'!K30 | G23: =IF($F$37=0,"",F23/$F$37)
A24: 8 | B24: 09_Insulation | C24: Insulation | D24: Phase 8 — Insulation (§23) | E24: 16 | F24: ='09_Insulation'!K22 | G24: =IF($F$37=0,"",F24/$F$37)
A25: 9 | B25: 10_Drywall | C25: Drywall | D25: Phase 9 — Drywall (§24) | E25: 20 | F25: ='10_Drywall'!K26 | G25: =IF($F$37=0,"",F25/$F$37)
A26: 10 | B26: 11_Paint | C26: Paint | D26: Phase 10 — Paint (§27) | E26: 20 | F26: ='11_Paint'!K26 | G26: =IF($F$37=0,"",F26/$F$37)
A27: 11 | B27: 12_Flooring_Trim | C27: Flooring | D27: Phase 11 — Flooring & Trim (§26) | E27: 14 | F27: ='12_Flooring_Trim'!K20 | G27: =IF($F$37=0,"",F27/$F$37)
A28: 12 | B28: 13_Kitchen_Cabinets | C28: Cabinetry | D28: Phase 12 — Kitchen Cabinets & Countertop (§11) | E28: 32 | F28: ='13_Kitchen_Cabinets'!K38 | G28: =IF($F$37=0,"",F28/$F$37)
A29: 13 | B29: 14_Bathroom_Fixtures | C29: Finish — Fixtures | D29: Phase 13 — Bathroom Fixtures (§14) | E29: 42 | F29: ='14_Bathroom_Fixtures'!K48 | G29: =IF($F$37=0,"",F29/$F$37)
A30: 14 | B30: 15_Closet_System | C30: Furnishing | D30: Phase 14 — Closet System (§13) | E30: 17 | F30: ='15_Closet_System'!K23 | G30: =IF($F$37=0,"",F30/$F$37)
A31: 15 | B31: 16_Water_Heater | C31: MEP — Water Heater | D31: Phase 15 — Water Heater & Utility (§16) | E31: 17 | F31: ='16_Water_Heater'!K23 | G31: =IF($F$37=0,"",F31/$F$37)
A32: 16 | B32: 17_Appliances | C32: Appliances | D32: Phase 16 — Appliances (§28) | E32: 17 | F32: ='17_Appliances'!K23 | G32: =IF($F$37=0,"",F32/$F$37)
A33: 17 | B33: 18_Furniture_IKEA | C33: Furniture | D33: Phase 17 — Furniture (§29) | E33: 27 | F33: ='18_Furniture_IKEA'!K33 | G33: =IF($F$37=0,"",F33/$F$37)
A34: 18 | B34: 19_Special_Orders | C34: Special Order | D34: Cross-reference — Special Orders (§31.5) | E34: 7 | F34: ='19_Special_Orders'!K13 | G34: =IF($F$37=0,"",F34/$F$37)
A35: 19 | B35: 20_Verification_Items | C35: Verification | D35: Cross-reference — Verification Items (§33) | E35: 26 | F35: ='20_Verification_Items'!K32 | G35: =IF($F$37=0,"",F35/$F$37)
B37: GRAND TOTAL | F37: =SUM(F17:F35)
A39: ℹ️ Phase 19 (Special Orders) = CROSS-REFERENCE only. Items already in respective phases (Phase 4, 7, 15, 16). Не додає до Grand Total.
A40: ℹ️ Phase 20 (Verification Items) = 26 пунктів §33 not priced, but may change quantities after field verification.
A42: 📊 Reference Totals (НЕ включено в Grand Total)
A43: Item | B43: $
A44: Grand Total — Materials Only | B44: =F37
A45: Estimated CA Sales Tax 9.375% (reference) | B45: =F37*0.09375
A46: Materials + Tax (reference) | B46: =F37*1.09375
A47: 10% Material Buffer (reference) | B47: =F37*0.10
A48: 15% Material Buffer (reference) | B48: =F37*0.15
A49: 20% Material Buffer (reference) | B49: =F37*0.20
A50: Materials + Tax + 15% Buffer (planning) | B50: =F37*1.09375 + F37*0.15
A53: 🔝 Top Cost Drivers (top phases по сумі)
A54: • 1. Doors & Windows / Openings — ~18%
A55: • 2. Appliances — ~11%
A56: • 3. HVAC Mini-Split — ~8%
A57: • 4. Electrical Rough-in — ~8%
A58: • 5. Furniture — ~7%
A59: • 6. Raised Floor — ~7%
A60: • 7. Kitchen Cabinets — ~7%
A61: • 8. Site / Exterior Utilities — ~6%
A63: ⚠️ High-Risk Verification Items (можуть змінити quantities)
A64: • Bathroom + laundry + utility fit (5'×7' може не вмістити все)
A65: • Existing garage door opening — closure framing + sheathing
... A93: • CA Code-required items (seismic strap, AFCI breakers, TR outlets, hardwired smoke/CO)

Sheet 02_Site_Exterior_Utilities
A1: Phase 1 — Site & Exterior Utilities (§19)
A2: Sewer 100ft + Water 100ft + Electric 50ft
A4: # | B4: Phase | C4: Категорія | D4: Item / Material | E4: Spec / Опис | F4: Unit | G4: Qty (Low) | H4: Qty (Mid) | I4: Qty (High) | J4: Unit Price ($) | K4: Total ($) | L4: Source | M4: SKU / Model | N4: URL | O4: Status | P4: Confidence | Q4: Notes
A5: 1 | B5: Site / Trenching | C5: Sewer | D5: Sewer Pipe 4" | E5: SDR35 PVC, 10 ft pieces | F5: linear ft | G5: 100 | H5: 110 | I5: 120 | J5: 2.4 | K5: =IF(OR(H5="",J5="",J5=0),"",H5*J5) | L5: Home Depot | M5: Charlotte / JM Eagle 4" SDR35 | N5: https://www.homedepot.com/p/Charlotte-Pipe-4-in-x-10-ft-White-PVC-Sewer-Main-SDR35-Pipe-with-Gaskete-S-M-06004G-1400/203504420 | O5: Confirmed | P5: high | Q5: 100 ft підтверджено власником | $2.40/LF. Charlotte SDR35 10ft pieces ~$24 | Ціна збір: 2026-05-28
A6: 2 | B6: Site / Trenching | C6: Sewer | D6: Sewer Couplings 4" | E6: Hub couplings | F6: pcs | G6: 4 | H6: 6 | I6: 8 | J6: 5.5 | K6: =IF(OR(H6="",J6="",J6=0),"",H6*J6) | L6: Home Depot | M6: Generic SDR35 4" | O6: Confirmed | P6: medium | Q6: Hub couplings | Ціна збір: 2026-05-28
A7: 3 | B7: Site / Trenching | C7: Sewer | D7: Sewer Elbows 45°/90° | E7: ABS/PVC short radius | F7: pcs | G7: 4 | H7: 6 | I7: 8 | J7: 7.5 | K7: =IF(OR(H7="",J7="",J7=0),"",H7*J7) | L7: Home Depot | M7: Generic SDR35 4" | O7: Confirmed | P7: medium | Q7: 45° + 90° short radius mix | Ціна збір: 2026-05-28
A8: 4 | B8: Site / Trenching | C8: Sewer | D8: Long-radius Sweep 4" | E8: Для slope (рекомендовано) | F8: pcs | G8: 2 | H8: 3 | I8: 4 | J8: 15 | K8: =IF(OR(H8="",J8="",J8=0),"",H8*J8) | L8: Home Depot | M8: Generic SDR35 4" | O8: TBD | P8: medium | Q8: Slope to be verified by plumber / local code | Long-radius sweep — slope verify by plumber | Ціна збір: 2026-05-28
A9: 5 | B9: Site / Trenching | C9: Sewer | D9: Wye Fittings 4" | E9: Branch tie-ins | F9: pcs | G9: 2 | H9: 3 | I9: 4 | J9: 15 | K9: =IF(OR(H9="",J9="",J9=0),"",H9*J9) | L9: Home Depot | M9: Generic SDR35 4" | O9: Confirmed | P9: medium | Q9: Wye 4×4×4 | Ціна збір: 2026-05-28
A10: 6 | B10: Site / Trenching | C10: Sewer | D10: Sewer Cleanouts 4" | E10: Body + plug + collar | F10: pcs | G10: 2 | H10: 3 | I10: 4 | J10: 28 | K10: =IF(OR(H10="",J10="",J10=0),"",H10*J10) | L10: Home Depot | M10: Generic 4" cleanout | O10: Confirmed | P10: medium | Q10: Depends on route and bends — підвищено Mid до 3 | Body + plug + collar. Mid підвищено до 3 | Ціна збір: 2026-05-28
A11: 7 | B11: Site / Trenching | C11: Sewer | D11: Primer / Cement ABS-PVC | E11: Solvent weld | F11: cans | G11: 2 | H11: 3 | I11: 4 | J11: 12 | K11: =IF(OR(H11="",J11="",J11=0),"",H11*J11) | L11: Home Depot | M11: Oatey / Christy's | O11: Confirmed | P11: medium | Q11: Primer+cement combo | Ціна збір: 2026-05-28
A12: 8 | B12: Site / Trenching | C12: Sewer | D12: Sand Bedding (3" under pipe) | E12: Cushion under pipe | F12: cu yd | G12: 1 | H12: 2 | I12: 3 | J12: 35 | K12: =IF(OR(H12="",J12="",J12=0),"",H12*J12) | L12: Aggregate yard | M12: Aggregate yard | O12: Confirmed | P12: medium | Q12: Recommended — verify if required by local code / utility | Sand bedding — verify if required | Ціна збір: 2026-05-28
A13: 9 | B13: Site / Trenching | C13: Sewer | D13: Gravel / Bedding (above pipe) | E13: 3/4" rock | F13: cu yd | G13: 1 | H13: 2 | I13: 3 | J13: 45 | K13: =IF(OR(H13="",J13="",J13=0),"",H13*J13) | L13: Aggregate yard | M13: Aggregate yard | O13: TBD | P13: medium | Q13: 3/4" rock backfill | Ціна збір: 2026-05-28
A14: 10 | B14: Site / Trenching | C14: Sewer | D14: Tracer Wire 14 AWG | E14: Locator wire для non-metallic | F14: linear ft | G14: 100 | H14: 110 | I14: 120 | J14: 0.15 | K14: =IF(OR(H14="",J14="",J14=0),"",H14*J14) | L14: Home Depot | M14: Generic 14 AWG tracer | O14: Confirmed | P14: medium | Q14: Recommended — verify if required by local code | Tracer wire — verify if required by code | Ціна збір: 2026-05-28
A15: 11 | B15: Site / Trenching | C15: Sewer | D15: Warning Tape Detectable | E15: 'CAUTION SEWER' | F15: rolls | G15: 1 | H15: 1 | I15: 1 | J15: 15 | K15: =IF(OR(H15="",J15="",J15=0),"",H15*J15) | L15: Home Depot | M15: Generic detectable | O15: Confirmed | P15: medium | Q15: 'CAUTION SEWER' | Ціна збір: 2026-05-28
A16: 12 | B16: Site / Trenching | C16: Sewer | D16: Wall / Foundation Sleeve 4" | E16: Slab penetration | F16: pcs | G16: 1 | H16: 1 | I16: 1 | J16: 25 | K16: =IF(OR(H16="",J16="",J16=0),"",H16*J16) | L16: Home Depot | M16: 4" PVC sleeve | O16: TBD | P16: low | Q16: Slab penetration | Ціна збір: 2026-05-28
A17: 13 | B17: Site / Trenching | C17: Sewer | D17: Concrete Patch Material | E17: 50 lb bag | F17: bags | G17: 1 | H17: 2 | I17: 3 | J17: 9 | K17: =IF(OR(H17="",J17="",J17=0),"",H17*J17) | L17: Home Depot | M17: Quikrete / Sakrete | O17: TBD | P17: medium | Q17: 50 lb bag | Ціна збір: 2026-05-28
A18: 14 | B18: Site / Trenching | C18: Sewer | D18: Test Caps / Cleanout Plugs allowance | E18: Для rough-in / pressure testing | F18: set | G18: 1 | H18: 1 | I18: 2 | J18: 25 | K18: =IF(OR(H18="",J18="",J18=0),"",H18*J18) | L18: Home Depot | M18: Generic 4" caps allowance | O18: Confirmed | P18: medium | Q18: ДОДАНО (review): для тестування pipe ends | ДОДАНО: test caps/plugs для pipe ends | Ціна збір: 2026-05-28
A19: 15 | B19: Site / Trenching | C19: Water Supply | D19: Main Water Supply Pipe | E19: PEX-A 1" coil | F19: linear ft | G19: 100 | H19: 110 | I19: 120 | J19: 1.45 | K19: =IF(OR(H19="",J19="",J19=0),"",H19*J19) | L19: Home Depot | M19: SharkBite UA80W100 PEX-A 1" | N19: https://www.homedepot.com/p/SharkBite-1-in-x-100-ft-Coil-White-PEX-A-Pipe-UA80W100/316358329 | O19: Confirmed | P19: high | Q19: 100 ft підтверджено | $1.45/LF ($145 per 100ft coil). Alt: copper L $4-5/LF | Ціна збір: 2026-05-28
A20: 16 | B20: Site / Trenching | C20: Water Supply | D20: PEX-A UV Protective Sleeve | E20: HDPE для buried PEX | F20: linear ft | G20: 100 | H20: 110 | I20: 120 | J20: 1 | K20: =IF(OR(H20="",J20="",J20=0),"",H20*J20) | L20: Home Depot / specialty | M20: HDPE protective sleeve | O20: Confirmed | P20: medium | Q20: PEX-A degrades on UV — required для buried sections | PEX-A UV protection for buried | Ціна збір: 2026-05-28
A21: 17 | B21: Site / Trenching | C21: Water Supply | D21: Main Shut-off Valve (ADU) 1" | E21: Brass ball, full port | F21: pcs | G21: 1 | H21: 1 | I21: 1 | J21: 30 | K21: =IF(OR(H21="",J21="",J21=0),"",H21*J21) | L21: Home Depot | M21: Brass ball valve 1" | O21: Confirmed | P21: medium | Q21: Full port, lead-free | Ціна збір: 2026-05-28
A22: 18 | B22: Site / Trenching | C22: Water Supply | D22: Brass Union Connector | E22: Tap point + ADU connection | F22: pcs | G22: 1 | H22: 2 | I22: 2 | J22: 20 | K22: =IF(OR(H22="",J22="",J22=0),"",H22*J22) | L22: Home Depot | M22: Brass union 1" | O22: Confirmed | P22: medium | Q22: Tap point + ADU connection | Ціна збір: 2026-05-28
A23: 19 | B23: Site / Trenching | C23: Water Supply | D23: Water Meter (separate) | E23: Якщо ADU має окремий meter | F23: pcs | G23: 0 | H23: 0 | I23: 1 | J23: 250 | K23: =IF(OR(H23="",J23="",J23=0),"",H23*J23) | L23: Special Order / utility | M23: Badger / Neptune meter | O23: Optional | P23: low | Q23: OPTIONAL — verify with utility / town. Не входить в baseline total | OPTIONAL — verify з utility / town | Ціна збір: 2026-05-28
A24: 20 | B24: Site / Trenching | C24: Water Supply | D24: Water Fittings / Couplings | E24: PEX brass crimp pack | F24: pack | G24: 1 | H24: 2 | I24: 3 | J24: 35 | K24: =IF(OR(H24="",J24="",J24=0),"",H24*J24) | L24: Home Depot | M24: PEX brass crimp pack | O24: Confirmed | P24: medium | Q24: Fittings assortment | Ціна збір: 2026-05-28
A25: 21 | B25: Site / Trenching | C25: Water Supply | D25: Pipe Sleeves | E25: Slab/wall penetration | F25: pcs | G25: 2 | H25: 3 | I25: 4 | J25: 7 | K25: =IF(OR(H25="",J25="",J25=0),"",H25*J25) | L25: Home Depot | M25: Generic 1" sleeve | O25: TBD | P25: medium
A26: 22 | B26: Site / Trenching | C26: Water Supply | D26: Pipe Insulation (above-grade) | E26: Foam tube 1" | F26: linear ft | G26: 30 | H26: 50 | I26: 80 | J26: 0.7 | K26: =IF(OR(H26="",J26="",J26=0),"",H26*J26) | L26: Home Depot | M26: Armaflex foam 1" | O26: TBD | P26: medium | Q26: Above-grade insulation | Ціна збір: 2026-05-28
A27: 23 | B27: Site / Trenching | C27: Water Supply | D27: Tracer Wire 14 AWG (water) | E27: Locator wire для non-metallic | F27: linear ft | G27: 100 | H27: 110 | I27: 120 | J27: 0.15 | K27: =IF(OR(H27="",J27="",J27=0),"",H27*J27) | L27: Home Depot | M27: Generic 14 AWG tracer | O27: Confirmed | P27: medium | Q27: Recommended — verify if required by local code | Tracer wire — verify if required by code | Ціна збір: 2026-05-28
A28: 24 | B28: Site / Trenching | C28: Water Supply | D28: Warning Tape (water) | E28: 'CAUTION WATER' | F28: rolls | G28: 1 | H28: 1 | I28: 1 | J28: 12 | K28: =IF(OR(H28="",J28="",J28=0),"",H28*J28) | L28: Home Depot | M28: Generic 'WATER' tape | O28: Confirmed | P28: medium
A29: 25 | B29: Site / Trenching | C29: Water Supply | D29: Bedding Material | E29: Sand bed під pipe | F29: cu yd | G29: 1 | H29: 2 | I29: 3 | J29: 45 | K29: =IF(OR(H29="",J29="",J29=0),"",H29*J29) | L29: Aggregate yard | M29: Aggregate yard | O29: TBD | P29: medium | Q29: Sand bedding | Ціна збір: 2026-05-28
A30: 26 | B30: Site / Trenching | C30: Water Supply | D30: Pressure Regulator / Backflow | E30: Якщо street >80 PSI | F30: pcs | G30: 0 | H30: 1 | I30: 1 | J30: 100 | K30: =IF(OR(H30="",J30="",J30=0),"",H30*J30) | L30: Home Depot | M30: Watts / Honeywell PRV | O30: TBD | P30: low | Q30: If street >80 PSI | Ціна збір: 2026-05-28
A31: 27 | B31: Site / Trenching | C31: Water Supply | D31: Pressure Test Cap / Plug Set | E31: Для rough-in pressure test | F31: set | G31: 1 | H31: 1 | I31: 1 | J31: 20 | K31: =IF(OR(H31="",J31="",J31=0),"",H31*J31) | L31: Home Depot | M31: Generic test cap set | O31: Confirmed | P31: medium | Q31: ДОДАНО (review): для rough-in testing | ДОДАНО: pressure test caps | Ціна збір: 2026-05-28
A32: 28 | B32: Site / Trenching | C32: Water Supply | D32: Ball Valve Access Box | E32: Якщо shut-off зовні / underground | F32: pcs | G32: 0 | H32: 1 | I32: 1 | J32: 25 | K32: =IF(OR(H32="",J32="",J32=0),"",H32*J32) | L32: Home Depot | M32: Generic valve access box | O32: TBD | P32: medium | Q32: ДОДАНО (review): access для outdoor shut-off | ДОДАНО: outdoor shut-off access | Ціна збір: 2026-05-28
A33: 29 | B33: Site / Trenching | C33: Water Supply | D33: Pipe Clamps / Supports | E33: Для above-grade sections | F33: pack | G33: 1 | H33: 1 | I33: 2 | J33: 20 | K33: =IF(OR(H33="",J33="",J33=0),"",H33*J33) | L33: Home Depot | M33: Generic pipe clamps pack | O33: Confirmed | P33: medium | Q33: ДОДАНО (review) | ДОДАНО: above-grade pipe supports | Ціна збір: 2026-05-28
A34: 30 | B34: Site / Trenching | C34: Electrical Feed | D34: Electrical Conduit (feeder) | E34: Schedule 40 PVC 2" | F34: linear ft | G34: 50 | H34: 60 | I34: 70 | J34: 1.1 | K34: =IF(OR(H34="",J34="",J34=0),"",H34*J34) | L34: Home Depot | M34: Cantex / Carlon Sch40 2" | O34: Confirmed | P34: medium | Q34: 50 ft підтверджено | $11 per 10ft. Sch 40 PVC | Ціна збір: 2026-05-28
A35: 31 | B35: Site / Trenching | C35: Electrical Feed | D35: PVC 90° Sweeps Long-Radius 2" | E35: Bends in trench | F35: pcs | G35: 2 | H35: 3 | I35: 4 | J35: 20 | K35: =IF(OR(H35="",J35="",J35=0),"",H35*J35) | L35: Home Depot | M35: Cantex / Carlon long-radius | O35: Confirmed | P35: medium | Q35: Long-radius для cable pulling | 90° LR sweep для cable pulling | Ціна збір: 2026-05-28
A36: 32 | B36: Site / Trenching | C36: Electrical Feed | D36: PVC 45° Sweeps 2" | E36: Transitions | F36: pcs | G36: 1 | H36: 2 | I36: 3 | J36: 15 | K36: =IF(OR(H36="",J36="",J36=0),"",H36*J36) | L36: Home Depot | M36: Cantex / Carlon | O36: Confirmed | P36: medium | Q36: 45° sweep | Ціна збір: 2026-05-28
A37: 33 | B37: Site / Trenching | C37: Electrical Feed | D37: PVC Expansion Fitting 2" | E37: Thermal expansion compensation | F37: pcs | G37: 1 | H37: 1 | I37: 1 | J37: 25 | K37: =IF(OR(H37="",J37="",J37=0),"",H37*J37) | L37: Home Depot | M37: Cantex expansion | O37: Confirmed | P37: medium | Q37: Recommended — verify if required by local code | Thermal expansion — verify if req'd | Ціна збір: 2026-05-28
A38: 34 | B38: Site / Trenching | C38: Electrical Feed | D38: PVC Conduit Cement | E38: Solvent weld for PVC | F38: cans | G38: 1 | H38: 1 | I38: 1 | J38: 10 | K38: =IF(OR(H38="",J38="",J38=0),"",H38*J38) | L38: Home Depot | M38: Oatey PVC cement | O38: Confirmed | P38: medium | Q38: Conduit solvent weld | Ціна збір: 2026-05-28
A39: 35 | B39: Site / Trenching | C39: Electrical Feed | D39: Feeder Wire | E39: Cu SER 4-4-4-6 (base) OR Al SER 2-2-2-4 | F39: linear ft | G39: 50 | H39: 60 | I39: 70 | J39: 8.78 | K39: =IF(OR(H39="",J39="",J39=0),"",H39*J39) | L39: Home Depot / specialty | M39: Cu SER 4-4-4-6 (base) / Al SER 2-2-2-4 (alt) | N39: https://www.wireandcableyourway.com/4-4-4-6-copper-ser-service-entrance-cable | O39: TBD | P39: high | Q39: TBD by electrician / load calculation. Cu SER ~$8.78/LF, Al SER ~$3.50/LF (-$315 з 60 LF). Final type/size pendant on ADU load calc | TBD by electrician/load calc. Cu $8.78/LF, Al ~$3.50/LF (-$315) | Ціна збір: 2026-05-28
A40: 36 | B40: Site / Trenching | C40: Electrical Feed | D40: Disconnect Switch (exterior) | E40: 100A non-fusible if req'd | F40: pcs | G40: 0 | H40: 1 | I40: 1 | J40: 45 | K40: =IF(OR(H40="",J40="",J40=0),"",H40*J40) | L40: Home Depot | M40: Square D / Eaton 100A | O40: TBD | P40: medium | Q40: Non-fusible exterior if req'd | Ціна збір: 2026-05-28
A41: 37 | B41: Site / Trenching | C41: Electrical Feed | D41: Ground Rod 8 ft Copper-clad | E41: Driven rod | F41: pcs | G41: 1 | H41: 1 | I41: 2 | J41: 18 | K41: =IF(OR(H41="",J41="",J41=0),"",H41*J41) | L41: Home Depot | M41: Copper-clad 8 ft rod | O41: Confirmed | P41: medium | Q41: Driven ground rod | Ціна збір: 2026-05-28
A42: 38 | B42: Site / Trenching | C42: Electrical Feed | D42: Ground Rod Clamp | E42: Acorn or bolt clamp | F42: pcs | G42: 1 | H42: 1 | I42: 2 | J42: 5 | K42: =IF(OR(H42="",J42="",J42=0),"",H42*J42) | L42: Home Depot | M42: Acorn ground clamp | O42: Confirmed | P42: medium | Q42: Bolt-on | Ціна збір: 2026-05-28
A43: 39 | B43: Site / Trenching | C43: Electrical Feed | D43: #6 Bare Cu Ground Wire | E43: Service ground | F43: linear ft | G43: 10 | H43: 15 | I43: 25 | J43: 1.2 | K43: =IF(OR(H43="",J43="",J43=0),"",H43*J43) | L43: Home Depot | M43: #6 bare copper | O43: Confirmed | P43: medium | Q43: Per LF, service ground | Ціна збір: 2026-05-28
A44: 40 | B44: Site / Trenching | C44: Electrical Feed | D44: Pull String / Fish Tape | E44: Для cable pulling | F44: pcs | G44: 1 | H44: 1 | I44: 1 | J44: 20 | K44: =IF(OR(H44="",J44="",J44=0),"",H44*J44) | L44: Home Depot | M44: Generic pull string / mule tape | O44: Confirmed | P44: medium | Q44: Cable pulling aid | Ціна збір: 2026-05-28
A45: 41 | B45: Site / Trenching | C45: Electrical Feed | D45: Anti-oxidant Compound (NOALOX) | E45: Якщо AL feeder used | F45: tube | G45: 0 | H45: 1 | I45: 1 | J45: 15 | K45: =IF(OR(H45="",J45="",J45=0),"",H45*J45) | L45: Home Depot | M45: NOALOX anti-oxidant | O45: TBD | P45: medium | Q45: Якщо AL feeder used | Ціна збір: 2026-05-28
A46: 42 | B46: Site / Trenching | C46: Electrical Feed | D46: Conduit Straps / Clamps / Mounting | E46: Для exposed conduit sections | F46: pack | G46: 1 | H46: 1 | I46: 2 | J46: 20 | K46: =IF(OR(H46="",J46="",J46=0),"",H46*J46) | L46: Home Depot | M46: Carlon / Cantex straps pack | O46: Confirmed | P46: medium | Q46: ДОДАНО (review): mounting hardware | ДОДАНО: mounting hardware | Ціна збір: 2026-05-28
A47: 43 | B47: Site / Trenching | C47: Electrical Feed | D47: Terminal Adapters / Bushings | E47: Stubs, male adapters, bell ends | F47: pack | G47: 1 | H47: 1 | I47: 1 | J47: 15 | K47: =IF(OR(H47="",J47="",J47=0),"",H47*J47) | L47: Home Depot | M47: Generic adapters/bushings pack | O47: Confirmed | P47: medium | Q47: ДОДАНО (review) | ДОДАНО: terminal adapters | Ціна збір: 2026-05-28
A48: 44 | B48: Site / Trenching | C48: Electrical Feed | D48: Subpanel / Circuit Labels | E48: Для identification | F48: set | G48: 1 | H48: 1 | I48: 1 | J48: 10 | K48: =IF(OR(H48="",J48="",J48=0),"",H48*J48) | L48: Home Depot | M48: Generic labels set | O48: Confirmed | P48: medium | Q48: ДОДАНО (review) | ДОДАНО: subpanel/circuit labels | Ціна збір: 2026-05-28
A49: 45 | B49: Site / Trenching | C49: Electrical Feed | D49: Weatherproof Boxes | F49: pcs | G49: 2 | H49: 3 | I49: 4 | J49: 10 | K49: =IF(OR(H49="",J49="",J49=0),"",H49*J49) | L49: Home Depot | M49: RACO / Carlon WP box | O49: Confirmed | P49: medium
A50: 46 | B50: Site / Trenching | C50: Electrical Feed | D50: Pull Boxes | E50: If req'd | F50: pcs | G50: 0 | H50: 1 | I50: 2 | J50: 25 | K50: =IF(OR(H50="",J50="",J50=0),"",H50*J50) | L50: Home Depot | M50: Generic 6×6×4 PVC | O50: TBD | P50: medium
A51: 47 | B51: Site / Trenching | C51: Electrical Feed | D51: Underground Warning Tape | E51: 'CAUTION ELECTRIC' | F51: rolls | G51: 1 | H51: 1 | I51: 1 | J51: 12 | K51: =IF(OR(H51="",J51="",J51=0),"",H51*J51) | L51: Home Depot | M51: Generic 'ELECTRIC' red | O51: Confirmed | P51: medium
A52: 48 | B52: Site / Trenching | C52: Electrical Feed | D52: Exterior-rated Fittings | E52: Adapters, bushings pack | F52: pack | G52: 1 | H52: 1 | I52: 1 | J52: 25 | K52: =IF(OR(H52="",J52="",J52=0),"",H52*J52) | L52: Home Depot | M52: Adapters/bushings pack | O52: Confirmed | P52: medium | Q52: Stubs, male adapters, bell ends | Ціна збір: 2026-05-28
A53: 49 | B53: Site / Trenching | C53: Site Prep | D53: Marking Paint / Stakes / String Line | E53: Для trench layout всіх 3 утилит | F53: set | G53: 1 | H53: 1 | I53: 1 | J53: 30 | K53: =IF(OR(H53="",J53="",J53=0),"",H53*J53) | L53: Home Depot | M53: Generic marking paint / stakes / string set | O53: Confirmed | P53: medium | Q53: ДОДАНО (review): layout aids | ДОДАНО: trench layout aids | Ціна збір: 2026-05-28
C55: ПІДСУМОК ФАЗИ | K55: =SUM(K5:K53)

Sheet 03_Raised_Floor_System
A1: Phase 2 — Raised Floor System (§17)
A2: Vapor barrier + sleepers + joists + subfloor (10")
A4: # | B4: Phase | C4: Категорія | D4: Item / Material | E4: Spec / Опис | F4: Unit | G4: Qty (Low) | H4: Qty (Mid) | I4: Qty (High) | J4: Unit Price ($) | K4: Total ($) | L4: Source | M4: SKU / Model | N4: URL | O4: Status | P4: Confidence | Q4: Notes
A5: 1 | B5: Floor System | C5: Moisture Control | D5: Vapor / Moisture Barrier | E5: 6-mil poly | F5: sq ft | G5: 315 | H5: 350 | I5: 380 | J5: 0.1 | K5: =IF(OR(H5="",J5="",J5=0),"",H5*J5) | L5: Home Depot | M5: Husky / generic 6-mil poly | O5: Confirmed | P5: medium | Q5: 10" raised over slab | $0.10/sf. 10x100 roll ~$80-100 | Ціна збір: 2026-05-28
A6: 2 | B6: Floor System | C6: Lumber | D6: Pressure-treated Sleepers | E6: 2x4 PT laid flat as bearing | F6: linear ft | G6: 200 | H6: 260 | I6: 320 | J6: 0.95 | K6: =IF(OR(H6="",J6="",J6=0),"",H6*J6) | L6: Home Depot | M6: 2x4 PT SPF/SYP | O6: Confirmed | P6: medium | Q6: Bearing surface для joists на slab | PT для bearing на slab. 8ft ~$7-8 | Ціна збір: 2026-05-28
A7: 3 | B7: Floor System | C7: Lumber | D7: Floor Joists | E7: 2x10 SPF/HF @ 16" OC, 15 ft span | F7: linear ft | G7: 240 | H7: 280 | I7: 340 | J7: 1.85 | K7: =IF(OR(H7="",J7="",J7=0),"",H7*J7) | L7: Home Depot | M7: 2x10 #2 SPF/HF 16 ft | N7: https://www.homedepot.com/p/2-in-x-10-in-x-16-ft-2-Premium-Grade-SPF-Dimensional-Lumber-201673/100016326 | O7: Confirmed | P7: high | Q7: Final joist size/span to be verified by contractor/engineer based on actual support layout | $1.85/LF. SPF 2x10 16ft ~$30/piece (Doug Fir ~$36.63/piece ref). | Ціна збір: 2026-05-28
A8: 4 | B8: Floor System | C8: Lumber | D8: Rim Joists | E8: 2x10 PT за perimeter | F8: linear ft | G8: 60 | H8: 72 | I8: 80 | J8: 2.2 | K8: =IF(OR(H8="",J8="",J8=0),"",H8*J8) | L8: Home Depot | M8: 2x10 PT for perimeter | O8: Confirmed | P8: medium | Q8: PT lumber required where wood contacts concrete or moisture-prone areas | PT для rim on concrete contact | Ціна збір: 2026-05-28
A9: 5 | B9: Floor System | C9: Lumber | D9: Blocking | E9: 2x10 mid-span | F9: linear ft | G9: 30 | H9: 50 | I9: 70 | J9: 1.85 | K9: =IF(OR(H9="",J9="",J9=0),"",H9*J9) | L9: Home Depot | M9: 2x10 SPF blocking | O9: Confirmed | P9: medium | Q9: Same as joists | Ціна збір: 2026-05-28
A10: 6 | B10: Floor System | C10: Hardware | D10: Joist Hangers / Connectors | E10: Simpson LUS210 | F10: pcs | G10: 30 | H10: 50 | I10: 70 | J10: 4 | K10: =IF(OR(H10="",J10="",J10=0),"",H10*J10) | L10: Home Depot | M10: Simpson LUS210 | O10: Confirmed | P10: medium | Q10: Joist hanger for 2x10. $3.50-4.50 each | Ціна збір: 2026-05-28
A11: 7 | B11: Floor System | C11: Hardware | D11: Concrete Anchors (PT to slab) | E11: Wedge / Tapcon 1/2" | F11: pcs | G11: 40 | H11: 60 | I11: 80 | J11: 1.5 | K11: =IF(OR(H11="",J11="",J11=0),"",H11*J11) | L11: Home Depot | M11: Tapcon 1/2" wedge | O11: Confirmed | P11: medium | Q11: Concrete anchor PT to slab | Ціна збір: 2026-05-28
A12: 8 | B12: Floor System | C12: Insulation (floor) | D12: Insulation R-30 batt or Rigid | E12: Batt R-30 between joists | F12: sq ft | G12: 315 | H12: 330 | I12: 350 | J12: 1.61 | K12: =IF(OR(H12="",J12="",J12=0),"",H12*J12) | L12: Home Depot | M12: Owens Corning R-30 EcoTouch 16" OC unfaced | N12: https://www.homedepot.com/p/Owens-Corning-R-30-EcoTouch-PINK-Unfaced-Fiberglass-Insulation-Batt-16-in-x-48-in-BU74/300147480 | O12: Confirmed | P12: high | Q12: Verify floor insulation type: batt vs rigid foam depending on moisture and floor assembly | $1.61/sf. R-30 unfaced 16x48. CA Title 24 compliant | Ціна збір: 2026-05-28
A13: 9 | B13: Floor System | C13: Subfloor | D13: Plywood Subfloor | E13: 3/4" T&G CDX | F13: sq ft | G13: 315 | H13: 350 | I13: 380 | J13: 1.35 | K13: =IF(OR(H13="",J13="",J13=0),"",H13*J13) | L13: Home Depot | M13: CDX 3/4" T&G plywood | N13: https://www.homedepot.com/p/3-4-in-x-4-ft-x-8-ft-CDX-Pine-Plywood-1060/202088096 | O13: Confirmed | P13: high | Q13: $1.35/sf. 4x8 = $43/sheet (LENCO ref $44.95) | Ціна збір: 2026-05-28
A14: 10 | B14: Floor System | C14: Adhesives/Fasteners | D14: Construction Adhesive | E14: PL Premium subfloor | F14: tubes | G14: 6 | H14: 10 | I14: 14 | J14: 10 | K14: =IF(OR(H14="",J14="",J14=0),"",H14*J14) | L14: Home Depot | M14: Loctite PL Premium 10oz | O14: Confirmed | P14: medium | Q14: Subfloor adhesive | Ціна збір: 2026-05-28
A15: 11 | B15: Floor System | C15: Adhesives/Fasteners | D15: Subfloor Screws | E15: 3" #8 deck/subfloor | F15: lb | G15: 5 | H15: 8 | I15: 12 | J15: 6 | K15: =IF(OR(H15="",J15="",J15=0),"",H15*J15) | L15: Home Depot | M15: GRK / generic 3" #8 | O15: Confirmed | P15: medium | Q15: Часто продаються в 5 lb або 10 lb boxes | Subfloor deck screws per lb. 5 lb box ~$30 | Ціна збір: 2026-05-28
A16: 12 | B16: Floor System | C16: Sealants | D16: Foam Sealant / Caulk | E16: Air gap sealing | F16: cans | G16: 3 | H16: 5 | I16: 7 | J16: 6 | K16: =IF(OR(H16="",J16="",J16=0),"",H16*J16) | L16: Home Depot | M16: Great Stuff window/door | O16: Confirmed | P16: medium | Q16: Foam sealant | Ціна збір: 2026-05-28
A17: 13 | B17: Floor System | C17: Transitions | D17: Thresholds & Transitions | E17: Entry, French door, bathroom, exterior step | F17: pcs | G17: 3 | H17: 4 | I17: 5 | J17: 25 | K17: =IF(OR(H17="",J17="",J17=0),"",H17*J17) | L17: Home Depot | M17: Generic aluminum threshold 36" | O17: TBD | P17: medium | Q17: §17.4. Не дублювати з Phase 12 (decorative transitions only) | Entry, French door, bathroom, exterior step | Ціна збір: 2026-05-28
A18: 14 | B18: Floor System | C18: Sealing | D18: Sill Seal Foam Gasket | E18: 1x50 ft roll, між PT і slab | F18: rolls | G18: 1 | H18: 2 | I18: 3 | J18: 12 | K18: =IF(OR(H18="",J18="",J18=0),"",H18*J18) | L18: Home Depot | M18: Owens Corning / TVM sill seal 1x50 | O18: Confirmed | P18: medium | Q18: Air sealing | ДОДАНО: foam gasket між PT і slab | Ціна збір: 2026-05-28
A19: 15 | B19: Floor System | C19: Slab Prep | D19: Self-leveling Compound | E19: Allowance only — partial leveling | F19: bags | G19: 0 | H19: 4 | I19: 10 | J19: 35 | K19: =IF(OR(H19="",J19="",J19=0),"",H19*J19) | L19: Home Depot | M19: Mapei Planipatch 25 lb | O19: TBD | P19: medium | Q19: §33.22. Якщо full leveling req'd — qty зростає significantly | ДОДАНО: $35/bag, ~25 sf @ 1/8". Партіальне выравнивание | Ціна збір: 2026-05-28
A20: 16 | B20: Floor System | C20: Slab Prep | D20: Concrete Sealer / DryLok | E20: Optional moisture mitigation | F20: gal | G20: 0 | H20: 0 | I20: 5 | J20: 45 | K20: =IF(OR(H20="",J20="",J20=0),"",H20*J20) | L20: Home Depot | M20: DryLok concrete sealer 5 gal | O20: TBD | P20: medium | Q20: §33.23 verify moisture conditions. Baseline 0 | ДОДАНО: $45/gal, baseline qty=0 — only if §33.23 moisture issue | Ціна збір: 2026-05-28
A21: 17 | B21: Floor System | C21: Sealants | D21: Acoustical / Sound Caulk | E21: Floor joints sound dampening | F21: tubes | G21: 0 | H21: 3 | I21: 6 | J21: 12 | K21: =IF(OR(H21="",J21="",J21=0),"",H21*J21) | L21: Home Depot | M21: OSI ProSeries acoustical 28oz | O21: TBD | P21: medium | Q21: Optional | ДОДАНО: optional sound dampening | Ціна збір: 2026-05-28
A22: 18 | B22: Floor System | C22: Moisture Control | D22: Vapor Barrier Seam Tape | E22: Для overlap joints poly | F22: rolls | G22: 1 | H22: 1 | I22: 2 | J22: 15 | K22: =IF(OR(H22="",J22="",J22=0),"",H22*J22) | L22: Home Depot | M22: Stego seam tape / generic | O22: Confirmed | P22: medium | Q22: ДОДАНО (review): Stego/generic seam tape | ДОДАНО: для overlap vapor barrier joints | Ціна збір: 2026-05-28
A23: 19 | B23: Floor System | C23: Insulation (floor) | D23: Insulation Supports / Wire Supports | E23: Для утримання batt між joists | F23: pack | G23: 1 | H23: 2 | I23: 3 | J23: 9 | K23: =IF(OR(H23="",J23="",J23=0),"",H23*J23) | L23: Home Depot | M23: Owens Corning insul support wires | O23: Confirmed | P23: medium | Q23: ДОДАНО (review): тримає R-30 batt вгору | ДОДАНО: тримає R-30 batt між joists | Ціна збір: 2026-05-28
A24: 20 | B24: Floor System | C24: Hardware | D24: Composite / Plastic Shims | E24: Для вирівнювання sleepers/joists | F24: pack | G24: 1 | H24: 2 | I24: 3 | J24: 10 | K24: =IF(OR(H24="",J24="",J24=0),"",H24*J24) | L24: Home Depot | M24: Generic composite shims pack | O24: Confirmed | P24: medium | Q24: ДОДАНО (review) | ДОДАНО: для leveling sleepers/joists | Ціна збір: 2026-05-28
A25: 21 | B25: Floor System | C25: Hardware | D25: Structural Screws / Lag Screws | E25: SDS / Ledgerlok для rim-joist | F25: box | G25: 1 | H25: 1 | I25: 2 | J25: 25 | K25: =IF(OR(H25="",J25="",J25=0),"",H25*J25) | L25: Home Depot | M25: Simpson SDS / Ledgerlok box | O25: Confirmed | P25: medium | Q25: ДОДАНО (review): для connections without hangers | ДОДАНО: structural screws для rim-joist connections | Ціна збір: 2026-05-28
A26: 22 | B26: Floor System | C26: Access / Utility | D26: Small Access Panel allowance | E26: 12x12 PVC/металевий | F26: pcs | G26: 0 | H26: 1 | I26: 2 | J26: 22 | K26: =IF(OR(H26="",J26="",J26=0),"",H26*J26) | L26: Home Depot | M26: Generic 12x12 PVC access panel | O26: TBD | P26: medium | Q26: ДОДАНО (review): для доступу до MEP під підлогою | ДОДАНО: MEP access під raised floor | Ціна збір: 2026-05-28
C28: ПІДСУМОК ФАЗИ | K28: =SUM(K5:K26)

Sheet 04_Framing
A1: Phase 3 — Framing (§18)
A2: Left wall +21ft + interior partitions + headers
A4: # | B4: Phase | C4: Категорія | D4: Item / Material | E4: Spec / Опис | F4: Unit | G4: Qty (Low) | H4: Qty (Mid) | I4: Qty (High) | J4: Unit Price ($) | K4: Total ($) | L4: Source | M4: SKU / Model | N4: URL | O4: Status | P4: Confidence | Q4: Notes
A5: 1 | B5: Framing | C5: Studs/Plates | D5: 2x4 Studs (8 ft) | E5: SPF #2, wall framing | F5: pcs | G5: 75 | H5: 90 | I5: 110 | J5: 4.5 | K5: =IF(OR(H5="",J5="",J5=0),"",H5*J5) | L5: Home Depot | M5: 2x4 SPF #2 8ft | O5: Confirmed | P5: medium | Q5: 95-105 LF wall × 0.75 + 20-25% overhead. Включає left wall +21 LF + utility + openings | $4.50/each Bay Area premium. Menards ref $3.64 + ~25% CA | Ціна збір: 2026-05-28
A6: 2 | B6: Framing | C6: Studs/Plates | D6: 2x6 Studs (8 ft) — wet wall | E6: Для bathroom plumbing wall | F6: pcs | G6: 5 | H6: 8 | I6: 12 | J6: 7 | K6: =IF(OR(H6="",J6="",J6=0),"",H6*J6) | L6: Home Depot | M6: 2x6 SPF #2 8ft | O6: TBD | P6: medium | Q6: Depends on final bathroom/laundry layout — wet wall behind shower/vanity/laundry | Wet wall studs — final per bathroom layout | Ціна збір: 2026-05-28
A7: 3 | B7: Framing | C7: Studs/Plates | D7: Cripple / Jack / King Studs | E7: Allowance для openings | F7: pcs | G7: 15 | H7: 20 | I7: 28 | J7: 4.5 | K7: =IF(OR(H7="",J7="",J7=0),"",H7*J7) | L7: Home Depot | M7: 2x4 SPF #2 8ft (jack/king/cripple) | O7: Confirmed | P7: medium | Q7: Для 12+ framed openings | Same as standard 2x4, allowance для openings | Ціна збір: 2026-05-28
A8: 4 | B8: Framing | C8: Studs/Plates | D8: PT Bottom Plates | E8: Pressure-treated 2x4 — на subfloor edge | F8: linear ft | G8: 65 | H8: 75 | I8: 85 | J8: 0.95 | K8: =IF(OR(H8="",J8="",J8=0),"",H8*J8) | L8: Home Depot | M8: 2x4 PT | O8: Confirmed | P8: medium | Q8: PT де lumber contacts moisture-prone area | PT bottom plate per LF | Ціна збір: 2026-05-28
A9: 5 | B9: Framing | C9: Studs/Plates | D9: Top / Bottom Plates (regular) | E9: 2x4 SPF (double top + bottom) | F9: linear ft | G9: 130 | H9: 150 | I9: 170 | J9: 0.56 | K9: =IF(OR(H9="",J9="",J9=0),"",H9*J9) | L9: Home Depot | M9: 2x4 SPF #2 | O9: Confirmed | P9: medium | Q9: $0.56/LF ($4.50/8ft). Regular plate stock | Ціна збір: 2026-05-28
A10: 6 | B10: Framing | C10: Headers | D10: Standard Headers (2x6) | E10: Above standard openings (windows, doors) | F10: linear ft | G10: 20 | H10: 30 | I10: 40 | J10: 0.88 | K10: =IF(OR(H10="",J10="",J10=0),"",H10*J10) | L10: Home Depot | M10: 2x6 SPF #2 | O10: Confirmed | P10: medium | Q10: Structural sizing — final per engineer | $0.88/LF ($7/8ft). Standard window/door headers | Ціна збір: 2026-05-28
A11: 7 | B11: Framing | C11: Headers | D11: Engineered LVL Header | E11: Для French door (~6ft) + folding 8ft | F11: linear ft | G11: 12 | H11: 16 | I11: 20 | J11: 6 | K11: =IF(OR(H11="",J11="",J11=0),"",H11*J11) | L11: Home Depot / specialty | M11: LVL 1.75x7.25 engineered | N11: https://www.homedepot.com/b/Lumber-Composites-Engineered-Wood-Products/LVL/N-5yc1vZcb73Z1z0xv6e | O11: TBD | P11: medium | Q11: Final size depends on opening width, load above, existing roof/wall structure | LVL header для French door + folding 8ft. Final size per engineer | Ціна збір: 2026-05-28
A12: 8 | B12: Framing | C12: Blocking | D12: Blocking Lumber (2x4) | E12: 12 типів blocking per §18.3 | F12: linear ft | G12: 40 | H12: 60 | I12: 80 | J12: 0.56 | K12: =IF(OR(H12="",J12="",J12=0),"",H12*J12) | L12: Home Depot | M12: 2x4 SPF #2 blocking | O12: Confirmed | P12: medium | Q12: Cabinets/vanity/W-D/WH straps/TV/doors/towels/shelves... | Same as plates stock | Ціна збір: 2026-05-28
A13: 9 | B13: Framing | C13: Backing | D13: Drywall Backing / Nailers | E13: Inside corners + T-intersections | F13: linear ft | G13: 20 | H13: 30 | I13: 40 | J13: 0.56 | K13: =IF(OR(H13="",J13="",J13=0),"",H13*J13) | L13: Home Depot | M13: 2x4 SPF #2 nailer | O13: Confirmed | P13: medium | Q13: Для drywall attachment points | Drywall backing per LF | Ціна збір: 2026-05-28
A14: 10 | B14: Framing | C14: Hardware | D14: Simpson Connectors / Brackets | E14: L, T, A35 mixed | F14: pcs | G14: 20 | H14: 30 | I14: 40 | J14: 3 | K14: =IF(OR(H14="",J14="",J14=0),"",H14*J14) | L14: Home Depot | M14: Simpson mixed pack | O14: TBD | P14: medium | Q14: L, T, A35 mixed connectors | Ціна збір: 2026-05-28
A15: 11 | B15: Framing | C15: Hardware | D15: Hold-downs Simpson HDU2 allowance | E15: Allowance — TBD per structural engineer | F15: pcs | G15: 0 | H15: 4 | I15: 6 | J15: 30 | K15: =IF(OR(H15="",J15="",J15=0),"",H15*J15) | L15: Home Depot | M15: Simpson HDU2-SDS2.5 | O15: TBD | P15: medium | Q15: §33.25 — verify shear wall requirement | Hold-down. $25-35 each. Allowance, TBD per engineer | Ціна збір: 2026-05-28
A16: 12 | B16: Framing | C16: Hardware | D16: Metal Protection Plates | E16: Stud guards 1.5x5 за trades | F16: pcs | G16: 20 | H16: 30 | I16: 40 | J16: 0.5 | K16: =IF(OR(H16="",J16="",J16=0),"",H16*J16) | L16: Home Depot | M16: Generic 16-gauge stud guard | O16: TBD | P16: medium | Q16: Nail protection plate for trades | Ціна збір: 2026-05-28
A17: 13 | B17: Framing | C17: Hardware | D17: Composite / Wood Shims | E17: Для вирівнювання walls/openings | F17: pack | G17: 1 | H17: 2 | I17: 4 | J17: 10 | K17: =IF(OR(H17="",J17="",J17=0),"",H17*J17) | L17: Home Depot | M17: Generic composite/wood shims pack | O17: Confirmed | P17: medium | Q17: ДОДАНО (review): wall plumbing і opening setting | ДОДАНО (review): для wall plumbing і opening setting | Ціна збір: 2026-05-28
A18: 14 | B18: Framing | C18: Anchors | D18: Anchor Bolts 1/2 × 10 galvanized | E18: Для sill/perimeter/structural conditions | F18: pcs | G18: 12 | H18: 20 | I18: 30 | J18: 1 | K18: =IF(OR(H18="",J18="",J18=0),"",H18*J18) | L18: Home Depot | M18: Simpson / generic 1/2 × 10 galv | O18: TBD | P18: medium | Q18: Verify use: anchor bolts для sill/perimeter/structural; interior partitions on subfloor можуть use screws/nails | Anchor bolt — verify use for sill/perimeter only | Ціна збір: 2026-05-28
A19: 15 | B19: Framing | C19: Fasteners | D19: Framing Nails / Screws | E19: 16d collated, 3-1/4" mixed | F19: lb | G19: 10 | H19: 15 | I19: 20 | J19: 5 | K19: =IF(OR(H19="",J19="",J19=0),"",H19*J19) | L19: Home Depot | M19: Generic 16d collated framing nails | O19: Confirmed | P19: medium | Q19: $5/lb pneumatic collated | Ціна збір: 2026-05-28
A20: 16 | B20: Framing | C20: Fasteners | D20: Structural Screws / Header Fasteners | E20: SDS/Strong-Drive для LVL & headers | F20: box | G20: 1 | H20: 1 | I20: 2 | J20: 30 | K20: =IF(OR(H20="",J20="",J20=0),"",H20*J20) | L20: Home Depot | M20: Simpson SDS / Strong-Drive box | O20: Confirmed | P20: medium | Q20: ДОДАНО (review): для LVL/header/opening connections | ДОДАНО (review): structural screws для LVL/header | Ціна збір: 2026-05-28
A21: 17 | B21: Framing | C21: Sheathing | D21: OSB / Plywood Sheathing allowance | E21: Garage opening close-up / shear panels | F21: sheets | G21: 1 | H21: 3 | I21: 5 | J21: 30 | K21: =IF(OR(H21="",J21="",J21=0),"",H21*J21) | L21: Home Depot | M21: 3/4" OSB 4x8 sheet | O21: TBD | P21: medium | Q21: ДОДАНО (review): garage door opening closure / shear wall / backing | ДОДАНО (review): garage opening close-up + shear allowance | Ціна збір: 2026-05-28
A22: 18 | B22: Framing | C22: Adhesives | D22: Construction Adhesive (framing) | E22: PL Premium plate-to-floor | F22: tubes | G22: 3 | H22: 5 | I22: 7 | J22: 10 | K22: =IF(OR(H22="",J22="",J22=0),"",H22*J22) | L22: Home Depot | M22: Loctite PL Premium 10oz | O22: Confirmed | P22: medium | Q22: Plate-to-floor adhesive | Ціна збір: 2026-05-28
A23: 19 | B23: Framing | C23: Sealants | D23: Acoustical Sealant | E23: Bedroom/bathroom partitions sound | F23: tubes | G23: 2 | H23: 4 | I23: 6 | J23: 10 | K23: =IF(OR(H23="",J23="",J23=0),"",H23*J23) | L23: Home Depot | M23: OSI ProSeries acoustical 28oz | O23: TBD | P23: medium | Q23: Sound dampening per partition | Sound dampening для bedroom/bathroom partitions | Ціна збір: 2026-05-28
... A27: 23 | B27: Framing | C27: Bracing | D27: Temporary Bracing Lumber | E27: Для setting walls during framing | F27: linear ft | G27: 15 | H27: 25 | I27: 40 | J27: 0.56 | K27: =IF(OR(H27="",J27="",J27=0),"",H27*J27) | L27: Home Depot | M27: 2x4 SPF temp bracing (reusable) | O27: TBD | P27: medium | Q27: ДОДАНО (review): можна reuse після | ДОДАНО (review): temporary bracing, можна reuse | Ціна збір: 2026-05-28
C29: ПІДСУМОК ФАЗИ | K29: =SUM(K5:K27)

Sheet 05_Doors_Windows
A1: Phase 4 — Doors & Windows / Openings (§25)
A2: 3 windows + 5 doors + folding system
A4: # | B4: Phase | C4: Категорія | D4: Item / Material | E4: Spec / Опис | F4: Unit | G4: Qty (Low) | H4: Qty (Mid) | I4: Qty (High) | J4: Unit Price ($) | K4: Total ($) | L4: Source | M4: SKU / Model | N4: URL | O4: Status | P4: Confidence | Q4: Notes
A5: 1 | B5: Openings | C5: Windows | D5: Bathroom Window | E5: Vinyl ES, ~24×36 (TBD §33.12) | F5: pcs | G5: 1 | H5: 1 | I5: 1 | J5: 180 | K5: =IF(OR(H5="",J5="",J5=0),"",H5*J5) | L5: Home Depot | M5: JELD-WEN V-4500 24×36 white | N5: https://www.homedepot.com/b/Doors-Windows-Windows-Single-Hung-Windows/Energy-Star/N-5yc1vZas73Z1z1wgir | O5: TBD | P5: medium | Q5: Field-verify size | Bathroom window, smaller size ~$150-220 | Ціна збір: 2026-05-28
A6: 2 | B6: Openings | C6: Windows | D6: Kitchen Window | E6: Vinyl ES, ~36×48 (TBD) | F6: pcs | G6: 1 | H6: 1 | I6: 1 | J6: 300 | K6: =IF(OR(H6="",J6="",J6=0),"",H6*J6) | L6: Home Depot | M6: JELD-WEN V-4500 36×48 white | N6: https://www.homedepot.com/p/JELD-WEN-36-in-x-48-in-V-4500-Series-White-Single-Hung-Vinyl-Window-with-Fiberglass-Mesh-Screen-THDJW143900466/304848395 | O6: TBD | P6: medium | Q6: Field-verify size | Kitchen window, standard size. HD retail $250-350 | Ціна збір: 2026-05-28
A7: 3 | B7: Openings | C7: Windows | D7: Living Room Window | E7: Vinyl ES, ~36×60 (TBD) | F7: pcs | G7: 1 | H7: 1 | I7: 1 | J7: 400 | K7: =IF(OR(H7="",J7="",J7=0),"",H7*J7) | L7: Home Depot | M7: JELD-WEN V-4500 36×60 white | O7: TBD | P7: medium | Q7: Field-verify size | Living window, larger size. Premium V-4500 dealer $675 ref | Ціна збір: 2026-05-28
A8: 4 | B8: Openings | C8: Exterior Doors | D8: Main Entry Door | E8: Prehung steel 36×80 insulated | F8: pcs | G8: 1 | H8: 1 | I8: 1 | J8: 400 | K8: =IF(OR(H8="",J8="",J8=0),"",H8*J8) | L8: Home Depot | M8: Masonite Premium 6-panel 36×80 | N8: https://www.homedepot.com/p/Masonite-36-in-x-80-in-Premium-6-Panel-Right-Hand-Inswing-Primed-Steel-Prehung-Front-Exterior-Door-with-Brickmold-27105/100053184 | O8: TBD | P8: medium | Q8: Field-verify size (§33.14) | Prehung steel insulated з brickmold. $300-500 range | Ціна збір: 2026-05-28
A9: 5 | B9: Openings | C9: Exterior Doors | D9: Backyard French Door | E9: Fiberglass prehung 60×80, glazed | F9: pcs | G9: 1 | H9: 1 | I9: 1 | J9: 1500 | K9: =IF(OR(H9="",J9="",J9=0),"",H9*J9) | L9: Special Order | M9: Masonite/ThermaTru fiberglass 60×80 patio | N9: https://www.homedepot.com/b/Doors-Windows-Exterior-Doors-Patio-Doors/Masonite/60-x-80/French-Patio-Door/N-5yc1vZarqnZyqZ1z0rbkpZ1z0v1y3 | O9: Confirmed | P9: medium | Q9: Special Order. Lead 4-8 weeks. Delivery not included. Field-verify (§33.13) | Special Order. Fiberglass French. $1200-1800 range | Ціна збір: 2026-05-28
A10: 6 | B10: Openings | C10: Interior Doors | D10: Bathroom Door | E10: Prehung hollow core 30×80 | F10: pcs | G10: 1 | H10: 1 | I10: 1 | J10: 110 | K10: =IF(OR(H10="",J10="",J10=0),"",H10*J10) | L10: Home Depot | M10: Masonite hollow core 30×80 | O10: TBD | P10: medium | Q10: Verify if privacy lockset included; otherwise add separately | Prehung з privacy lock | Ціна збір: 2026-05-28
A11: 7 | B11: Openings | C11: Interior Doors | D11: Utility Closet Door | E11: 24×80 louvered bifold або slab | F11: pcs | G11: 1 | H11: 1 | I11: 1 | J11: 80 | K11: =IF(OR(H11="",J11="",J11=0),"",H11*J11) | L11: Home Depot | M11: Masonite louvered prehung 24×80 | O11: TBD | P11: medium | Q11: Final type TBD based on clearance | Або bifold louvered | Ціна збір: 2026-05-28
A12: 8 | B12: Openings | C12: Specialty Systems | D12: Closet Sliding Door System | E12: Bypass 6 ft, 2-panel | F12: system | G12: 1 | H12: 1 | I12: 1 | J12: 250 | K12: =IF(OR(H12="",J12="",J12=0),"",H12*J12) | L12: Home Depot / IKEA | M12: Home Depot bypass system 6ft | O12: TBD | P12: medium | Q12: Field-verify (§33.16) | 2-panel bypass sliding closet system | Ціна збір: 2026-05-28
A13: 9 | B13: Openings | C13: Specialty Systems | D13: Folding / Panel Door System 8 ft | E13: INTERIOR partition між bedroom і living (per §17.4) | F13: system | G13: 1 | H13: 1 | I13: 1 | J13: 3000 | K13: =IF(OR(H13="",J13="",J13=0),"",H13*J13) | L13: Special Order | M13: Mid-tier folding partition system 8ft | N13: https://homeguide.com/costs/folding-accordion-patio-doors-cost | O13: Confirmed | P13: low | Q13: Special Order INTERIOR. High variability — final cost залежить від material: accordion / bifold / glass folding / wood / track / sound level. Field-verify (§33.15) | Special Order INTERIOR partition. Variability $1500 (basic accordion) - $6000 (LaCantina-style interior). Mid $3000 для quality glass/wood folding | Ціна збір: 2026-05-28
A14: 10 | B14: Openings | C14: Weatherproofing | D14: Flashing Tape | E14: Windows + doors butyl/peel-stick | F14: rolls | G14: 2 | H14: 3 | I14: 4 | J14: 25 | K14: =IF(OR(H14="",J14="",J14=0),"",H14*J14) | L14: Home Depot | M14: Tyvek FlexWrap / 3M flashing tape | O14: Confirmed | P14: medium | Q14: Per roll | Ціна збір: 2026-05-28
A15: 11 | B15: Openings | C15: Weatherproofing | D15: Sill Pans | E15: Windows + 2 exterior doors | F15: pcs | G15: 4 | H15: 5 | I15: 5 | J15: 30 | K15: =IF(OR(H15="",J15="",J15=0),"",H15*J15) | L15: Home Depot | M15: Generic vinyl sill pan | O15: Confirmed | P15: medium | Q15: Підвищено Mid: 3 windows + entry + French = 5 openings | Per window | Ціна збір: 2026-05-28
A16: 12 | B16: Openings | C16: Weatherproofing | D16: Exterior Sealant | E16: Polyurethane caulk | F16: tubes | G16: 4 | H16: 6 | I16: 8 | J16: 8 | K16: =IF(OR(H16="",J16="",J16=0),"",H16*J16) | L16: Home Depot | M16: Sika / OSI polyurethane sealant | O16: Confirmed | P16: medium | Q16: Caulk tube | Ціна збір: 2026-05-28
A17: 13 | B17: Openings | C17: Weatherproofing | D17: Low-expansion Foam | E17: Для perimeter gaps | F17: cans | G17: 3 | H17: 4 | I17: 6 | J17: 7 | K17: =IF(OR(H17="",J17="",J17=0),"",H17*J17) | L17: Home Depot | M17: Great Stuff window/door foam | O17: Confirmed | P17: medium | Q17: Low-expansion cans | Ціна збір: 2026-05-28
A18: 14 | B18: Openings | C18: Trim | D18: Interior Casing | E18: За дверима/вікнами, 7+ openings | F18: linear ft | G18: 80 | H18: 120 | I18: 160 | J18: 0.8 | K18: =IF(OR(H18="",J18="",J18=0),"",H18*J18) | L18: Home Depot | M18: MDF / pine interior casing | O18: Confirmed | P18: medium | Q18: Per LF | Ціна збір: 2026-05-28
A19: 15 | B19: Openings | C19: Trim | D19: Exterior Trim | E19: Standard exterior molding | F19: linear ft | G19: 40 | H19: 60 | I19: 80 | J19: 1.2 | K19: =IF(OR(H19="",J19="",J19=0),"",H19*J19) | L19: Home Depot | M19: Pine/PVC exterior trim | O19: Confirmed | P19: medium | Q19: Per LF | Ціна збір: 2026-05-28
A20: 16 | B20: Openings | C20: Hardware | D20: Entry Door Lockset + Deadbolt | E20: Для main entry only | F20: set | G20: 1 | H20: 1 | I20: 1 | J20: 200 | K20: =IF(OR(H20="",J20="",J20=0),"",H20*J20) | L20: Home Depot | M20: Schlage/Kwikset Entry lockset+deadbolt | O20: Confirmed | P20: medium | Q20: Schlage/Kwikset deadbolt + handle | Entry ONLY (French door has separate multi-point in row 24) | Ціна збір: 2026-05-28
A21: 17 | B21: Openings | C21: Windows | D21: Window Screens | E21: Fiberglass mesh | F21: pcs | G21: 3 | H21: 3 | I21: 3 | J21: 40 | K21: =IF(OR(H21="",J21="",J21=0),"",H21*J21) | L21: Home Depot | M21: Generic vinyl window screen | O21: Confirmed | P21: medium | Q21: May be included with selected windows; keep as allowance until product selected | Per window. May be included з window selection | Ціна збір: 2026-05-28
A22: 18 | B22: Openings | C22: Windows | D22: Window Sills / Stools | E22: Interior trim під window | F22: pcs | G22: 3 | H22: 3 | I22: 3 | J22: 30 | K22: =IF(OR(H22="",J22="",J22=0),"",H22*J22) | L22: Home Depot | M22: Pine/MDF window sill stool | O22: Confirmed | P22: medium | Q22: Окремо від generic casing | Per window | Ціна збір: 2026-05-28
A23: 19 | B23: Openings | C23: Trim | D23: Brick Mold / Exterior Casing | E23: Для exterior openings | F23: linear ft | G23: 40 | H23: 60 | I23: 80 | J23: 1.5 | K23: =IF(OR(H23="",J23="",J23=0),"",H23*J23) | L23: Home Depot | M23: Pine brick mold exterior casing | O23: Confirmed | P23: medium | Q23: Окремо від generic exterior trim | Per LF, surrounds exterior openings | Ціна збір: 2026-05-28
A24: 20 | B24: Openings | C24: Hardware | D24: French Door Hardware | E24: Multi-point lock + handles | F24: set | G24: 1 | H24: 1 | I24: 1 | J24: 300 | K24: =IF(OR(H24="",J24="",J24=0),"",H24*J24) | L24: Special Order | M24: Multi-point lock French door set | O24: TBD | P24: medium | Q24: Специфічно для French door (§25.3) | 3-point lock + handles для French door | Ціна збір: 2026-05-28
A25: 21 | B25: Openings | C25: Hardware | D25: Weatherstripping | E25: Kit для exterior doors | F25: set | G25: 2 | H25: 2 | I25: 2 | J25: 25 | K25: =IF(OR(H25="",J25="",J25=0),"",H25*J25) | L25: Home Depot | M25: Generic kit weatherstripping | O25: Confirmed | P25: medium | Q25: Entry + French | Per exterior door | Ціна збір: 2026-05-28
... A34: 30 | B34: Openings | C34: Finish | D34: Interior Paintable Caulk | E34: Для casing/trim joints | F34: tubes | G34: 6 | H34: 8 | I34: 10 | J34: 5 | K34: =IF(OR(H34="",J34="",J34=0),"",H34*J34) | L34: Home Depot | M34: DAP Alex Plus paintable caulk | O34: Confirmed | P34: medium | Q34: ДОДАНО (review) | ДОДАНО (review): casing/trim joints | Ціна збір: 2026-05-28
C36: ПІДСУМОК ФАЗИ | K36: =SUM(K5:K34)

Sheet 06_Plumbing_Roughin
A1: Phase 5 — Plumbing Rough-in (§20)
A2: PEX supply + ABS/PVC drain + vent + fittings
A4: # | B4: Phase | C4: Категорія | D4: Item / Material | E4: Spec / Опис | F4: Unit | G4: Qty (Low) | H4: Qty (Mid) | I4: Qty (High) | J4: Unit Price ($) | K4: Total ($) | L4: Source | M4: SKU / Model | N4: URL | O4: Status | P4: Confidence | Q4: Notes
A5: 1 | B5: Plumbing R-I | C5: Supply | D5: PEX Hot/Cold Pipe 1/2" | E5: PEX-B coil 100 ft | F5: linear ft | G5: 200 | H5: 230 | I5: 260 | J5: 0.35 | K5: =IF(OR(H5="",J5="",J5=0),"",H5*J5) | L5: Home Depot | M5: SharkBite/Apollo PEX-B 1/2" 100ft | N5: https://www.homedepot.com/p/SharkBite-1-2-in-x-100-ft-Coil-Red-PEX-B-Pipe-U860R100/202033011 | O5: Confirmed | P5: high | Q5: $0.35/LF ($35/100ft coil) | Ціна збір: 2026-05-28
A6: 2 | B6: Plumbing R-I | C6: Supply | D6: PEX Hot/Cold Pipe 3/4" | E6: Main runs PEX-B | F6: linear ft | G6: 100 | H6: 120 | I6: 140 | J6: 0.7 | K6: =IF(OR(H6="",J6="",J6=0),"",H6*J6) | L6: Home Depot | M6: SharkBite PEX-B 3/4" 100ft | O6: Confirmed | P6: medium | Q6: $0.70/LF ($70/100ft coil) | Ціна збір: 2026-05-28
A7: 3 | B7: Plumbing R-I | C7: Supply | D7: PEX Fittings (assortment) | E7: Elbows, tees, couplings, crimps | F7: pack | G7: 2 | H7: 3 | I7: 4 | J7: 25 | K7: =IF(OR(H7="",J7="",J7=0),"",H7*J7) | L7: Home Depot | M7: Apollo/SharkBite PEX fittings pack | O7: Confirmed | P7: medium | Q7: Assortment: elbows, tees, couplings, crimp rings | Ціна збір: 2026-05-28
A8: 4 | B8: Plumbing R-I | C8: Supply | D8: Shut-off Valves (1/4-turn) | E8: Interior fixtures angle stops | F8: pcs | G8: 16 | H8: 19 | I8: 22 | J8: 7 | K8: =IF(OR(H8="",J8="",J8=0),"",H8*J8) | L8: Home Depot | M8: Apollo PEX-B 1/2" angle stop quarter-turn | N8: https://www.homedepot.com/p/Apollo-1-2-in-Chrome-Plated-Brass-PEX-B-Barb-x-1-4-in-Compression-Quarter-Turn-Angle-Stop-Valve-APXVA1214C/305455212 | O8: Confirmed | P8: high | Q8: Per valve, brass chrome-plated | Ціна збір: 2026-05-28
A9: 5 | B9: Plumbing R-I | C9: Drain | D9: ABS/PVC Drain Pipe 1.5" | E9: Sink/vanity drains | F9: linear ft | G9: 30 | H9: 40 | I9: 50 | J9: 0.85 | K9: =IF(OR(H9="",J9="",J9=0),"",H9*J9) | L9: Home Depot | M9: Charlotte/IPEX ABS DWV 1.5" | O9: Confirmed | P9: medium | Q9: Per LF, DWV grade | Ціна збір: 2026-05-28
A10: 6 | B10: Plumbing R-I | C10: Drain | D10: ABS/PVC Drain Pipe 2" | E10: Shower/laundry drains | F10: linear ft | G10: 40 | H10: 60 | I10: 80 | J10: 1.1 | K10: =IF(OR(H10="",J10="",J10=0),"",H10*J10) | L10: Home Depot | M10: Charlotte/IPEX ABS DWV 2" | O10: Confirmed | P10: medium | Q10: Per LF | Ціна збір: 2026-05-28
A11: 7 | B11: Plumbing R-I | C11: Drain | D11: ABS/PVC Drain Pipe 3" | E11: Branch + toilet drain | F11: linear ft | G11: 20 | H11: 30 | I11: 40 | J11: 1.8 | K11: =IF(OR(H11="",J11="",J11=0),"",H11*J11) | L11: Home Depot | M11: Charlotte/IPEX ABS DWV 3" | O11: Confirmed | P11: medium | Q11: Per LF, for toilet drain | Ціна збір: 2026-05-28
A12: 8 | B12: Plumbing R-I | C12: Drain | D12: ABS/PVC Drain Pipe 4" | E12: Main building drain | F12: linear ft | G12: 15 | H12: 20 | I12: 25 | J12: 3 | K12: =IF(OR(H12="",J12="",J12=0),"",H12*J12) | L12: Home Depot | M12: IPEX ABS DWV 4" 10ft | N12: https://www.homedepot.com/p/IPEX-4-in-x-10-ft-ABS-DWV-Cell-Core-Pipe-179687/309282462 | O12: Confirmed | P12: medium | Q12: $3/LF ($30/10ft piece). Cell core ABS | Ціна збір: 2026-05-28
A13: 9 | B13: Plumbing R-I | C13: Vent | D13: Vent Pipe | E13: ABS/PVC 1.5-2" | F13: linear ft | G13: 20 | H13: 30 | I13: 40 | J13: 0.95 | K13: =IF(OR(H13="",J13="",J13=0),"",H13*J13) | L13: Home Depot | M13: Charlotte ABS DWV 2" vent | O13: Confirmed | P13: medium | Q13: Per LF | Ціна збір: 2026-05-28
A14: 10 | B14: Plumbing R-I | C14: Fittings | D14: P-traps | E14: Sinks, shower, washer | F14: pcs | G14: 4 | H14: 4 | I14: 5 | J14: 8 | K14: =IF(OR(H14="",J14="",J14=0),"",H14*J14) | L14: Home Depot | M14: Oatey/generic P-trap kit | O14: Confirmed | P14: medium | Q14: 1.5" or 2" P-trap | Ціна збір: 2026-05-28
A15: 11 | B15: Plumbing R-I | C15: Fittings | D15: Cleanouts (interior) | E15: Body + plug | F15: pcs | G15: 2 | H15: 2 | I15: 3 | J15: 20 | K15: =IF(OR(H15="",J15="",J15=0),"",H15*J15) | L15: Home Depot | M15: Charlotte 4" ABS cleanout | O15: Confirmed | P15: medium | Q15: Body + threaded plug | Ціна збір: 2026-05-28
A16: 12 | B16: Plumbing R-I | C16: Fittings | D16: Pipe Clamps / Hangers | E16: ABS strut/strap pack | F16: pack | G16: 2 | H16: 3 | I16: 4 | J16: 15 | K16: =IF(OR(H16="",J16="",J16=0),"",H16*J16) | L16: Home Depot | M16: Sioux Chief strut/strap pack | O16: Confirmed | P16: medium | Q16: Per pack — pipe hangers/clamps | Ціна збір: 2026-05-28
A17: 13 | B17: Plumbing R-I | C17: Fittings | D17: Primer / Cement ABS-PVC | E17: Solvent weld | F17: cans | G17: 2 | H17: 3 | I17: 4 | J17: 12 | K17: =IF(OR(H17="",J17="",J17=0),"",H17*J17) | L17: Home Depot | M17: Oatey ABS primer + cement combo | O17: Confirmed | P17: medium | Q17: Per can | Ціна збір: 2026-05-28
A18: 14 | B18: Plumbing R-I | C18: Misc | D18: Washer Outlet Box | E18: Recessed, hot/cold + drain | F18: pcs | G18: 1 | H18: 1 | I18: 1 | J18: 40 | K18: =IF(OR(H18="",J18="",J18=0),"",H18*J18) | L18: Home Depot | M18: Sioux Chief / LSP washer outlet box | O18: Confirmed | P18: medium | Q18: Recessed hot/cold + drain box | Ціна збір: 2026-05-28
A19: 15 | B19: Plumbing R-I | C19: Misc | D19: Toilet Flange | E19: PVC/ABS w/ ring | F19: pcs | G19: 1 | H19: 1 | I19: 1 | J19: 12 | K19: =IF(OR(H19="",J19="",J19=0),"",H19*J19) | L19: Home Depot | M19: Oatey ABS toilet flange w/ ring | O19: Confirmed | P19: medium | Q19: Standard 3" or 4" | Ціна збір: 2026-05-28
A20: 16 | B20: Plumbing R-I | C20: Misc | D20: Water Heater Connection Kit | E20: Flex lines + fittings | F20: set | G20: 1 | H20: 1 | I20: 1 | J20: 50 | K20: =IF(OR(H20="",J20="",J20=0),"",H20*J20) | L20: Home Depot | M20: WH connection kit (flex lines + dielectric) | O20: TBD | P20: medium | Q20: Coordinate w/ Phase 15 Water Heater | Coordinate Phase 15 WH | Ціна збір: 2026-05-28
A21: 17 | B21: Plumbing R-I | C21: Misc | D21: Pipe Insulation (interior) | E21: Hot lines foam 1/2-3/4" | F21: linear ft | G21: 30 | H21: 50 | I21: 70 | J21: 0.5 | K21: =IF(OR(H21="",J21="",J21=0),"",H21*J21) | L21: Home Depot | M21: Armaflex foam 1/2"-3/4" | O21: Confirmed | P21: medium | Q21: Hot line insulation per LF | Ціна збір: 2026-05-28
A22: 18 | B22: Plumbing R-I | C22: Fittings | D22: ABS/PVC DWV Fittings | E22: Elbows, couplings, tees, sanitary tees, wyes, reducers | F22: pack | G22: 2 | H22: 3 | I22: 5 | J22: 50 | K22: =IF(OR(H22="",J22="",J22=0),"",H22*J22) | L22: Home Depot | M22: ABS DWV fittings assortment pack | O22: Confirmed | P22: medium | Q22: ДОДАНО (§20.3): drain fittings okремо | ДОДАНО: elbows, tees, sanitary tees, wyes, reducers. $50/pack | Ціна збір: 2026-05-28
A23: 19 | B23: Plumbing R-I | C23: Misc | D23: Washer Standpipe | E23: 2" 18-30" tall | F23: pcs | G23: 1 | H23: 1 | I23: 1 | J23: 15 | K23: =IF(OR(H23="",J23="",J23=0),"",H23*J23) | L23: Home Depot | M23: 2" PVC/ABS washer standpipe | O23: Confirmed | P23: medium | Q23: ДОДАНО (§20.3): окремо від outlet box | ДОДАНО (§20.3) | Ціна збір: 2026-05-28
A24: 20 | B24: Plumbing R-I | C24: Misc | D24: Dishwasher Connection Kit | E24: Tee + brass elbow + 3/8 supply | F24: set | G24: 1 | H24: 1 | I24: 1 | J24: 25 | K24: =IF(OR(H24="",J24="",J24=0),"",H24*J24) | L24: Home Depot | M24: Generic dishwasher install kit | O24: Confirmed | P24: medium | Q24: ДОДАНО (§20.3) | ДОДАНО: tee + elbow + supply line | Ціна збір: 2026-05-28
... A38: 34 | B38: Plumbing R-I | C38: Misc | D38: Water Heater Pan + Drain (cross-ref Phase 15) | E38: Залишено в Phase 15 — не дублюйте | F38: set | G38: 0 | H38: 0 | I38: 0 | J38: 0 | K38: =IF(OR(H38="",J38="",J38=0),"",H38*J38) | L38: Home Depot | M38: — | O38: Confirmed | P38: medium | Q38: ДОДАНО (review): cross-reference. Cost у Phase 15 Water Heater | ДОДАНО (review): cross-ref Phase 15. Не дублювати — qty 0 | Ціна збір: 2026-05-28
C40: ПІДСУМОК ФАЗИ | K40: =SUM(K5:K38)

Sheet 07_Electrical_Roughin
A1: Phase 6 — Electrical Rough-in (§21)
A2: ADU subpanel + Romex + boxes + devices + light fixtures
A4: # | B4: Phase | C4: Категорія | D4: Item / Material | E4: Spec / Опис | F4: Unit | G4: Qty (Low) | H4: Qty (Mid) | I4: Qty (High) | J4: Unit Price ($) | K4: Total ($) | L4: Source | M4: SKU / Model | N4: URL | O4: Status | P4: Confidence | Q4: Notes
A5: 1 | B5: Electrical R-I | C5: Panel | D5: ADU Subpanel 100A | E5: Square D QO 20-space allowance | F5: pcs | G5: 1 | H5: 1 | I5: 1 | J5: 139 | K5: =IF(OR(H5="",J5="",J5=0),"",H5*J5) | L5: Home Depot | M5: Square D QO120M100C 100A 20-space | N5: https://www.homedepot.com/p/Square-D-QO-100-Amp-20-Space-20-Circuit-Indoor-Main-Breaker-Load-Center-with-Cover-QO120M100C/100195842 | O5: Confirmed | P5: high | Q5: Final amperage by load calculation (§33.21) | $139 retail (promo $114 з HD card). 100A indoor main breaker load center | Ціна збір: 2026-05-28
A6: 2 | B6: Electrical R-I | C6: Panel | D6: Standard Breakers (non-AFCI) | E6: Single/double pole для 240V appliances + non-AFCI circuits | F6: set | G6: 1 | H6: 1 | I6: 1 | J6: 130 | K6: =IF(OR(H6="",J6="",J6=0),"",H6*J6) | L6: Home Depot | M6: Square D QO standard breakers (non-AFCI only) | O6: Confirmed | P6: medium | Q6: Тільки для circuits де AFCI не required: range, WH, mini-split, dryer, bathroom GFCI | Тільки для non-AFCI circuits: 240V (range/WH/HVAC) + bath GFCI + non-AFCI. AFCI breakers в r26 окремо | Ціна збір: 2026-05-28
A7: 3 | B7: Electrical R-I | C7: Wire | D7: Romex 12/2 (20A circuits) | E7: 250ft / 1000ft rolls NM-B | F7: linear ft | G7: 500 | H7: 600 | I7: 700 | J7: 0.65 | K7: =IF(OR(H7="",J7="",J7=0),"",H7*J7) | L7: Home Depot | M7: Southwire 12/2 NM-B Romex SIMpull | N7: https://www.homedepot.com/p/Southwire-250-ft-12-2-Solid-Romex-SIMpull-CU-NM-B-W-G-Wire-28828269/202019375 | O7: Confirmed | P7: medium | Q7: $0.65/LF (~$163 per 250ft roll). Bay Area premium | Ціна збір: 2026-05-28
A8: 4 | B8: Electrical R-I | C8: Wire | D8: Romex 14/2 (15A circuits) | E8: Lighting general NM-B | F8: linear ft | G8: 300 | H8: 400 | I8: 500 | J8: 0.45 | K8: =IF(OR(H8="",J8="",J8=0),"",H8*J8) | L8: Home Depot | M8: Southwire 14/2 NM-B Romex | O8: Confirmed | P8: medium | Q8: $0.45/LF lighter gauge | Ціна збір: 2026-05-28
A9: 5 | B9: Electrical R-I | C9: Wire | D9: 240V Cable (range/WH/HVAC) | E9: 8/3 (range) + 10/2 (WH, mini-split) | F9: linear ft | G9: 80 | H9: 120 | I9: 160 | J9: 2.5 | K9: =IF(OR(H9="",J9="",J9=0),"",H9*J9) | L9: Home Depot | M9: Southwire 8/3 + 10/2 NM-B (240V) | O9: Confirmed | P9: medium | Q9: Range 40A, WH 30A, mini-split 30A | Average $2.50/LF mixed. 8/3 для range, 10/2 для WH/HVAC | Ціна збір: 2026-05-28
A10: 6 | B10: Electrical R-I | C10: Wire | D10: Interior Conduit (where req'd) | E10: EMT/PVC 1/2-3/4" | F10: linear ft | G10: 20 | H10: 40 | I10: 60 | J10: 0.8 | K10: =IF(OR(H10="",J10="",J10=0),"",H10*J10) | L10: Home Depot | M10: Allied EMT / Cantex PVC conduit 1/2-3/4" | O10: TBD | P10: medium | Q10: Interior conduit per LF | Ціна збір: 2026-05-28
A11: 7 | B11: Electrical R-I | C11: Devices | D11: Electrical Boxes (mixed) | E11: 1-gang, 2-gang, ceiling, old-work | F11: pcs | G11: 55 | H11: 62 | I11: 70 | J11: 1.75 | K11: =IF(OR(H11="",J11="",J11=0),"",H11*J11) | L11: Home Depot | M11: Carlon plastic boxes mixed | O11: Confirmed | P11: medium | Q11: Average $1.75/box: 1g $1.50, 2g $2.50, ceiling $3, old-work $3.50, WP $12 | Ціна збір: 2026-05-28
A12: 8 | B12: Electrical R-I | C12: Devices | D12: Standard Outlets TR-rated | E12: Tamper-resistant 15A/20A | F12: pcs | G12: 25 | H12: 30 | I12: 35 | J12: 2.5 | K12: =IF(OR(H12="",J12="",J12=0),"",H12*J12) | L12: Home Depot | M12: Leviton TR-rated 15A/20A outlet | O12: Confirmed | P12: medium | Q12: CA Code 2019+ TR mandatory | Tamper-resistant per CA Code 2019+ | Ціна збір: 2026-05-28
A13: 9 | B13: Electrical R-I | C13: Devices | D13: GFCI Outlets | E13: Bath, kitchen, exterior | F13: pcs | G13: 8 | H13: 10 | I13: 12 | J13: 18 | K13: =IF(OR(H13="",J13="",J13=0),"",H13*J13) | L13: Home Depot | M13: Leviton/Eaton GFCI receptacle | O13: Confirmed | P13: medium | Q13: Final GFCI strategy TBD: protection may be provided by GFCI receptacles, GFCI breakers, or dual-function breakers | Per pc | Ціна збір: 2026-05-28
A14: 10 | B14: Electrical R-I | C14: Devices | D14: Switches / Dimmers (LED-compatible) | E14: Single/3-way mix | F14: pcs | G14: 12 | H14: 15 | I14: 18 | J14: 7 | K14: =IF(OR(H14="",J14="",J14=0),"",H14*J14) | L14: Home Depot | M14: Leviton switches + dimmers mix | O14: Confirmed | P14: medium | Q14: CA Title 24 LED dimming | $2-4 single switch, $15-25 LED dimmer. Average $7 | Ціна збір: 2026-05-28
A15: 11 | B15: Electrical R-I | C15: Devices | D15: Cover Plates | F15: pcs | G15: 55 | H15: 62 | I15: 70 | J15: 0.75 | K15: =IF(OR(H15="",J15="",J15=0),"",H15*J15) | L15: Home Depot | M15: Leviton plastic cover plates | O15: Confirmed | P15: medium | Q15: Average per cover | Ціна збір: 2026-05-28
A16: 12 | B16: Electrical R-I | C16: Devices | D16: Bathroom Fan Timer Switch | F16: pcs | G16: 1 | H16: 1 | I16: 1 | J16: 30 | K16: =IF(OR(H16="",J16="",J16=0),"",H16*J16) | L16: Home Depot | M16: Leviton bathroom fan timer switch | O16: TBD | P16: medium | Q16: Single-pole | Ціна збір: 2026-05-28
A17: 13 | B17: Electrical R-I | C17: Devices | D17: Smoke / CO Detectors | E17: Combo hardwired interconnected + battery backup | F17: pcs | G17: 2 | H17: 3 | I17: 4 | J17: 43.44 | K17: =IF(OR(H17="",J17="",J17=0),"",H17*J17) | L17: Home Depot | M17: First Alert 1039339 hardwired combo | N17: https://www.homedepot.com/p/First-Alert-Smoke-and-CO-Detector-AA-Battery-1039339/313143543 | O17: Confirmed | P17: medium | Q17: Final placement TBD. CA Code: hardwired interconnected | Smoke+CO combo. CA Code: hardwired interconnected з battery backup | Ціна збір: 2026-05-28
A18: 14 | B18: Electrical R-I | C18: Devices | D18: Weatherproof Outlets | E18: Exterior GFCI in-use cover | F18: pcs | G18: 1 | H18: 2 | I18: 2 | J18: 22 | K18: =IF(OR(H18="",J18="",J18=0),"",H18*J18) | L18: Home Depot | M18: Leviton GFCI weatherproof + in-use cover | O18: TBD | P18: medium | Q18: Exterior | Ціна збір: 2026-05-28
A19: 15 | B19: Electrical R-I | C19: Devices | D19: Mini-split Disconnect (outdoor) | E19: 60A pull-out switch | F19: pcs | G19: 1 | H19: 1 | I19: 1 | J19: 40 | K19: =IF(OR(H19="",J19="",J19=0),"",H19*J19) | L19: Home Depot | M19: Square D 60A pull-out disconnect | O19: Confirmed | P19: medium | Q19: Mini-split outdoor disconnect | Ціна збір: 2026-05-28
A20: 16 | B20: Electrical R-I | C20: Devices | D20: Appliance Receptacles | E20: Range/dryer/etc receptacles | F20: pcs | G20: 3 | H20: 4 | I20: 5 | J20: 15 | K20: =IF(OR(H20="",J20="",J20=0),"",H20*J20) | L20: Home Depot | M20: Leviton range/dryer/WH receptacle | O20: TBD | P20: medium | Q20: TBD by appliance specs; some equipment may be hardwired (WH, mini-split) | Mix 14-50R + 14-30R + 6-30R | Ціна збір: 2026-05-28
A21: 17 | B21: Electrical R-I | C21: Lighting Fixtures | D21: Recessed Lights LED (cans+trim) | E21: Wafer LED 4"/6" dimmable | F21: pcs | G21: 10 | H21: 12 | I21: 14 | J21: 20 | K21: =IF(OR(H21="",J21="",J21=0),"",H21*J21) | L21: Home Depot | M21: Halo/Lithonia LED wafer 4"/6" dimmable | O21: Confirmed | P21: medium | Q21: LED recessed, CA Title 24 compliant | Ціна збір: 2026-05-28
A22: 18 | B22: Electrical R-I | C22: Lighting Fixtures | D22: Ceiling Lights (surface) | E22: Closet, utility | F22: pcs | G22: 2 | H22: 3 | I22: 4 | J22: 40 | K22: =IF(OR(H22="",J22="",J22=0),"",H22*J22) | L22: Home Depot | M22: Generic surface-mount LED ceiling | O22: TBD | P22: medium | Q22: Closet/utility | Ціна збір: 2026-05-28
A23: 19 | B23: Electrical R-I | C23: Lighting Fixtures | D23: Exterior Lights | E23: Entry + French door | F23: pcs | G23: 1 | H23: 2 | I23: 2 | J23: 60 | K23: =IF(OR(H23="",J23="",J23=0),"",H23*J23) | L23: Home Depot | M23: Generic LED wall mount exterior | O23: TBD | P23: medium | Q23: Entry + French door | Ціна збір: 2026-05-28
A24: 20 | B24: Electrical R-I | C24: Lighting Fixtures | D24: Bathroom Vanity Light | F24: pcs | G24: 1 | H24: 1 | I24: 1 | J24: 60 | K24: =IF(OR(H24="",J24="",J24=0),"",H24*J24) | L24: Home Depot | M24: Generic bathroom vanity LED | O24: TBD | P24: medium | Q24: Above mirror | Ціна збір: 2026-05-28
A25: 21 | B25: Electrical R-I | C25: Lighting Fixtures | D25: Closet Lighting | E25: Motion sensor | F25: pcs | G25: 1 | H25: 1 | I25: 1 | J25: 30 | K25: =IF(OR(H25="",J25="",J25=0),"",H25*J25) | L25: Home Depot / IKEA | M25: Generic LED motion sensor light | O25: TBD | P25: medium | Q25: Closet | Ціна збір: 2026-05-28
A26: 22 | B26: Electrical R-I | C26: Panel | D26: AFCI / Dual-Function Breakers | E26: CA Code 2019+ для bedroom/living/kitchen/dining | F26: pcs | G26: 6 | H26: 8 | I26: 10 | J26: 67 | K26: =IF(OR(H26="",J26="",J26=0),"",H26*J26) | L26: Home Depot | M26: Square D QO120DFC dual-function AFCI/GFCI | N26: https://www.homedepot.com/p/Square-D-QO-20-Amp-Single-Pole-Dual-Function-CAFCI-and-GFCI-Circuit-Breaker-6-Pack-QO120DFC6/206474144 | O26: Confirmed | P26: high | Q26: ДОДАНО (CA Code). НЕ дублюється з standard breakers — це окремі circuits | $67/each (6-pack $401.31). ДОДАНО (CA Code 2019+): bedroom/living/kitchen/dining mandatory | Ціна збір: 2026-05-28
A27: 23 | B27: Electrical R-I | C27: Consumables | D27: Wire Nuts (Marrettes/Wago) pack | E27: Splices | F27: pack | G27: 1 | H27: 1 | I27: 2 | J27: 10 | K27: =IF(OR(H27="",J27="",J27=0),"",H27*J27) | L27: Home Depot | M27: Buchanan/Ideal wire nuts pack 50ct | O27: Confirmed | P27: medium | Q27: ДОДАНО | ДОДАНО | Ціна збір: 2026-05-28
A28: 24 | B28: Electrical R-I | C28: Consumables | D28: Electrical Tape (B/W/R phasing) | E28: 3M Super 33 | F28: pack | G28: 1 | H28: 1 | I28: 1 | J28: 15 | K28: =IF(OR(H28="",J28="",J28=0),"",H28*J28) | L28: Home Depot | M28: 3M Super 33 electrical tape pack 5pk | O28: Confirmed | P28: medium | Q28: ДОДАНО | ДОДАНО: black/white/red phasing | Ціна збір: 2026-05-28
A29: 25 | B29: Electrical R-I | C29: Consumables | D29: Cable Staples / Romex Clips | E29: Для cable runs по studs | F29: lb | G29: 1 | H29: 1 | I29: 2 | J29: 12 | K29: =IF(OR(H29="",J29="",J29=0),"",H29*J29) | L29: Home Depot | M29: Gardner Bender Romex staples 1 lb | O29: Confirmed | P29: medium | Q29: ДОДАНО | ДОДАНО | Ціна збір: 2026-05-28
A30: 26 | B30: Electrical R-I | C30: Consumables | D30: Romex Cable Connectors | E30: Clamps box entry | F30: pack | G30: 1 | H30: 1 | I30: 2 | J30: 15 | K30: =IF(OR(H30="",J30="",J30=0),"",H30*J30) | L30: Home Depot | M30: Generic Romex 3/8 connectors 25-pack | O30: Confirmed | P30: medium | Q30: ДОДАНО: 25-count packs | ДОДАНО | Ціна збір: 2026-05-28
A31: 27 | B31: Electrical R-I | C31: Consumables | D31: Grounding Pigtails / Extra Green Wire | E31: Extra grounds | F31: pack | G31: 1 | H31: 1 | I31: 1 | J31: 10 | K31: =IF(OR(H31="",J31="",J31=0),"",H31*J31) | L31: Home Depot | M31: Generic #12 green ground pigtails pack | O31: Confirmed | P31: medium | Q31: ДОДАНО | ДОДАНО | Ціна збір: 2026-05-28
A32: 28 | B32: Electrical R-I | C32: Devices | D32: Junction Boxes (ceiling splice) | E32: Окремо від device boxes | F32: pcs | G32: 3 | H32: 5 | I32: 8 | J32: 2 | K32: =IF(OR(H32="",J32="",J32=0),"",H32*J32) | L32: Home Depot | M32: Carlon junction boxes plastic | O32: Confirmed | P32: medium | Q32: ДОДАНО | ДОДАНО: ceiling splices | Ціна збір: 2026-05-28
A33: 29 | B33: Electrical R-I | C33: Devices | D33: GFCI + USB Outlets | E33: Modern code allowance bedroom/kitchen | F33: pcs | G33: 1 | H33: 2 | I33: 4 | J33: 35 | K33: =IF(OR(H33="",J33="",J33=0),"",H33*J33) | L33: Home Depot | M33: Leviton T5832 GFCI+USB receptacle | O33: TBD | P33: medium | Q33: ДОДАНО | ДОДАНО: modern code allowance | Ціна збір: 2026-05-28
A34: 30 | B34: Electrical R-I | C34: Panel | D34: Whole-House Surge Protector | E34: SPD type 2 для subpanel | F34: pcs | G34: 0 | H34: 1 | I34: 1 | J34: 100 | K34: =IF(OR(H34="",J34="",J34=0),"",H34*J34) | L34: Home Depot | M34: Eaton CHSPT2ULTRA whole-house SPD type 2 | O34: TBD | P34: medium | Q34: ДОДАНО (CA recommendation — Optional) | ДОДАНО: CA recommendation | Ціна збір: 2026-05-28
A35: 31 | B35: Electrical R-I | C35: Bonding | D35: Bonding Jumpers + Clamps | E35: Metal water lines (WH) | F35: pcs | G35: 1 | H35: 2 | I35: 2 | J35: 8 | K35: =IF(OR(H35="",J35="",J35=0),"",H35*J35) | L35: Home Depot | M35: Bridgeport bonding bushing + jumper | O35: Confirmed | P35: medium | Q35: ДОДАНО | ДОДАНО: metal water line bonding | Ціна збір: 2026-05-28
A36: 32 | B36: Electrical R-I | C36: Panel | D36: Ground Bar / Neutral Bar Kit | E36: Часто потрібно окремо від subpanel | F36: set | G36: 1 | H36: 1 | I36: 1 | J36: 15 | K36: =IF(OR(H36="",J36="",J36=0),"",H36*J36) | L36: Home Depot | M36: Square D ground/neutral bar kit | O36: Confirmed | P36: medium | Q36: ДОДАНО (review): may not be included з load center | ДОДАНО (review): окремо від subpanel | Ціна збір: 2026-05-28
A37: 33 | B37: Electrical R-I | C37: Panel | D37: Panel Labels / Circuit Directory | E37: Identification labels | F37: set | G37: 1 | H37: 1 | I37: 1 | J37: 8 | K37: =IF(OR(H37="",J37="",J37=0),"",H37*J37) | L37: Home Depot | M37: Generic panel/circuit label set | O37: Confirmed | P37: medium | Q37: ДОДАНО (review) | ДОДАНО (review) | Ціна збір: 2026-05-28
A38: 34 | B38: Electrical R-I | C38: Lighting Fixtures | D38: Under-cabinet LED Driver / Transformer | E38: Якщо kitchen LED strip | F38: pcs | G38: 0 | H38: 1 | I38: 1 | J38: 35 | K38: =IF(OR(H38="",J38="",J38=0),"",H38*J38) | L38: Home Depot / IKEA | M38: Mean Well/IKEA LED driver 60W | O38: Optional | P38: medium | Q38: ДОДАНО (review): для under-cabinet lighting (Phase 13) | ДОДАНО (review): under-cabinet LED — Optional, qty mid=1 only if обрано | Ціна збір: 2026-05-28
... A41: 37 | B41: Electrical R-I | C41: Wire | D41: Spare Conduit Allowance | E41: Запас для future expansion | F41: set | G41: 0 | H41: 1 | I41: 1 | J41: 30 | K41: =IF(OR(H41="",J41="",J41=0),"",H41*J41) | L41: Home Depot | M41: Generic spare conduit + fittings | O41: Optional | P41: medium | Q41: ДОДАНО (review): якщо trench/walls open | ДОДАНО (review): future expansion — Optional | Ціна збір: 2026-05-28
C43: ПІДСУМОК ФАЗИ | K43: =SUM(K5:K41)

Sheet 08_HVAC_MiniSplit
A1: Phase 7 — HVAC Mini-Split (§22)
A2: 1 outdoor + 2 indoor units, line sets, mounting
A4: # | B4: Phase | C4: Категорія | D4: Item / Material | E4: Spec / Опис | F4: Unit | G4: Qty (Low) | H4: Qty (Mid) | I4: Qty (High) | J4: Unit Price ($) | K4: Total ($) | L4: Source | M4: SKU / Model | N4: URL | O4: Status | P4: Confidence | Q4: Notes
A5: 1 | B5: HVAC | C5: Outdoor Unit | D5: Mini-split Outdoor Condenser | E5: MRCOOL DIY 5th Gen 18k 9+9 KIT (z 2 indoor + line sets + remotes) | F5: pcs | G5: 1 | H5: 1 | I5: 1 | J5: 3150 | K5: =IF(OR(H5="",J5="",J5=0),"",H5*J5) | L5: Special Order | M5: MRCOOL DIY 5th Gen 18k BTU 9k+9k kit (25ft lines) | N5: https://www.homedepot.com/p/MRCOOL-DIY-5th-Gen-18-000-BTU-1-5-Ton-2-Zone-23-9-SEER2-Ductless-Mini-Split-AC-and-Heat-Pump-with-9K-9K-and-25-25ft-Lines-DIYM218HPW03D06/337863265 | O5: Confirmed | P5: high | Q5: Special Order. Full kit. Sizing TBD per §33.9 Manual J. Lead 4-8 weeks | $3,073 kit з 16ft lines + premium для 25ft = ~$3,150. Includes 2 indoor + line sets + controllers. Alt: Pioneer/Senville $2,500-2,800 | Ціна збір: 2026-05-28
A6: 2 | B6: HVAC | C6: Indoor Units | D6: Indoor Wall Units (2) | E6: 9k BTU × 2 — included in kit r5 | F6: pcs | G6: 0 | H6: 0 | I6: 0 | J6: 0 | K6: =IF(OR(H6="",J6="",J6=0),"",H6*J6) | L6: Special Order | M6: Cross-ref kit r5 — qty 0 | O6: Confirmed | P6: high | Q6: Included in main kit — do not price separately unless kit changes | Included в MRCOOL DIY kit. Standalone $400/unit if separately purchased | Ціна збір: 2026-05-28
A7: 3 | B7: HVAC | C7: Refrigerant | D7: Line Sets (pre-charged 25 ft) | E7: Included in kit r5 | F7: set | G7: 0 | H7: 0 | I7: 0 | J7: 0 | K7: =IF(OR(H7="",J7="",J7=0),"",H7*J7) | L7: Home Depot / specialty | M7: Cross-ref kit r5 — qty 0 | O7: Confirmed | P7: high | Q7: Included in main kit | Included в kit. Standalone $100/set if separately | Ціна збір: 2026-05-28
A8: 4 | B8: HVAC | C8: Condensate | D8: Condensate Drain Lines | E8: 3/4" PVC + fittings (2 sets) | F8: set | G8: 2 | H8: 2 | I8: 2 | J8: 30 | K8: =IF(OR(H8="",J8="",J8=0),"",H8*J8) | L8: Home Depot | M8: Generic 3/4 PVC + fittings | O8: Confirmed | P8: medium | Q8: Per set | Ціна збір: 2026-05-28
A9: 5 | B9: HVAC | C9: Penetrations | D9: Wall Sleeves | E9: Прохід крізь стіну (2) | F9: pcs | G9: 2 | H9: 2 | I9: 2 | J9: 30 | K9: =IF(OR(H9="",J9="",J9=0),"",H9*J9) | L9: Home Depot | M9: Generic 3-inch wall sleeve | O9: Confirmed | P9: medium | Q9: Per unit | Ціна збір: 2026-05-28
A10: 6 | B10: HVAC | C10: Mounting | D10: Wall Bracket (Optional) | E10: Optional alternative якщо ground placement не suitable | F10: pcs | G10: 0 | H10: 0 | I10: 1 | J10: 35 | K10: =IF(OR(H10="",J10="",J10=0),"",H10*J10) | L10: Home Depot | M10: Quick-Sling wall bracket allowance | O10: Optional | P10: medium | Q10: Baseline = concrete pad (r14). Wall bracket only якщо ground не підходить | Optional alternative — baseline = concrete pad r14 | Ціна збір: 2026-05-28
A11: 7 | B11: HVAC | C11: Trim | D11: Line Hide / Cover Kits | E11: Decorative exterior cover | F11: set | G11: 1 | H11: 1 | I11: 2 | J11: 70 | K11: =IF(OR(H11="",J11="",J11=0),"",H11*J11) | L11: Home Depot | M11: Mitsubishi/Pioneer line hide kit | O11: TBD | P11: medium | Q11: Decorative cover, 7-8 ft length | Ціна збір: 2026-05-28
A12: 8 | B12: HVAC | C12: Mounting | D12: Mounting Hardware | E12: Lag bolts + brackets + screws | F12: set | G12: 1 | H12: 1 | I12: 1 | J12: 40 | K12: =IF(OR(H12="",J12="",J12=0),"",H12*J12) | L12: Home Depot | M12: Generic lag bolts + brackets pack | O12: Confirmed | P12: medium | Q12: Mounting hardware | Ціна збір: 2026-05-28
A13: 9 | B13: HVAC | C13: Controls | D13: Controllers / Remotes | E13: Included in kit r5 | F13: pcs | G13: 0 | H13: 0 | I13: 0 | J13: 0 | K13: =IF(OR(H13="",J13="",J13=0),"",H13*J13) | L13: Manufacturer | M13: Included з indoor units | O13: Confirmed | P13: high | Q13: Included з indoor units in kit | Standard remote included | Ціна збір: 2026-05-28
A14: 10 | B14: HVAC | C14: Mounting | D14: Concrete Pad для Outdoor Unit | E14: 36×36" precast — BASELINE mount | F14: pcs | G14: 1 | H14: 1 | I14: 1 | J14: 35 | K14: =IF(OR(H14="",J14="",J14=0),"",H14*J14) | L14: Home Depot | M14: Diversitech precast 36x36 pad | O14: Confirmed | P14: medium | Q14: Baseline mounting. Wall bracket — Optional alternative (r10) | ДОДАНО: stable base + CA seismic | Ціна збір: 2026-05-28
A15: 11 | B15: HVAC | C15: Mounting | D15: Vibration Isolation Pads | E15: Rubber/cork pads під condenser | F15: set | G15: 1 | H15: 1 | I15: 1 | J15: 20 | K15: =IF(OR(H15="",J15="",J15=0),"",H15*J15) | L15: Home Depot | M15: Diversitech rubber/cork pads | O15: Confirmed | P15: medium | Q15: Noise/vibration reduction | ДОДАНО: noise/vibration | Ціна збір: 2026-05-28
A16: 12 | B16: HVAC | C16: Condensate | D16: Condensate Trap / Vent | E16: Prevent air-lock в drain line | F16: pcs | G16: 1 | H16: 2 | I16: 2 | J16: 15 | K16: =IF(OR(H16="",J16="",J16=0),"",H16*J16) | L16: Home Depot | M16: Generic 3/4 PVC condensate trap | O16: Confirmed | P16: medium | Q16: ДОДАНО | Ціна збір: 2026-05-28
A17: 13 | B17: HVAC | C17: Condensate | D17: Condensate Pump (Optional) | E17: Якщо gravity drain неможливий | F17: pcs | G17: 0 | H17: 0 | I17: 1 | J17: 100 | K17: =IF(OR(H17="",J17="",J17=0),"",H17*J17) | L17: Home Depot | M17: Aspen Mini Aqua condensate pump | O17: Optional | P17: medium | Q17: Backup allowance | ДОДАНО: optional, qty 0 baseline | Ціна збір: 2026-05-28
... A28: 24 | B28: HVAC | C28: Cross-ref | D28: Mini-split Electrical Whip / Disconnect | E28: Cross-ref Phase 6 r19 — не дублювати | F28: pcs | G28: 0 | H28: 0 | I28: 0 | J28: 0 | K28: =IF(OR(H28="",J28="",J28=0),"",H28*J28) | L28: — | M28: Cross-ref Phase 6 r19 — qty 0 | O28: Confirmed | P28: high | Q28: ДОДАНО (review): електричне з'єднання disconnect → condenser у Phase 6 | ДОДАНО (review): electrical whip/disconnect у Phase 6 — не дублювати | Ціна збір: 2026-05-28
C30: ПІДСУМОК ФАЗИ | K30: =SUM(K5:K28)

Sheet 09_Insulation
A1: Phase 8 — Insulation (§23)
A2: Walls R-15/R-21, ceiling R-30, floor R-19, sound
A4: # | B4: Phase | C4: Категорія | D4: Item / Material | E4: Spec / Опис | F4: Unit | G4: Qty (Low) | H4: Qty (Mid) | I4: Qty (High) | J4: Unit Price ($) | K4: Total ($) | L4: Source | M4: SKU / Model | N4: URL | O4: Status | P4: Confidence | Q4: Notes
A5: 1 | B5: Insulation | C5: Walls | D5: Exterior Wall Batt R-15 | E5: Kraft-faced fiberglass 16" OC (2x4 cavities) | F5: sq ft | G5: 600 | H5: 625 | I5: 650 | J5: 1 | K5: =IF(OR(H5="",J5="",J5=0),"",H5*J5) | L5: Home Depot | M5: Owens Corning R-15 Kraft-Faced 16" OC | N5: https://www.homedepot.com/p/Owens-Corning-R-15-Kraft-Faced-Fiberglass-Insulation-Batt-16-in-x-96-in-F95/313909974 | O5: Confirmed | P5: high | Q5: R-15 для 2x4 walls. If 2x6 cavities — use R-21. Final R-values to be verified before purchase per CA Title 24 | $1.00/sf. R-15 kraft-faced range $0.69-1.10 | Ціна збір: 2026-05-28
A6: 2 | B6: Insulation | C6: Ceiling | D6: Vaulted Ceiling Insulation R-30 | E6: Unfaced fiberglass batt 16" OC | F6: sq ft | G6: 360 | H6: 380 | I6: 400 | J6: 1.61 | K6: =IF(OR(H6="",J6="",J6=0),"",H6*J6) | L6: Home Depot | M6: Owens Corning R-30 Unfaced 16" OC | N6: https://www.homedepot.com/p/Owens-Corning-R-30-EcoTouch-PINK-Unfaced-Fiberglass-Insulation-Batt-16-in-x-48-in-BU74/300147480 | O6: Confirmed | P6: high | Q6: R-30 allowance — final R-value to be verified per code assembly. Vented assembly з baffles (alternative: unvented spray foam r17) | $1.61/sf. R-30 same Phase 2 pricing reference | Ціна збір: 2026-05-28
A7: 3 | B7: Insulation | C7: Floor | D7: Floor Insulation (cross-ref Phase 2) | E7: Already у Phase 2 row 12 — qty 0 | F7: sq ft | G7: 0 | H7: 0 | I7: 0 | J7: 0 | K7: =IF(OR(H7="",J7="",J7=0),"",H7*J7) | L7: — | M7: Cross-ref Phase 2 row 12 — qty 0 | O7: Confirmed | P7: high | Q7: DUPLICATE — vже в Phase 2 Raised Floor row 12 | DUPLICATE — already в Phase 2 Raised Floor | Ціна збір: 2026-05-28
A8: 4 | B8: Insulation | C8: Sound | D8: Sound Insulation R-13 | E8: Bedroom/bathroom walls fiberglass | F8: sq ft | G8: 250 | H8: 300 | I8: 350 | J8: 1.1 | K8: =IF(OR(H8="",J8="",J8=0),"",H8*J8) | L8: Home Depot | M8: Owens Corning R-13 Kraft-Faced | N8: https://www.homedepot.com/p/Owens-Corning-R-13-Kraft-Faced-Fiberglass-Insulation-Batt-16-in-x-96-in-10-Bags-C86/202746452 | O8: Confirmed | P8: medium | Q8: R-13 fiberglass (baseline). Premium alternative — mineral wool r15. Choose ONE not both | $1.10/sf fiberglass R-13. Alt mineral wool $1.85/sf r15 | Ціна збір: 2026-05-28
A9: 5 | B9: Insulation | C9: Air Sealing | D9: Spray Foam | E9: Great Stuff window/door foam | F9: cans | G9: 4 | H9: 6 | I9: 8 | J9: 7 | K9: =IF(OR(H9="",J9="",J9=0),"",H9*J9) | L9: Home Depot | M9: Great Stuff Pro window/door foam | O9: Confirmed | P9: medium | Q9: Per can | Ціна збір: 2026-05-28
A10: 6 | B10: Insulation | C10: Air Sealing | D10: Fire-blocking Foam / Caulk | E10: DAP fire-block | F10: tubes | G10: 4 | H10: 6 | I10: 8 | J10: 10 | K10: =IF(OR(H10="",J10="",J10=0),"",H10*J10) | L10: Home Depot | M10: DAP Fire-block foam tube | O10: Confirmed | P10: medium | Q10: Per tube | Ціна збір: 2026-05-28
A11: 7 | B11: Insulation | C11: Air Sealing | D11: Air Sealing Tape | E11: 3M All Weather / Tyvek | F11: rolls | G11: 2 | H11: 3 | I11: 4 | J11: 25 | K11: =IF(OR(H11="",J11="",J11=0),"",H11*J11) | L11: Home Depot | M11: 3M All Weather flashing tape | O11: Confirmed | P11: medium | Q11: Per roll | Ціна збір: 2026-05-28
A12: 8 | B12: Insulation | C12: Ventilation | D12: Baffles | E12: Rafter air vents для VENTED vaulted ceiling | F12: pcs | G12: 8 | H12: 14 | I12: 20 | J12: 1.5 | K12: =IF(OR(H12="",J12="",J12=0),"",H12*J12) | L12: Home Depot | M12: ADO Products attic rafter vent baffle | O12: TBD | P12: medium | Q12: Mid підвищено до 14 (every rafter bay). Choose VENTED batt+baffles OR UNVENTED spray foam r17 — not both | Per pc | Ціна збір: 2026-05-28
A13: 9 | B13: Insulation | C13: Supports | D13: Insulation Supports / Wire Supports | E13: Hold wall+ceiling batt в place | F13: pack | G13: 1 | H13: 2 | I13: 3 | J13: 9 | K13: =IF(OR(H13="",J13="",J13=0),"",H13*J13) | L13: Home Depot | M13: Owens Corning insulation wire supports | O13: Confirmed | P13: medium | Q13: For wall/ceiling batt | ДОДАНО: per pack | Ціна збір: 2026-05-28
A14: 10 | B14: Insulation | C14: Vapor | D14: Vapor Barrier Poly (Optional) | E14: Allowance — kraft-faced batt usually enough | F14: set | G14: 0 | H14: 1 | I14: 1 | J14: 40 | K14: =IF(OR(H14="",J14="",J14=0),"",H14*J14) | L14: Home Depot | M14: Stego/generic 6-mil poly allowance | O14: Optional | P14: medium | Q14: Verify if required — kraft-facing usually serves as vapor retarder | ДОДАНО: kraft-faced usually sufficient | Ціна збір: 2026-05-28
A15: 11 | B15: Insulation | C15: Sound | D15: Mineral Wool R-13 Alternative (Optional) | E15: Roxul Safe'n'Sound — premium sound + fire | F15: sq ft | G15: 0 | H15: 0 | I15: 350 | J15: 1.85 | K15: =IF(OR(H15="",J15="",J15=0),"",H15*J15) | L15: Home Depot | M15: ROCKWOOL Safe'n'Sound R-13 | N15: https://www.homedepot.com/p/ROCKWOOL-Safe-n-Sound-3-in-x-15-1-4-in-x-47-in-Soundproofing-and-Fire-Resistant-Stone-Wool-Insulation-Batt-59-7-sq-ft-RXSS31525/202531875 | O15: Optional | P15: high | Q15: Premium alt для r8. Choose ONE not both | $1.85/sf. Premium mineral wool alternative to r8. Choose ONE not both | Ціна збір: 2026-05-28
A16: 12 | B16: Insulation | C16: Supports | D16: Cap Strips / Batt Straps | E16: Bottom plate compression | F16: pack | G16: 0 | H16: 1 | I16: 2 | J16: 10 | K16: =IF(OR(H16="",J16="",J16=0),"",H16*J16) | L16: Home Depot | M16: Generic cap strips / batt straps pack | O16: TBD | P16: medium | Q16: ДОДАНО | Ціна збір: 2026-05-28
A17: 13 | B17: Insulation | C17: Air Sealing | D17: Closed-cell Spray Foam Kit (Optional) | E17: Для UNVENTED vaulted ceiling assembly | F17: kit | G17: 0 | H17: 0 | I17: 1 | J17: 300 | K17: =IF(OR(H17="",J17="",J17=0),"",H17*J17) | L17: Home Depot / specialty | M17: Tiger Foam closed-cell kit (Optional) | O17: Optional | P17: low | Q17: Alternative до vented batt+baffles. Choose ONE strategy | ДОДАНО: closed-cell spray foam allowance | Ціна збір: 2026-05-28
A18: 14 | B18: Insulation | C18: Air Sealing | D18: General Air-sealing Caulk | E18: Top/bottom plates, corners, small gaps | F18: tubes | G18: 3 | H18: 4 | I18: 6 | J18: 5 | K18: =IF(OR(H18="",J18="",J18=0),"",H18*J18) | L18: Home Depot | M18: DAP Alex Plus general caulk | O18: Confirmed | P18: medium | Q18: ДОДАНО (review): air sealing perimeters | ДОДАНО (review): top/bottom plates, corners | Ціна збір: 2026-05-28
A19: 15 | B19: Insulation | C19: Supports | D19: Staples / Insulation Fastening Supplies | E19: Для kraft-faced batt stapling | F19: set | G19: 1 | H19: 1 | I19: 1 | J19: 20 | K19: =IF(OR(H19="",J19="",J19=0),"",H19*J19) | L19: Home Depot | M19: Generic T50 staples + insulation fasteners set | O19: Confirmed | P19: medium | Q19: ДОДАНО (review): T50 staples + крепежі | ДОДАНО (review): kraft-faced batt stapling | Ціна збір: 2026-05-28
A20: 16 | B20: Insulation | C20: Safety | D20: Protective Gear allowance | E20: Fiberglass gloves + mask + goggles | F20: set | G20: 1 | H20: 1 | I20: 1 | J20: 25 | K20: =IF(OR(H20="",J20="",J20=0),"",H20*J20) | L20: Home Depot | M20: Generic PPE pack (gloves + mask + goggles) | O20: Confirmed | P20: medium | Q20: ДОДАНО (review): PPE для fiberglass installation | ДОДАНО (review): fiberglass safety | Ціна збір: 2026-05-28
C22: ПІДСУМОК ФАЗИ | K22: =SUM(K5:K20)

Sheet 10_Drywall
A1: Phase 9 — Drywall (§24)
A2: 60-75 sheets regular + 10-15 moisture-resistant
A4: # | B4: Phase | C4: Категорія | D4: Item / Material | E4: Spec / Опис | F4: Unit | G4: Qty (Low) | H4: Qty (Mid) | I4: Qty (High) | J4: Unit Price ($) | K4: Total ($) | L4: Source | M4: SKU / Model | N4: URL | O4: Status | P4: Confidence | Q4: Notes
A5: 1 | B5: Drywall | C5: Board | D5: Regular Drywall 1/2" | E5: 4x8 sheets — walls (baseline) | F5: sheets | G5: 60 | H5: 67 | I5: 75 | J5: 13 | K5: =IF(OR(H5="",J5="",J5=0),"",H5*J5) | L5: Home Depot | M5: USG UltraLight 1/2" 4x8 sheet | N5: https://www.homedepot.com/p/USG-Sheetrock-Brand-1-2-in-x-4-ft-x-8-ft-UltraLight-Drywall-14113411708/202530243 | O5: Confirmed | P5: high | Q5: 1/2" walls + standard ceiling. PVA primer counted ТУТ — не дублювати в Paint phase | $11-15/sheet. ToughRock alt cheaper | Ціна збір: 2026-05-28
A6: 2 | B6: Drywall | C6: Board | D6: Moisture-resistant Drywall | E6: Greenboard 1/2" — bathroom, laundry, utility | F6: sheets | G6: 10 | H6: 12 | I6: 15 | J6: 20 | K6: =IF(OR(H6="",J6="",J6=0),"",H6*J6) | L6: Home Depot | M6: USG Mold Tough 1/2" 4x8 greenboard | N6: https://www.homedepot.com/p/USG-Sheetrock-Brand-1-2-in-x-4-ft-x-8-ft-UltraLight-Mold-Tough-Drywall-14302111708/203768542 | O6: Confirmed | P6: high | Q6: $22.98 single / $19.53 bulk 34+. Mid $20 | Ціна збір: 2026-05-28
A7: 3 | B7: Drywall | C7: Board | D7: Cement Board / Backer Board | E7: HardieBacker 1/2" — shower wet zone | F7: sheets | G7: 3 | H7: 4 | I7: 5 | J7: 20 | K7: =IF(OR(H7="",J7="",J7=0),"",H7*J7) | L7: Home Depot | M7: HardieBacker 1/2" 3x5 cement board | N7: https://www.homedepot.com/p/James-Hardie-HardieBacker-1-2-in-x-3-ft-x-5-ft-Cement-Backerboard-220023/100170507 | O7: Confirmed | P7: medium | Q7: Pair з RedGard r16. Counted тут — не дублювати в Bathroom phase | Range $13-25 depending on size 3x5 vs 4x8 | Ціна збір: 2026-05-28
A8: 4 | B8: Drywall | C8: Fasteners | D8: Drywall Screws | E8: 1¼" coarse — підвищено Mid | F8: lb | G8: 8 | H8: 10 | I8: 14 | J8: 7 | K8: =IF(OR(H8="",J8="",J8=0),"",H8*J8) | L8: Home Depot | M8: Generic 1¼ coarse drywall screws | O8: Confirmed | P8: medium | Q8: Mid підвищено до 10 lb (review): достатньо для 67 sheets | Per lb. 5 lb box ~$35 | Ціна збір: 2026-05-28
A9: 5 | B9: Drywall | C9: Finishing | D9: Joint Compound (All-Purpose) | E9: 5 gal ready-mix — підвищено Mid | F9: buckets | G9: 4 | H9: 6 | I9: 8 | J9: 17 | K9: =IF(OR(H9="",J9="",J9=0),"",H9*J9) | L9: Home Depot | M9: USG Sheetrock All-Purpose 5 gal | O9: Confirmed | P9: medium | Q9: Mid підвищено до 6 buckets (review): для vaulted ceiling + corners | Per bucket | Ціна збір: 2026-05-28
A10: 6 | B10: Drywall | C10: Finishing | D10: Drywall Tape (Paper) | E10: 250 ft roll | F10: rolls | G10: 4 | H10: 6 | I10: 8 | J10: 5 | K10: =IF(OR(H10="",J10="",J10=0),"",H10*J10) | L10: Home Depot | M10: Generic paper joint tape 250 ft | O10: Confirmed | P10: medium | Q10: Paper для joints; mesh окремо r15 | Per roll | Ціна збір: 2026-05-28
A11: 7 | B11: Drywall | C11: Finishing | D11: Corner Bead | E11: Metal або paper-faced | F11: linear ft | G11: 100 | H11: 140 | I11: 180 | J11: 0.65 | K11: =IF(OR(H11="",J11="",J11=0),"",H11*J11) | L11: Home Depot | M11: Generic metal corner bead 8 ft | O11: Confirmed | P11: medium | Q11: Per LF | Ціна збір: 2026-05-28
A12: 8 | B12: Drywall | C12: Primer | D12: Drywall Primer (PVA) | E12: 5 gal — counted тут, не дублювати в Paint phase | F12: gal | G12: 2 | H12: 3 | I12: 4 | J12: 25 | K12: =IF(OR(H12="",J12="",J12=0),"",H12*J12) | L12: Home Depot | M12: Kilz PVA Sealer primer 1 gal | O12: Confirmed | P12: medium | Q12: PVA drywall primer — окремо від finish primer | Per gal | Ціна збір: 2026-05-28
A13: 9 | B13: Drywall | C13: Finishing | D13: Texture Material | E13: Homax knockdown spray (CA default) | F13: cans | G13: 3 | H13: 4 | I13: 6 | J13: 30 | K13: =IF(OR(H13="",J13="",J13=0),"",H13*J13) | L13: Home Depot | M13: Homax knockdown texture spray | O13: TBD | P13: medium | Q13: §24.4. Texture method TBD: spray cans = allowance only | ДОДАНО (§24.4): per can. CA default knockdown | Ціна збір: 2026-05-28
A14: 10 | B14: Drywall | C14: Access | D14: Access Panels 12×12 | E14: PVC — bathroom + utility access | F14: pcs | G14: 1 | H14: 2 | I14: 3 | J14: 22 | K14: =IF(OR(H14="",J14="",J14=0),"",H14*J14) | L14: Home Depot | M14: Generic PVC access panel 12x12 | O14: Confirmed | P14: medium | Q14: §24.4 | ДОДАНО (§24.4): plumbing/electric access | Ціна збір: 2026-05-28
A15: 11 | B15: Drywall | C15: Finishing | D15: Drywall Mesh Tape (cement board) | E15: Alkali-resistant fiberglass | F15: rolls | G15: 1 | H15: 1 | I15: 2 | J15: 5 | K15: =IF(OR(H15="",J15="",J15=0),"",H15*J15) | L15: Home Depot | M15: Generic alkali-resistant mesh tape | O15: Confirmed | P15: medium | Q15: Cement board joints | ДОДАНО: cement board joints | Ціна збір: 2026-05-28
A16: 12 | B16: Drywall | C16: Waterproofing | D16: RedGard Waterproofing Membrane | E16: Custom Building Products — shower walls | F16: gal | G16: 1 | H16: 1 | I16: 2 | J16: 50 | K16: =IF(OR(H16="",J16="",J16=0),"",H16*J16) | L16: Home Depot | M16: Custom Building Products RedGard 1 gal | N16: https://www.homedepot.com/b/Flooring-Flooring-Supplies/Custom-Building-Products/Waterproofing-Membrane/N-5yc1vZcabsZ1z10jx7Z2g1 | O16: Confirmed | P16: medium | Q16: За cement board у shower | ДОДАНО: waterproofing за cement board у shower | Ціна збір: 2026-05-28
A17: 13 | B17: Drywall | C17: Finishing | D17: Sanding Consumables | E17: Sanding screens + sponges + paper | F17: set | G17: 1 | H17: 1 | I17: 1 | J17: 20 | K17: =IF(OR(H17="",J17="",J17=0),"",H17*J17) | L17: Home Depot | M17: Generic sanding sponges + screens + paper set | O17: Confirmed | P17: medium | Q17: ДОДАНО | Ціна збір: 2026-05-28
A18: 14 | B18: Drywall | C18: Finishing | D18: Setting-type Compound Durabond (Optional) | E18: 20-min set | F18: bag | G18: 0 | H18: 1 | I18: 2 | J18: 25 | K18: =IF(OR(H18="",J18="",J18=0),"",H18*J18) | L18: Home Depot | M18: USG Durabond 90 setting-type 25 lb | O18: Optional | P18: medium | Q18: ДОДАНО: 20-min set для repair/shower | Ціна збір: 2026-05-28
A19: 15 | B19: Drywall | C19: Adhesives | D19: Drywall Adhesive (Optional) | E19: PL Premium stud attachment | F19: tubes | G19: 0 | H19: 6 | I19: 10 | J19: 10 | K19: =IF(OR(H19="",J19="",J19=0),"",H19*J19) | L19: Home Depot | M19: Loctite PL Premium 10oz drywall adhesive | O19: Optional | P19: medium | Q19: Reduce screws, optional | ДОДАНО: stud attachment optional | Ціна збір: 2026-05-28
A20: 16 | B20: Drywall | C20: Board | D20: 5/8" Type X Drywall (Allowance/Upgrade) | E20: Fire-rated ceiling assembly если req'd | F20: sheets | G20: 0 | H20: 0 | I20: 12 | J20: 18 | K20: =IF(OR(H20="",J20="",J20=0),"",H20*J20) | L20: Home Depot | M20: 5/8" Type X drywall 4x8 sheet | O20: Optional | P20: medium | Q20: ДОДАНО (review): verify fire-rating ceiling requirement per §33.26. Окрема upgrade позиція | ДОДАНО (review): fire-rated upgrade. Qty 0 baseline | Ціна збір: 2026-05-28
A21: 17 | B21: Drywall | C21: Finishing | D21: Flexible Corner Tape / No-Coat | E21: Vaulted ceiling transitions, нестандартні кути | F21: rolls | G21: 1 | H21: 1 | I21: 2 | J21: 10 | K21: =IF(OR(H21="",J21="",J21=0),"",H21*J21) | L21: Home Depot | M21: No-Coat flexible corner tape 100 ft | O21: Confirmed | P21: medium | Q21: ДОДАНО (review): vaulted ceiling angles | ДОДАНО (review): vaulted ceiling | Ціна збір: 2026-05-28
A22: 18 | B22: Drywall | C22: Site Protection | D22: Plastic Sheeting / Dust Protection | E22: Floor + adjacent rooms protection | F22: rolls | G22: 1 | H22: 1 | I22: 2 | J22: 30 | K22: =IF(OR(H22="",J22="",J22=0),"",H22*J22) | L22: Home Depot | M22: Generic 10x100 plastic sheeting 3-mil | O22: Confirmed | P22: medium | Q22: ДОДАНО (review): mudding/sanding dust | ДОДАНО (review): dust protection | Ціна збір: 2026-05-28
A23: 19 | B23: Drywall | C23: Finishing | D23: Control Joint / Expansion Bead (Optional) | E23: Якщо довгі площини або transitions | F23: linear ft | G23: 0 | H23: 0 | I23: 30 | J23: 1.5 | K23: =IF(OR(H23="",J23="",J23=0),"",H23*J23) | L23: Home Depot | M23: Trim-Tex control joint vinyl | O23: Optional | P23: medium | Q23: ДОДАНО (review): TBD per layout | ДОДАНО (review): per LF, qty 0 baseline | Ціна збір: 2026-05-28
A24: 20 | B24: Drywall | C24: Repair | D24: Drywall Repair Patch (Optional) | E24: Для utility access або corrections | F24: pcs | G24: 0 | H24: 0 | I24: 2 | J24: 5 | K24: =IF(OR(H24="",J24="",J24=0),"",H24*J24) | L24: Home Depot | M24: Generic 6x6 drywall patch | O24: Optional | P24: medium | Q24: ДОДАНО (review) | ДОДАНО (review): qty 0 baseline | Ціна збір: 2026-05-28
C26: ПІДСУМОК ФАЗИ | K26: =SUM(K5:K24)

Sheet 11_Paint
A1: Phase 10 — Paint (§27)
A2: Primer + walls + ceiling + trim + bathroom moisture
A4: # | B4: Phase | C4: Категорія | D4: Item / Material | E4: Spec / Опис | F4: Unit | G4: Qty (Low) | H4: Qty (Mid) | I4: Qty (High) | J4: Unit Price ($) | K4: Total ($) | L4: Source | M4: SKU / Model | N4: URL | O4: Status | P4: Confidence | Q4: Notes
A5: 1 | B5: Paint | C5: Wall Paint | D5: Wall Paint | E5: Behr Premium Plus Ultra eggshell, 2 coats | F5: gal | G5: 8 | H5: 12 | I5: 16 | J5: 35 | K5: =IF(OR(H5="",J5="",J5=0),"",H5*J5) | L5: Home Depot | M5: Behr Premium Plus Ultra eggshell 1 gal | O5: Confirmed | P5: medium | Q5: Mid підвищено 7→12 для 2-coat standard (2,200 sf × 2 / 350 = 12.6) | Range $30-45/gal. 5gal bucket cheaper per gal | Ціна збір: 2026-05-28
A6: 2 | B6: Paint | C6: Ceiling Paint | D6: Ceiling Paint | E6: Flat white ceiling-specific | F6: gal | G6: 2 | H6: 3 | I6: 4 | J6: 30 | K6: =IF(OR(H6="",J6="",J6=0),"",H6*J6) | L6: Home Depot | M6: Behr Premium Plus Ultra ceiling flat 1 gal | O6: Confirmed | P6: medium | Q6: Vaulted ~400 sf × 2 coats | Flat ceiling-specific | Ціна збір: 2026-05-28
A7: 3 | B7: Paint | C7: Specialty | D7: Bathroom Moisture-resistant Paint | E7: Behr Premium Mildew-resistant semi-gloss | F7: gal | G7: 1 | H7: 1 | I7: 2 | J7: 45 | K7: =IF(OR(H7="",J7="",J7=0),"",H7*J7) | L7: Home Depot | M7: Behr Premium Mildew-resistant semi-gloss 1 gal | O7: Confirmed | P7: medium | Q7: Bathroom moisture | Ціна збір: 2026-05-28
A8: 4 | B8: Paint | C8: Trim | D8: Trim Paint | E8: Behr semi-gloss acrylic | F8: gal | G8: 1 | H8: 2 | I8: 3 | J8: 42 | K8: =IF(OR(H8="",J8="",J8=0),"",H8*J8) | L8: Home Depot | M8: Behr Premium semi-gloss acrylic 1 gal | O8: Confirmed | P8: medium | Q8: Trim/door paint | Ціна збір: 2026-05-28
A9: 5 | B9: Paint | C9: Prep | D9: Painter's Caulk | E9: DAP Alex Plus latex — підвищено Mid | F9: tubes | G9: 6 | H9: 8 | I9: 12 | J9: 5 | K9: =IF(OR(H9="",J9="",J9=0),"",H9*J9) | L9: Home Depot | M9: DAP Alex Plus painter's caulk | O9: Confirmed | P9: medium | Q9: Mid підвищено 6→8 (review): для trim/casing/baseboards | Per tube | Ціна збір: 2026-05-28
A10: 6 | B10: Paint | C10: Prep | D10: Painter's Tape | E10: 3M ScotchBlue 1.88" | F10: rolls | G10: 4 | H10: 6 | I10: 8 | J10: 12 | K10: =IF(OR(H10="",J10="",J10=0),"",H10*J10) | L10: Home Depot | M10: 3M ScotchBlue painter's tape 1.88" | O10: Confirmed | P10: medium | Q10: Per roll | Ціна збір: 2026-05-28
A11: 7 | B11: Paint | C11: Prep | D11: Drop Cloths / Plastic | E11: Canvas drop cloths + plastic sheeting | F11: set | G11: 1 | H11: 1 | I11: 2 | J11: 30 | K11: =IF(OR(H11="",J11="",J11=0),"",H11*J11) | L11: Home Depot | M11: Generic canvas drop cloths + plastic set | O11: Confirmed | P11: medium | Q11: Mixed canvas + plastic sheeting | Ціна збір: 2026-05-28
A12: 8 | B12: Paint | C12: Prep | D12: Sandpaper / Wood Filler | E12: Assortment + wood filler | F12: set | G12: 1 | H12: 1 | I12: 1 | J12: 20 | K12: =IF(OR(H12="",J12="",J12=0),"",H12*J12) | L12: Home Depot | M12: Generic sandpaper + DAP wood filler set | O12: Confirmed | P12: medium | Q12: Assortment grit + filler | Ціна збір: 2026-05-28
A13: 9 | B13: Paint | C13: Touch-up | D13: Touch-up Supplies | E13: Mini-rollers + small brushes + containers | F13: set | G13: 1 | H13: 1 | I13: 1 | J13: 15 | K13: =IF(OR(H13="",J13="",J13=0),"",H13*J13) | L13: Home Depot | M13: Generic touch-up supplies kit | O13: Confirmed | P13: medium | Q13: ДОДАНО (per §27.2) | ДОДАНО (per §27.2) | Ціна збір: 2026-05-28
A14: 10 | B14: Paint | C14: Tools | D14: Paint Rollers + Covers | E14: 9" 3/8" nap covers 6-pack | F14: set | G14: 1 | H14: 1 | I14: 2 | J14: 20 | K14: =IF(OR(H14="",J14="",J14=0),"",H14*J14) | L14: Home Depot | M14: Wooster 9" roller covers 6-pack 3/8 nap | O14: Confirmed | P14: medium | Q14: ДОДАНО | ДОДАНО | Ціна збір: 2026-05-28
A15: 11 | B15: Paint | C15: Tools | D15: Paint Brushes | E15: 2" + 2.5" + 3" angled sash mix | F15: set | G15: 1 | H15: 1 | I15: 2 | J15: 25 | K15: =IF(OR(H15="",J15="",J15=0),"",H15*J15) | L15: Home Depot | M15: Purdy paint brushes set 2"+2.5"+3" | O15: Confirmed | P15: medium | Q15: ДОДАНО | ДОДАНО | Ціна збір: 2026-05-28
A16: 12 | B16: Paint | C16: Tools | D16: Paint Trays + Liners | E16: 9" tray + disposable liners 4-pack | F16: set | G16: 1 | H16: 1 | I16: 2 | J16: 15 | K16: =IF(OR(H16="",J16="",J16=0),"",H16*J16) | L16: Home Depot | M16: 9" paint tray + 4-pack disposable liners | O16: Confirmed | P16: medium | Q16: ДОДАНО | ДОДАНО | Ціна збір: 2026-05-28
... A24: 20 | B24: Paint | C24: Prep | D24: Tack Cloth / Microfiber Cloths | E24: Trim prep перед фарбуванням | F24: pack | G24: 1 | H24: 1 | I24: 1 | J24: 10 | K24: =IF(OR(H24="",J24="",J24=0),"",H24*J24) | L24: Home Depot | M24: Generic tack cloth + microfiber cloths | O24: Confirmed | P24: medium | Q24: ДОДАНО (review) | ДОДАНО (review): trim prep | Ціна збір: 2026-05-28
C26: ПІДСУМОК ФАЗИ | K26: =SUM(K5:K24)

Sheet 12_Flooring_Trim
A1: Phase 11 — Flooring & Trim (§26)
A2: LVP 350 sf + baseboards 140 LF
A4: # | B4: Phase | C4: Категорія | D4: Item / Material | E4: Spec / Опис | F4: Unit | G4: Qty (Low) | H4: Qty (Mid) | I4: Qty (High) | J4: Unit Price ($) | K4: Total ($) | L4: Source | M4: SKU / Model | N4: URL | O4: Status | P4: Confidence | Q4: Notes
A5: 1 | B5: Flooring | C5: Flooring | D5: LVP / Luxury Vinyl Plank | E5: LifeProof 22 MIL click-lock waterproof | F5: sq ft | G5: 315 | H5: 350 | I5: 380 | J5: 3 | K5: =IF(OR(H5="",J5="",J5=0),"",H5*J5) | L5: Home Depot | M5: LifeProof 22 MIL Click-Lock Waterproof LVP | N5: https://www.homedepot.com/p/Lifeproof-Sterling-Oak-22-MIL-x-8-7-in-W-x-48-in-L-Click-Lock-Waterproof-Luxury-Vinyl-Plank-Flooring-20-1-sqft-case-I966106LP/309083456 | O5: Confirmed | P5: high | Q5: Across entire ADU. Long dimension parallel to walls (21 ft) | $2.98-3.50/sf. LifeProof Sterling Oak / Trail / Fresh — Home Depot exclusive (Shaw) | Ціна збір: 2026-05-28
A6: 2 | B6: Flooring | C6: Flooring | D6: Underlayment (Optional) | E6: Foam 2mm з vapor barrier — ONLY if LVP без attached pad | F6: sq ft | G6: 0 | H6: 0 | I6: 380 | J6: 0.3 | K6: =IF(OR(H6="",J6="",J6=0),"",H6*J6) | L6: Home Depot | M6: Roberts Super Felt foam underlayment | O6: TBD | P6: medium | Q6: LifeProof 22 MIL зазвичай має attached underlayment — verify product specs. Mid 0 baseline | Per sf. Verify if LVP має attached underlayment first | Ціна збір: 2026-05-28
A7: 3 | B7: Flooring | C7: Trim | D7: Decorative Transition Strips | E7: T-molding + reducer + end-cap для LVP | F7: pcs | G7: 3 | H7: 4 | I7: 5 | J7: 20 | K7: =IF(OR(H7="",J7="",J7=0),"",H7*J7) | L7: Home Depot | M7: Generic LVP T-molding/reducer/end-cap | O7: Confirmed | P7: medium | Q7: Decorative (LVP transitions). Phase 2 r13 = structural (10" raise) | Per piece. Average mix | Ціна збір: 2026-05-28
A8: 4 | B8: Flooring | C8: Trim | D8: Baseboards | E8: 5.25" pine MDF primed | F8: linear ft | G8: 130 | H8: 150 | I8: 170 | J8: 0.85 | K8: =IF(OR(H8="",J8="",J8=0),"",H8*J8) | L8: Home Depot | M8: Pine MDF 5.25" primed baseboard | O8: Confirmed | P8: medium | Q8: Mid 150 LF includes 10-15% waste/returns for corners | Per LF | Ціна збір: 2026-05-28
A9: 5 | B9: Flooring | C9: Trim | D9: Quarter Round | E9: Shoe molding 3/4" pine primed | F9: linear ft | G9: 0 | H9: 100 | I9: 160 | J9: 0.55 | K9: =IF(OR(H9="",J9="",J9=0),"",H9*J9) | L9: Home Depot | M9: Pine 3/4" shoe molding primed | O9: TBD | P9: medium | Q9: Per LF | Ціна збір: 2026-05-28
A10: 6 | B10: Flooring | C10: Moisture | D10: Vapor Barrier Sheet (Optional) | E10: 6-mil poly під LVP — якщо LVP без attached | F10: sq ft | G10: 0 | H10: 0 | I10: 380 | J10: 0.1 | K10: =IF(OR(H10="",J10="",J10=0),"",H10*J10) | L10: Home Depot | M10: Generic 6-mil poly vapor sheet | O10: Optional | P10: medium | Q10: ДОДАНО: skip if LVP має attached vapor | ДОДАНО: only if LVP без attached vapor | Ціна збір: 2026-05-28
A11: 7 | B11: Flooring | C11: Supplies | D11: Flooring Spacers | E11: 1/4"-3/8" expansion gap | F11: pack | G11: 1 | H11: 1 | I11: 1 | J11: 5 | K11: =IF(OR(H11="",J11="",J11=0),"",H11*J11) | L11: Home Depot | M11: Generic flooring spacers 1/4-3/8" pack | O11: Confirmed | P11: medium | Q11: ДОДАНО | ДОДАНО | Ціна збір: 2026-05-28
A12: 8 | B12: Flooring | C12: Supplies | D12: LVP Installation Kit | E12: Tapping block + pull bar + utility knife | F12: set | G12: 1 | H12: 1 | I12: 1 | J12: 20 | K12: =IF(OR(H12="",J12="",J12=0),"",H12*J12) | L12: Home Depot | M12: Roberts LVP installation kit | O12: Confirmed | P12: medium | Q12: ДОДАНО | ДОДАНО: tapping block + pull bar + utility knife | Ціна збір: 2026-05-28
A13: 9 | B13: Flooring | C13: Sealants | D13: Floor Caulk | E13: Perimeter sealing | F13: tubes | G13: 2 | H13: 4 | I13: 6 | J13: 5 | K13: =IF(OR(H13="",J13="",J13=0),"",H13*J13) | L13: Home Depot | M13: Generic floor caulk tube | O13: Confirmed | P13: medium | Q13: ДОДАНО | ДОДАНО: perimeter sealing | Ціна збір: 2026-05-28
A14: 10 | B14: Flooring | C14: Fasteners | D14: Finish Nails (18 ga brad) | E14: Baseboard + quarter round installation | F14: box | G14: 1 | H14: 1 | I14: 2 | J14: 15 | K14: =IF(OR(H14="",J14="",J14=0),"",H14*J14) | L14: Home Depot | M14: Generic 18-gauge brad nails box | O14: Confirmed | P14: medium | Q14: ДОДАНО | ДОДАНО | Ціна збір: 2026-05-28
A15: 11 | B15: Flooring | C15: Adjustment | D15: Door Undercut Allowance | E15: Якщо doors торкаються нового flooring | F15: allowance | G15: 0 | H15: 1 | I15: 1 | J15: 20 | K15: =IF(OR(H15="",J15="",J15=0),"",H15*J15) | L15: Home Depot / service | M15: Door undercut allowance (saw rental or service) | O15: TBD | P15: medium | Q15: ДОДАНО | ДОДАНО | Ціна збір: 2026-05-28
A16: 12 | B16: Flooring | C16: Slab Prep | D16: Self-leveler Patch (Optional) | E16: Final subfloor touchups | F16: bag | G16: 0 | H16: 0 | I16: 2 | J16: 25 | K16: =IF(OR(H16="",J16="",J16=0),"",H16*J16) | L16: Home Depot | M16: Mapei Planipatch 25 lb (Optional) | O16: Optional | P16: medium | Q16: ДОДАНО: small allowance, cross-ref Phase 2 r19 | ДОДАНО: small allowance. Cross-ref Phase 2 r19 | Ціна збір: 2026-05-28
A17: 13 | B17: Flooring | C17: Trim | D17: Bathroom Reducer / Transition Allowance | E17: Якщо bathroom flooring відрізняється або є height diff | F17: pcs | G17: 0 | H17: 1 | I17: 2 | J17: 25 | K17: =IF(OR(H17="",J17="",J17=0),"",H17*J17) | L17: Home Depot | M17: Generic bathroom reducer / transition | O17: TBD | P17: medium | Q17: ДОДАНО (review) | ДОДАНО (review): per piece | Ціна збір: 2026-05-28
A18: 14 | B18: Flooring | C18: Trim | D18: Stair Nosing / Step Trim | E18: Через raised floor 10" — step at entry/French | F18: pcs | G18: 0 | H18: 1 | I18: 2 | J18: 40 | K18: =IF(OR(H18="",J18="",J18=0),"",H18*J18) | L18: Home Depot | M18: Generic LVP stair nosing / step nose | O18: TBD | P18: medium | Q18: ДОДАНО (review): verify step condition | ДОДАНО (review): через 10" raised floor step | Ціна збір: 2026-05-28
C20: ПІДСУМОК ФАЗИ | K20: =SUM(K5:K18)

Sheet 13_Kitchen_Cabinets
A1: Phase 12 — Kitchen Cabinets & Countertop (§11)
A2: IKEA SEKTION one-wall + countertop + sink/faucet
A4: # | B4: Phase | C4: Категорія | D4: Item / Material | E4: Spec / Опис | F4: Unit | G4: Qty (Low) | H4: Qty (Mid) | I4: Qty (High) | J4: Unit Price ($) | K4: Total ($) | L4: Source | M4: SKU / Model | N4: URL | O4: Status | P4: Confidence | Q4: Notes
A5: 1 | B5: Cabinetry | C5: Cabinets | D5: Base Cabinets | E5: IKEA SEKTION carcass 24" deep | F5: linear ft | G5: 8 | H5: 8.5 | I5: 9 | J5: 50 | K5: =IF(OR(H5="",J5="",J5=0),"",H5*J5) | L5: IKEA | M5: IKEA SEKTION base cabinet 24" deep | N5: https://www.ikea.com/us/en/cat/base-cabinets-frame-height-23607/ | O5: Confirmed | P5: medium | Q5: One-wall kitchen | Per LF carcass ~$50/LF (3 cabinets × $100-130 / 8.5 LF) | Ціна збір: 2026-05-28
A6: 2 | B6: Cabinetry | C6: Cabinets | D6: Wall Cabinets | E6: IKEA SEKTION 15" deep | F6: linear ft | G6: 8 | H6: 8.5 | I6: 9 | J6: 35 | K6: =IF(OR(H6="",J6="",J6=0),"",H6*J6) | L6: IKEA | M6: IKEA SEKTION wall cabinet 15" deep | N6: https://www.ikea.com/us/en/p/sektion-wall-cabinet-white-70265469/ | O6: Confirmed | P6: high | Q6: Per LF ($78 SEKTION 30" wide / 2.5 LF = $31/LF). Mid $35 | Ціна збір: 2026-05-28
A7: 3 | B7: Cabinetry | C7: Cabinets | D7: Tall / Pantry Cabinet | E7: SEKTION 24" wide × 80" tall | F7: pcs | G7: 0 | H7: 1 | I7: 1 | J7: 200 | K7: =IF(OR(H7="",J7="",J7=0),"",H7*J7) | L7: IKEA | M7: IKEA SEKTION tall pantry 24"x80" | O7: TBD | P7: medium | Q7: Carcass пантри cabinet | Ціна збір: 2026-05-28
A8: 4 | B8: Cabinetry | C8: Cabinets | D8: Cabinet Doors | E8: SEKTION + AXSTAD або alternative front style | F8: set | G8: 1 | H8: 1 | I8: 1 | J8: 400 | K8: =IF(OR(H8="",J8="",J8=0),"",H8*J8) | L8: IKEA | M8: IKEA METOD/AXSTAD doors set (mix) | O8: TBD | P8: medium | Q8: US naming: SEKTION system. Front style — AXSTAD/VOXTORP/etc | 6-7 doors mix sizes | Ціна збір: 2026-05-28
A9: 5 | B9: Cabinetry | C9: Cabinets | D9: Drawer Fronts | E9: Mix sizes per IKEA planner | F9: set | G9: 1 | H9: 1 | I9: 1 | J9: 240 | K9: =IF(OR(H9="",J9="",J9=0),"",H9*J9) | L9: IKEA | M9: IKEA drawer fronts set | O9: TBD | P9: medium | Q9: 6 drawers | Ціна збір: 2026-05-28
A10: 6 | B10: Cabinetry | C10: Cabinets | D10: Hinges | E10: Soft-close hinges (UTRUSTA) | F10: pack | G10: 1 | H10: 1 | I10: 1 | J10: 40 | K10: =IF(OR(H10="",J10="",J10=0),"",H10*J10) | L10: IKEA | M10: IKEA UTRUSTA soft-close hinges pack | O10: TBD | P10: medium | Q10: | Ціна збір: 2026-05-28
A11: 7 | B11: Cabinetry | C11: Cabinets | D11: Drawer Slides | E11: Soft-close runners (MAXIMERA) | F11: set | G11: 1 | H11: 1 | I11: 1 | J11: 40 | K11: =IF(OR(H11="",J11="",J11=0),"",H11*J11) | L11: IKEA | M11: IKEA MAXIMERA soft-close drawer runners set | O11: TBD | P11: medium | Q11: | Ціна збір: 2026-05-28
A12: 8 | B12: Cabinetry | C12: Cabinets | D12: Cabinet Legs | E12: Adjustable leveling legs | F12: set | G12: 1 | H12: 1 | I12: 1 | J12: 25 | K12: =IF(OR(H12="",J12="",J12=0),"",H12*J12) | L12: IKEA | M12: IKEA adjustable leveling legs set | O12: TBD | P12: medium | Q12: | Ціна збір: 2026-05-28
A13: 9 | B13: Cabinetry | C13: Cabinets | D13: Toe-kick | E13: FÖRBÄTTRA toe-kick | F13: linear ft | G13: 8 | H13: 9 | I13: 10 | J13: 4 | K13: =IF(OR(H13="",J13="",J13=0),"",H13*J13) | L13: IKEA | M13: IKEA FÖRBÄTTRA toe-kick per LF | O13: TBD | P13: medium | Q13: | Ціна збір: 2026-05-28
A14: 10 | B14: Cabinetry | C14: Cabinets | D14: Cover Panels | E14: FÖRBÄTTRA cover panels | F14: set | G14: 1 | H14: 1 | I14: 1 | J14: 80 | K14: =IF(OR(H14="",J14="",J14=0),"",H14*J14) | L14: IKEA | M14: IKEA FÖRBÄTTRA cover panels set | O14: TBD | P14: medium | Q14: | Ціна збір: 2026-05-28
A15: 11 | B15: Cabinetry | C15: Cabinets | D15: Filler Panels | E15: FÖRBÄTTRA filler panels | F15: set | G15: 1 | H15: 1 | I15: 1 | J15: 50 | K15: =IF(OR(H15="",J15="",J15=0),"",H15*J15) | L15: IKEA | M15: IKEA FÖRBÄTTRA filler panels set | O15: TBD | P15: medium | Q15: | Ціна збір: 2026-05-28
A16: 12 | B16: Cabinetry | C16: Countertop | D16: Countertop | E16: KARLBY butcher block (BASELINE). Alt: EKBACKEN laminate (~$14/LF budget) | F16: linear ft | G16: 9 | H16: 9.5 | I16: 10 | J16: 26 | K16: =IF(OR(H16="",J16="",J16=0),"",H16*J16) | L16: IKEA | M16: IKEA KARLBY butcher block 9.5 LF | N16: https://www.ikea.com/us/en/cat/countertops-10653/ | O16: TBD | P16: medium | Q16: Choose ONE material — not both. Final cabinet+countertop price via IKEA Kitchen Planner | Per LF. ~$250 for 9.5 LF. EKBACKEN laminate cheaper ~$14/LF | Ціна збір: 2026-05-28
A17: 13 | B17: Cabinetry | C17: Backsplash | D17: Backsplash Tile | E17: Subway tile 3x6 ceramic — або mosaic | F17: sq ft | G17: 25 | H17: 30 | I17: 35 | J17: 4 | K17: =IF(OR(H17="",J17="",J17=0),"",H17*J17) | L17: Home Depot | M17: Generic ceramic subway 3x6 white | O17: TBD | P17: medium | Q17: Per sf. $4/sf retail | Ціна збір: 2026-05-28
A18: 14 | B18: Cabinetry | C18: Fixtures | D18: Kitchen Sink | E18: HILLESJÖN single bowl 25" SS drop-in | F18: pcs | G18: 1 | H18: 1 | I18: 1 | J18: 175 | K18: =IF(OR(H18="",J18="",J18=0),"",H18*J18) | L18: IKEA / Home Depot | M18: IKEA HILLESJÖN 25" SS single bowl drop-in | O18: TBD | P18: medium | Q18: Or LANGUDDEN | Ціна збір: 2026-05-28
A19: 15 | B19: Cabinetry | C19: Fixtures | D19: Kitchen Faucet | E19: IKEA ÄLMAREN pull-down single-handle | F19: pcs | G19: 1 | H19: 1 | I19: 1 | J19: 110 | K19: =IF(OR(H19="",J19="",J19=0),"",H19*J19) | L19: IKEA / Home Depot | M19: IKEA ÄLMAREN pull-down faucet | O19: TBD | P19: medium | Q19: | Ціна збір: 2026-05-28
A20: 16 | B20: Cabinetry | C20: Hardware | D20: Handles / Knobs | E20: Modern bar pulls — 6-8 pulls | F20: set | G20: 1 | H20: 1 | I20: 1 | J20: 50 | K20: =IF(OR(H20="",J20="",J20=0),"",H20*J20) | L20: IKEA | M20: IKEA modern bar pulls set 6-8 pcs | O20: TBD | P20: medium | Q20: | Ціна збір: 2026-05-28
A21: 17 | B21: Cabinetry | C21: Lighting | D21: Under-cabinet Lighting | E21: IKEA OMLOPP LED strip set. Driver — cross-ref Phase 6 r38 | F21: set | G21: 0 | H21: 1 | I21: 1 | J21: 80 | K21: =IF(OR(H21="",J21="",J21=0),"",H21*J21) | L21: IKEA / Home Depot | M21: IKEA OMLOPP LED under-cabinet set | O21: TBD | P21: medium | Q21: LED driver counted в Phase 6 r38 | Driver окремо в Phase 6 r38 | Ціна збір: 2026-05-28
A22: 18 | B22: Cabinetry | C22: Plumbing | D22: Kitchen Sink Plumbing Kit | E22: Basket strainer + tailpiece + drain assembly | F22: set | G22: 1 | H22: 1 | I22: 1 | J22: 20 | K22: =IF(OR(H22="",J22="",J22=0),"",H22*J22) | L22: Home Depot | M22: Oatey sink drain assembly + strainer kit | O22: Confirmed | P22: medium | Q22: Phase 5 = rough-in to wall. Phase 12 = finish connection under sink | ДОДАНО | Ціна збір: 2026-05-28
A23: 19 | B23: Cabinetry | C23: Plumbing | D23: Sink Mounting Hardware | E23: Drop-in clips або undermount brackets | F23: set | G23: 1 | H23: 1 | I23: 1 | J23: 15 | K23: =IF(OR(H23="",J23="",J23=0),"",H23*J23) | L23: Home Depot | M23: Generic drop-in sink clips або undermount brackets | O23: Confirmed | P23: medium | Q23: ДОДАНО | ДОДАНО | Ціна збір: 2026-05-28
A24: 20 | B24: Cabinetry | C24: Backsplash | D24: Tile Adhesive + Grout | E24: Mastic + grout + sealant | F24: set | G24: 1 | H24: 1 | I24: 1 | J24: 30 | K24: =IF(OR(H24="",J24="",J24=0),"",H24*J24) | L24: Home Depot | M24: Custom Building Products tile mastic + grout set | O24: Confirmed | P24: medium | Q24: ДОДАНО | ДОДАНО | Ціна збір: 2026-05-28
A25: 21 | B25: Cabinetry | C25: Backsplash | D25: Backsplash Trim / Edge Mouldings | E25: Bullnose або metal edges | F25: set | G25: 1 | H25: 1 | I25: 1 | J25: 30 | K25: =IF(OR(H25="",J25="",J25=0),"",H25*J25) | L25: Home Depot | M25: Generic bullnose backsplash trim set | O25: Confirmed | P25: medium | Q25: ДОДАНО | ДОДАНО | Ціна збір: 2026-05-28
A26: 22 | B26: Cabinetry | C26: Sealants | D26: Countertop Silicone Sealant | E26: Kitchen-safe 100% silicone | F26: tubes | G26: 1 | H26: 1 | I26: 2 | J26: 8 | K26: =IF(OR(H26="",J26="",J26=0),"",H26*J26) | L26: Home Depot | M26: GE Silicone II Kitchen 100% silicone | O26: Confirmed | P26: medium | Q26: ДОДАНО | ДОДАНО: per tube | Ціна збір: 2026-05-28
A27: 23 | B27: Cabinetry | C27: Cabinets | D27: Cabinet Shelves / Organizers Allowance | E27: Drawer inserts + extra shelves | F27: set | G27: 0 | H27: 0 | I27: 1 | J27: 60 | K27: =IF(OR(H27="",J27="",J27=0),"",H27*J27) | L27: IKEA | M27: IKEA RATIONELL/SEKTION extras (Optional) | O27: Optional | P27: medium | Q27: ДОДАНО | ДОДАНО: drawer inserts, extra shelves | Ціна збір: 2026-05-28
A28: 24 | B28: Cabinetry | C28: Cabinets | D28: Cabinet Feet / Risers Allowance | E28: Custom heights | F28: set | G28: 0 | H28: 0 | I28: 1 | J28: 30 | K28: =IF(OR(H28="",J28="",J28=0),"",H28*J28) | L28: IKEA | M28: IKEA cabinet feet/risers allowance (Optional) | O28: Optional | P28: medium | Q28: ДОДАНО | ДОДАНО | Ціна збір: 2026-05-28
... A36: 32 | B36: Cabinetry | C36: Cross-ref | D36: Dishwasher Air Gap (CA UPC) | E36: Cross-ref Phase 5 r37 — не дублювати | F36: set | G36: 0 | H36: 0 | I36: 0 | J36: 0 | K36: =IF(OR(H36="",J36="",J36=0),"",H36*J36) | L36: — | M36: Cross-ref Phase 5 r37 — qty 0 | O36: Confirmed | P36: high | Q36: ДОДАНО: вже у Phase 5 r37 Dishwasher Branch + Air Gap | ДОДАНО: dishwasher air gap — already in Phase 5 | Ціна збір: 2026-05-28
C38: ПІДСУМОК ФАЗИ | K38: =SUM(K5:K36)

Sheet 14_Bathroom_Fixtures
A1: Phase 13 — Bathroom Fixtures (§14)
A2: Prefab shower + toilet + vanity + accessories + fan
A4: # | B4: Phase | C4: Категорія | D4: Item / Material | E4: Spec / Опис | F4: Unit | G4: Qty (Low) | H4: Qty (Mid) | I4: Qty (High) | J4: Unit Price ($) | K4: Total ($) | L4: Source | M4: SKU / Model | N4: URL | O4: Status | P4: Confidence | Q4: Notes
A5: 1 | B5: Finish — Fixtures | C5: Shower | D5: Prefab Shower Base 32×40 | E5: Acrylic/fiberglass | F5: pcs | G5: 1 | H5: 1 | I5: 1 | J5: 275 | K5: =IF(OR(H5="",J5="",J5=0),"",H5*J5) | L5: Home Depot | M5: MAAX/Sterling prefab shower base 32×40 | O5: Confirmed | P5: medium | Q5: MAAX/Sterling style | Acrylic/fiberglass base only | Ціна збір: 2026-05-28
A6: 2 | B6: Finish — Fixtures | C6: Shower | D6: Prefab Shower Wall System | E6: DEPRECATED — заміняємо tile (r28-r34) | F6: set | G6: 0 | H6: 0 | I6: 0 | J6: 0 | K6: =IF(OR(H6="",J6="",J6=0),"",H6*J6) | L6: — | M6: DEPRECATED — заміняємо tile shower | O6: Confirmed | P6: high | Q6: Removed: заміняємо на tile shower walls | Removed: заміняємо на tile shower walls (r38+) | Ціна збір: 2026-05-28
A7: 3 | B7: Finish — Fixtures | C7: Shower | D7: Shower Drain (cross-ref Phase 5) | E7: Cross-ref Phase 5 r33 — не дублювати | F7: pcs | G7: 0 | H7: 0 | I7: 0 | J7: 0 | K7: =IF(OR(H7="",J7="",J7=0),"",H7*J7) | L7: — | M7: Cross-ref Phase 5 r33 | O7: Confirmed | P7: high | Q7: Drain body+strainer assembly у Phase 5 r33 | Shower drain — Phase 5 | Ціна збір: 2026-05-28
A8: 4 | B8: Finish — Fixtures | C8: Shower | D8: Shower Valve Body (cross-ref Phase 5) | E8: Cross-ref Phase 5 r32 — не дублювати | F8: pcs | G8: 0 | H8: 0 | I8: 0 | J8: 0 | K8: =IF(OR(H8="",J8="",J8=0),"",H8*J8) | L8: — | M8: Cross-ref Phase 5 r32 | O8: Confirmed | P8: high | Q8: Rough-in valve body у Phase 5 r32 | Shower rough-in valve body — Phase 5 | Ціна збір: 2026-05-28
A9: 5 | B9: Finish — Fixtures | C9: Shower | D9: Shower Trim Kit | E9: Handle + escutcheon — finish stage | F9: set | G9: 1 | H9: 1 | I9: 1 | J9: 80 | K9: =IF(OR(H9="",J9="",J9=0),"",H9*J9) | L9: Home Depot | M9: Delta MultiChoice trim kit | O9: TBD | P9: medium | Q9: Visible trim (different from Phase 5 valve body) | Visible handle + escutcheon plate | Ціна збір: 2026-05-28
A10: 6 | B10: Finish — Fixtures | C10: Shower | D10: Shower Head | E10: Fixed або handheld | F10: pcs | G10: 1 | H10: 1 | I10: 1 | J10: 50 | K10: =IF(OR(H10="",J10="",J10=0),"",H10*J10) | L10: Home Depot | M10: Generic shower head fixed або handheld | O10: TBD | P10: medium | Q10: | Ціна збір: 2026-05-28
A11: 7 | B11: Finish — Fixtures | C11: Shower | D11: Waterproof Caulk / Sealant | E11: Silicone bath | F11: tubes | G11: 2 | H11: 3 | I11: 4 | J11: 7 | K11: =IF(OR(H11="",J11="",J11=0),"",H11*J11) | L11: Home Depot | M11: GE Silicone II 100% silicone bath caulk | O11: Confirmed | P11: medium | Q11: Per tube | Ціна збір: 2026-05-28
A12: 8 | B12: Finish — Fixtures | C12: Toilet | D12: Toilet | E12: 2-piece elongated chair-height | F12: pcs | G12: 1 | H12: 1 | I12: 1 | J12: 200 | K12: =IF(OR(H12="",J12="",J12=0),"",H12*J12) | L12: Home Depot | M12: Glacier Bay 2-piece elongated chair-height | O12: Confirmed | P12: medium | Q12: Basic toilet $150-300 | Ціна збір: 2026-05-28
A13: 9 | B13: Finish — Fixtures | C13: Toilet | D13: Toilet Supply Line | E13: Flex braided | F13: pcs | G13: 1 | H13: 1 | I13: 1 | J13: 8 | K13: =IF(OR(H13="",J13="",J13=0),"",H13*J13) | L13: Home Depot | M13: Generic braided supply line 12" | O13: Confirmed | P13: medium | Q13: | Ціна збір: 2026-05-28
A14: 10 | B14: Finish — Fixtures | C14: Vanity | D14: Vanity Cabinet 24" | E14: Home Decorators / Glacier Bay | F14: pcs | G14: 1 | H14: 1 | I14: 1 | J14: 200 | K14: =IF(OR(H14="",J14="",J14=0),"",H14*J14) | L14: Home Depot / IKEA | M14: Home Decorators Doveton 24" vanity | N14: https://www.homedepot.com/p/Home-Decorators-Collection-Doveton-24-in-Single-Sink-Freestanding-White-Bath-Vanity-with-White-Engineered-Marble-Top-Assembled-Doveton-24W/324252515 | O14: Confirmed | P14: high | Q14: HD combo $349-449 includes top+sink+backsplash | $299-349 combo з top+sink (split here as r14+r15) | Ціна збір: 2026-05-28
A15: 11 | B15: Finish — Fixtures | C15: Vanity | D15: Vanity Top / Sink | E15: Integrated cultured marble / quartz | F15: pcs | G15: 1 | H15: 1 | I15: 1 | J15: 150 | K15: =IF(OR(H15="",J15="",J15=0),"",H15*J15) | L15: Home Depot / IKEA | M15: Engineered marble top + integrated sink | O15: Confirmed | P15: medium | Q15: Часто sold з cabinet в combo | Combined HD price з vanity | Ціна збір: 2026-05-28
A16: 12 | B16: Finish — Fixtures | C16: Vanity | D16: Vanity Faucet | E16: Single-handle | F16: pcs | G16: 1 | H16: 1 | I16: 1 | J16: 100 | K16: =IF(OR(H16="",J16="",J16=0),"",H16*J16) | L16: Home Depot | M16: Glacier Bay/Moen single-handle vanity faucet | O16: Confirmed | P16: medium | Q16: | Ціна збір: 2026-05-28
A17: 13 | B17: Finish — Fixtures | C17: Vanity | D17: P-trap (cross-ref Phase 5) | E17: Cross-ref Phase 5 r14 — qty 0 | F17: pcs | G17: 0 | H17: 0 | I17: 0 | J17: 8 | K17: =IF(OR(H17="",J17="",J17=0),"",H17*J17) | L17: — | M17: Generic 1.5" P-trap kit | O17: Confirmed | P17: medium | Q17: P-trap включений у Phase 5 r14 (4 P-traps total: shower+vanity+kitchen+washer) | Bathroom small allowance | Ціна збір: 2026-05-28
A18: 14 | B18: Finish — Fixtures | C18: Vanity | D18: Shut-off Valves (cross-ref Phase 5) | E18: Cross-ref Phase 5 r8 — qty 0 | F18: pcs | G18: 0 | H18: 0 | I18: 0 | J18: 7 | K18: =IF(OR(H18="",J18="",J18=0),"",H18*J18) | L18: — | M18: Apollo PEX angle stop 1/2" | O18: Confirmed | P18: medium | Q18: Shut-offs включені у Phase 5 r8 (19 total covers all fixtures) | Per valve | Ціна збір: 2026-05-28
A19: 15 | B19: Finish — Fixtures | C19: Accessories | D19: Mirror | E19: Frameless або basic framed | F19: pcs | G19: 1 | H19: 1 | I19: 1 | J19: 60 | K19: =IF(OR(H19="",J19="",J19=0),"",H19*J19) | L19: Home Depot / IKEA | M19: Generic mirror 24x30 framed | O19: Confirmed | P19: medium | Q19: | Ціна збір: 2026-05-28
A20: 16 | B20: Finish — Fixtures | C20: Accessories | D20: Towel Bar / Hooks | E20: Set 24" bar + 2 hooks | F20: set | G20: 1 | H20: 1 | I20: 1 | J20: 40 | K20: =IF(OR(H20="",J20="",J20=0),"",H20*J20) | L20: Home Depot / IKEA | M20: Generic 24" towel bar + 2 hooks set | O20: Confirmed | P20: medium | Q20: | Ціна збір: 2026-05-28
A21: 17 | B21: Finish — Fixtures | C21: Accessories | D21: Toilet Paper Holder | F21: pcs | G21: 1 | H21: 1 | I21: 1 | J21: 20 | K21: =IF(OR(H21="",J21="",J21=0),"",H21*J21) | L21: Home Depot / IKEA | M21: Generic toilet paper holder | O21: Confirmed | P21: medium | Q21: | Ціна збір: 2026-05-28
A22: 18 | B22: Finish — Fixtures | C22: Ventilation | D22: Bathroom Exhaust Fan | E22: 80 CFM з timer compatible | F22: pcs | G22: 1 | H22: 1 | I22: 1 | J22: 100 | K22: =IF(OR(H22="",J22="",J22=0),"",H22*J22) | L22: Home Depot | M22: Broan 80 CFM exhaust fan | O22: Confirmed | P22: medium | Q22: Timer switch у Phase 6 r16 | Energy Star bath fan | Ціна збір: 2026-05-28
A23: 19 | B23: Finish — Fixtures | C23: Ventilation | D23: Fan Duct + Wall/Roof Cap | E23: Flex duct + exterior cap | F23: set | G23: 1 | H23: 1 | I23: 1 | J23: 30 | K23: =IF(OR(H23="",J23="",J23=0),"",H23*J23) | L23: Home Depot | M23: Generic 4" flex duct + wall cap | O23: Confirmed | P23: medium | Q23: | Ціна збір: 2026-05-28
A24: 20 | B24: Finish — Fixtures | C24: Shower | D24: Shower Curtain Rod + Curtain | E24: Budget enclosure (glass door alternative $300-800) | F24: set | G24: 1 | H24: 1 | I24: 1 | J24: 35 | K24: =IF(OR(H24="",J24="",J24=0),"",H24*J24) | L24: Home Depot / IKEA | M24: Generic shower curtain rod + curtain | O24: Confirmed | P24: medium | Q24: ДОДАНО: budget option. Glass door — Optional upgrade | ДОДАНО: budget enclosure | Ціна збір: 2026-05-28
A25: 21 | B25: Finish — Fixtures | C25: Toilet | D25: Toilet Wax Ring + Sealing | E25: Mandatory install component | F25: set | G25: 1 | H25: 1 | I25: 1 | J25: 7 | K25: =IF(OR(H25="",J25="",J25=0),"",H25*J25) | L25: Home Depot | M25: Oatey wax ring + sealing kit | O25: Confirmed | P25: medium | Q25: ДОДАНО | ДОДАНО | Ціна збір: 2026-05-28
A26: 22 | B26: Finish — Fixtures | C26: Toilet | D26: Toilet Seat | E26: Часто NOT included з toilet | F26: pcs | G26: 1 | H26: 1 | I26: 1 | J26: 30 | K26: =IF(OR(H26="",J26="",J26=0),"",H26*J26) | L26: Home Depot | M26: Bemis/generic toilet seat | O26: Confirmed | P26: medium | Q26: ДОДАНО | ДОДАНО: NOT included з toilet | Ціна збір: 2026-05-28
A27: 23 | B27: Finish — Fixtures | C27: Toilet | D27: Toilet Bolts / Caps | E27: Small allowance | F27: set | G27: 1 | H27: 1 | I27: 1 | J27: 5 | K27: =IF(OR(H27="",J27="",J27=0),"",H27*J27) | L27: Home Depot | M27: Generic toilet bolts + caps | O27: Confirmed | P27: medium | Q27: ДОДАНО | ДОДАНО | Ціна збір: 2026-05-28
A28: 24 | B28: Finish — Fixtures | C28: Vanity | D28: Vanity Mount Hardware | E28: Wall anchors якщо потрібно | F28: set | G28: 1 | H28: 1 | I28: 1 | J28: 15 | K28: =IF(OR(H28="",J28="",J28=0),"",H28*J28) | L28: Home Depot | M28: Generic vanity wall mount anchors | O28: Confirmed | P28: medium | Q28: ДОДАНО | ДОДАНО | Ціна збір: 2026-05-28
A29: 25 | B29: Finish — Fixtures | C29: Vanity | D29: Vanity Backsplash Allowance (Optional) | E29: Small tile або solid | F29: set | G29: 0 | H29: 0 | I29: 1 | J29: 50 | K29: =IF(OR(H29="",J29="",J29=0),"",H29*J29) | L29: Home Depot | M29: Vanity backsplash tile (Optional) | O29: Optional | P29: medium | Q29: ДОДАНО: usually included з vanity combo | ДОДАНО | Ціна збір: 2026-05-28
A30: 26 | B30: Finish — Fixtures | C30: Accessories | D30: Robe Hook (Optional) | E30: 1-2 hooks | F30: pcs | G30: 0 | H30: 0 | I30: 2 | J30: 15 | K30: =IF(OR(H30="",J30="",J30=0),"",H30*J30) | L30: Home Depot / IKEA | M30: Generic robe hook | O30: Optional | P30: medium | Q30: ДОДАНО | ДОДАНО | Ціна збір: 2026-05-28
A31: 27 | B31: Finish — Fixtures | C31: Vanity | D31: Vanity Pop-up Drain Assembly | E31: Якщо faucet не включає drain | F31: pcs | G31: 0 | H31: 1 | I31: 1 | J31: 15 | K31: =IF(OR(H31="",J31="",J31=0),"",H31*J31) | L31: Home Depot | M31: Generic vanity pop-up drain assembly | O31: Confirmed | P31: medium | Q31: ДОДАНО (review) | ДОДАНО (review) | Ціна збір: 2026-05-28
A32: 28 | B32: Finish — Fixtures | C32: Vanity | D32: Vanity Faucet Supply Lines | E32: Flex lines від shut-off до faucet | F32: pcs | G32: 2 | H32: 2 | I32: 2 | J32: 5 | K32: =IF(OR(H32="",J32="",J32=0),"",H32*J32) | L32: Home Depot | M32: Generic flex faucet supply line | O32: Confirmed | P32: medium | Q32: ДОДАНО (review) | ДОДАНО (review): per piece, mid 2 | Ціна збір: 2026-05-28
A33: 29 | B33: Finish — Fixtures | C33: Shower | D33: Shower Arm + Flange | E33: Якщо не included з shower head | F33: pcs | G33: 1 | H33: 1 | I33: 1 | J33: 15 | K33: =IF(OR(H33="",J33="",J33=0),"",H33*J33) | L33: Home Depot | M33: Generic shower arm + flange | O33: Confirmed | P33: medium | Q33: ДОДАНО (review) | ДОДАНО (review) | Ціна збір: 2026-05-28
... A46: 42 | B46: Finish — Fixtures | C46: Tile - Waterproofing | D46: Extra RedGard (floor + corners) | E46: Additional quart для shower floor + transitions | F46: qt | G46: 1 | H46: 1 | I46: 1 | J46: 30 | K46: =IF(OR(H46="",J46="",J46=0),"",H46*J46) | L46: Home Depot | M46: RedGard quart (floor + corners) | O46: Confirmed | P46: medium | Q46: ДОДАНО: окрема quart RedGard | ДОДАНО: окремий quart | Ціна збір: 2026-05-28
C48: ПІДСУМОК ФАЗИ | K48: =SUM(K5:K46)

Sheet 15_Closet_System
A1: Phase 14 — Closet System (§13)
A2: IKEA PAX/BOAXEL для walk-in 6×5'6"
A4: # | B4: Phase | C4: Категорія | D4: Item / Material | E4: Spec / Опис | F4: Unit | G4: Qty (Low) | H4: Qty (Mid) | I4: Qty (High) | J4: Unit Price ($) | K4: Total ($) | L4: Source | M4: SKU / Model | N4: URL | O4: Status | P4: Confidence | Q4: Notes
A5: 1 | B5: Furnishing | C5: Storage System | D5: IKEA BOAXEL wardrobe combination | E5: BOAXEL 49 1/8" main wall combo | F5: system | G5: 1 | H5: 1 | I5: 1 | J5: 262 | K5: =IF(OR(H5="",J5="",J5=0),"",H5*J5) | L5: IKEA | M5: IKEA BOAXEL 49" wardrobe combination | N5: https://www.ikea.com/us/en/p/boaxel-wardrobe-combination-white-s19332373/ | O5: Confirmed | P5: high | Q5: BASELINE = BOAXEL. PAX — separate upgrade scenario (r15), не входить у поточний total | BOAXEL combo includes frame+shelves+rail | Ціна збір: 2026-05-28
A6: 2 | B6: Furnishing | C6: Storage System | D6: Additional Hanging Rods | E6: Extra BOAXEL clothes rails для second wall | F6: pcs | G6: 0 | H6: 1 | I6: 2 | J6: 10 | K6: =IF(OR(H6="",J6="",J6=0),"",H6*J6) | L6: IKEA | M6: IKEA BOAXEL clothes rail 24"-31" | O6: TBD | P6: medium | Q6: Per pc | Ціна збір: 2026-05-28
A7: 3 | B7: Furnishing | C7: Storage System | D7: Additional Shelves | E7: BOAXEL extra shelves для second wall | F7: pcs | G7: 2 | H7: 3 | I7: 5 | J7: 15 | K7: =IF(OR(H7="",J7="",J7=0),"",H7*J7) | L7: IKEA | M7: IKEA BOAXEL extra shelf | O7: TBD | P7: medium | Q7: Per pc | Ціна збір: 2026-05-28
A8: 4 | B8: Furnishing | C8: Storage System | D8: Drawers (mesh baskets) | E8: BOAXEL mesh basket drawers | F8: pcs | G8: 2 | H8: 4 | I8: 6 | J8: 20 | K8: =IF(OR(H8="",J8="",J8=0),"",H8*J8) | L8: IKEA | M8: IKEA BOAXEL mesh basket drawer | O8: TBD | P8: medium | Q8: Per pc | Ціна збір: 2026-05-28
A9: 5 | B9: Furnishing | C9: Storage System | D9: Shoe Storage | E9: BOAXEL shoe shelves або freestanding rack | F9: pcs | G9: 1 | H9: 1 | I9: 2 | J9: 30 | K9: =IF(OR(H9="",J9="",J9=0),"",H9*J9) | L9: IKEA | M9: IKEA BOAXEL shoe shelf set | O9: TBD | P9: medium | Q9: | Ціна збір: 2026-05-28
A10: 6 | B10: Furnishing | C10: Accessories | D10: Mirror (closet) | E10: Wall-mounted full-length | F10: pcs | G10: 0 | H10: 1 | I10: 1 | J10: 40 | K10: =IF(OR(H10="",J10="",J10=0),"",H10*J10) | L10: IKEA | M10: IKEA wall-mounted mirror full-length | O10: TBD | P10: medium | Q10: Optional but Mid 1 | Ціна збір: 2026-05-28
A11: 7 | B11: Furnishing | C11: Storage System | D11: BOAXEL Wall Rails (additional) | E11: Для second wall mounting | F11: pcs | G11: 1 | H11: 2 | I11: 3 | J11: 20 | K11: =IF(OR(H11="",J11="",J11=0),"",H11*J11) | L11: IKEA | M11: IKEA BOAXEL wall rail (additional) | O11: Confirmed | P11: medium | Q11: ДОДАНО | ДОДАНО: per rail | Ціна збір: 2026-05-28
A12: 8 | B12: Furnishing | C12: Hardware | D12: Mounting Hardware (Stud Screws + Anchors) | E12: Stud-mounted screws у studs/blocking + drywall anchors де dozvoleno | F12: set | G12: 1 | H12: 1 | I12: 1 | J12: 15 | K12: =IF(OR(H12="",J12="",J12=0),"",H12*J12) | L12: Home Depot | M12: Generic drywall anchors + screws set | O12: Confirmed | P12: medium | Q12: Stud/blocking-mounted preferred. Drywall anchors тільки де дозволяє IKEA spec | ДОДАНО | Ціна збір: 2026-05-28
A13: 9 | B13: Furnishing | C13: Accessories | D13: Drawer Organizers / Dividers (Optional) | E13: IKEA KOMPLEMENT inserts | F13: set | G13: 0 | H13: 0 | I13: 1 | J13: 20 | K13: =IF(OR(H13="",J13="",J13=0),"",H13*J13) | L13: IKEA | M13: IKEA KOMPLEMENT drawer inserts (Optional) | O13: Optional | P13: medium | Q13: ДОДАНО | ДОДАНО | Ціна збір: 2026-05-28
A14: 10 | B14: Furnishing | C14: Accessories | D14: Closet Accessories (Optional) | E14: Valet hook, belt rack, hangers | F14: set | G14: 0 | H14: 0 | I14: 1 | J14: 15 | K14: =IF(OR(H14="",J14="",J14=0),"",H14*J14) | L14: IKEA | M14: Closet accessories valet/belt rack (Optional) | O14: Optional | P14: medium | Q14: ДОДАНО | ДОДАНО | Ціна збір: 2026-05-28
A15: 11 | B15: Furnishing | C15: Storage System | D15: BOAXEL Uprights / Vertical Rails | E15: Required для full system mounting | F15: pcs | G15: 1 | H15: 2 | I15: 3 | J15: 15 | K15: =IF(OR(H15="",J15="",J15=0),"",H15*J15) | L15: IKEA | M15: IKEA BOAXEL upright / vertical rail | O15: Confirmed | P15: medium | Q15: ДОДАНО (review): high pri — без uprights system не складається | ДОДАНО (review): per upright | Ціна збір: 2026-05-28
A16: 12 | B16: Furnishing | C16: Storage System | D16: BOAXEL Shelf / Rod Brackets | E16: Brackets для additional shelves/rods | F16: pack | G16: 1 | H16: 1 | I16: 2 | J16: 5 | K16: =IF(OR(H16="",J16="",J16=0),"",H16*J16) | L16: IKEA | M16: IKEA BOAXEL shelf/rod brackets pack | O16: Confirmed | P16: medium | Q16: ДОДАНО (review) | ДОДАНО (review) | Ціна збір: 2026-05-28
A17: 13 | B17: Furnishing | C17: Storage System | D17: Second-wall BOAXEL Add-on | E17: Complete add-on для short wall 5'6" | F17: system | G17: 0 | H17: 1 | I17: 1 | J17: 80 | K17: =IF(OR(H17="",J17="",J17=0),"",H17*J17) | L17: IKEA | M17: IKEA BOAXEL second-wall add-on combo | O17: Confirmed | P17: medium | Q17: ДОДАНО (review): краще ніж loose components | ДОДАНО (review): для 5'6" wall | Ціна збір: 2026-05-28
... A21: 17 | B21: Furnishing | C21: Accessories | D21: Hangers Set (Optional) | E21: Якщо ready-to-use furnishing | F21: set | G21: 0 | H21: 0 | I21: 1 | J21: 20 | K21: =IF(OR(H21="",J21="",J21=0),"",H21*J21) | L21: IKEA | M21: Generic plastic hangers set 50pc | O21: Optional | P21: medium | Q21: ДОДАНО (review) | ДОДАНО (review) | Ціна збір: 2026-05-28
C23: ПІДСУМОК ФАЗИ | K23: =SUM(K5:K21)

Sheet 16_Water_Heater
A1: Phase 15 — Water Heater & Utility (§16)
A2: Electric tank 20-30 gal + seismic strap + utility closet
A4: # | B4: Phase | C4: Категорія | D4: Item / Material | E4: Spec / Опис | F4: Unit | G4: Qty (Low) | H4: Qty (Mid) | I4: Qty (High) | J4: Unit Price ($) | K4: Total ($) | L4: Source | M4: SKU / Model | N4: URL | O4: Status | P4: Confidence | Q4: Notes
A5: 1 | B5: MEP — Water Heater | C5: Water Heater | D5: Electric Tank Water Heater | E5: Rheem Performance 30 gal short 240V | F5: pcs | G5: 1 | H5: 1 | I5: 1 | J5: 429 | K5: =IF(OR(H5="",J5="",J5=0),"",H5*J5) | L5: Home Depot | M5: Rheem Performance 30 Gal Short 240V | N5: https://www.homedepot.com/p/Rheem-Performance-30-Gal-4500-Watt-Elements-Short-Electric-Water-Heater-with-6-Year-Tank-Warranty-and-240-Volt-XE30S06ST45U1/326590405 | O5: Confirmed | P5: high | Q5: Rheem XE30S06ST45U1 short tank. §33.7 verify sizing + verify clearance — 30 gal must fit utility closet з service access | $379 promo / $429 regular. 4500W 6-yr warranty | Ціна збір: 2026-05-28
A6: 2 | B6: MEP — Water Heater | C6: Water Heater | D6: Water Heater Pan | E6: 24-26" round metal/plastic | F6: pcs | G6: 1 | H6: 1 | I6: 1 | J6: 25 | K6: =IF(OR(H6="",J6="",J6=0),"",H6*J6) | L6: Home Depot | M6: Camco 24" round WH pan | O6: Confirmed | P6: medium | Q6: Catch leak protection | | Ціна збір: 2026-05-28
A7: 3 | B7: MEP — Water Heater | C7: Water Heater | D7: Pan Drain Line | E7: 3/4" PVC до termination | F7: ft | G7: 5 | H7: 10 | I7: 15 | J7: 5 | K7: =IF(OR(H7="",J7="",J7=0),"",H7*J7) | L7: Home Depot | M7: 3/4" PVC drain pipe per ft | O7: Confirmed | P7: medium | Q7: 3/4" PVC consistent. Final size by plumber/product instructions. До exterior wall or floor drain | 3/4" consistent з spec | Ціна збір: 2026-05-28
A8: 4 | B8: MEP — Water Heater | C8: Water Heater | D8: Flex Connectors (cross-ref Phase 5) | E8: Phase 5 r20 WH Connection Kit — не дублювати | F8: pcs | G8: 0 | H8: 0 | I8: 0 | J8: 0 | K8: =IF(OR(H8="",J8="",J8=0),"",H8*J8) | L8: — | M8: Cross-ref Phase 5 r20 | O8: Confirmed | P8: high | Q8: Cross-ref Phase 5 r20 $50 | Flex connectors у Phase 5 WH Connection Kit | Ціна збір: 2026-05-28
A9: 5 | B9: MEP — Water Heater | C9: Water Heater | D9: Shut-off Valves WH (cross-ref Phase 5) | E9: Phase 5 r8 (19 total) — не дублювати | F9: pcs | G9: 0 | H9: 0 | I9: 0 | J9: 0 | K9: =IF(OR(H9="",J9="",J9=0),"",H9*J9) | L9: — | M9: Cross-ref Phase 5 r8 | O9: Confirmed | P9: high | Q9: Cross-ref Phase 5 r8 | Shut-offs у Phase 5 (19 total) | Ціна збір: 2026-05-28
A10: 6 | B10: MEP — Water Heater | C10: Water Heater | D10: T&P Relief Valve Discharge Pipe | E10: Cu 3/4" rigid pipe | F10: ft | G10: 3 | H10: 5 | I10: 7 | J10: 5 | K10: =IF(OR(H10="",J10="",J10=0),"",H10*J10) | L10: Home Depot | M10: Cu 3/4" T&P discharge pipe per ft | O10: Confirmed | P10: medium | Q10: | Ціна збір: 2026-05-28
A11: 7 | B11: MEP — Water Heater | C11: Water Heater | D11: Expansion Tank | E11: If required by code | F11: pcs | G11: 0 | H11: 1 | I11: 1 | J11: 50 | K11: =IF(OR(H11="",J11="",J11=0),"",H11*J11) | L11: Home Depot | M11: Watts thermal expansion tank | O11: TBD | P11: medium | Q11: Verify Menlo Park code | If req'd by code | Ціна збір: 2026-05-28
A12: 8 | B12: MEP — Water Heater | C12: Water Heater | D12: Seismic Strapping Kit | E12: CA mandatory — top + bottom straps | F12: set | G12: 1 | H12: 1 | I12: 1 | J12: 25 | K12: =IF(OR(H12="",J12="",J12=0),"",H12*J12) | L12: Home Depot | M12: Holdrite/generic seismic strap kit | O12: Confirmed | P12: medium | Q12: California code | CA mandatory | Ціна збір: 2026-05-28
A13: 9 | B13: MEP — Water Heater | C13: Closet Construction | D13: Access / Louvered Door (cross-ref Phase 4) | E13: Phase 4 r11 Utility Closet Door — не дублювати | F13: pcs | G13: 0 | H13: 0 | I13: 0 | J13: 0 | K13: =IF(OR(H13="",J13="",J13=0),"",H13*J13) | L13: — | M13: Cross-ref Phase 4 r11 | O13: Confirmed | P13: high | Q13: Cross-ref Phase 4 r11 $80 | Utility closet door already у Phase 4 $80 | Ціна збір: 2026-05-28
A14: 10 | B14: MEP — Water Heater | C14: Closet Construction | D14: Ventilation Grille | E14: Air circulation для closet | F14: pcs | G14: 1 | H14: 1 | I14: 1 | J14: 20 | K14: =IF(OR(H14="",J14="",J14=0),"",H14*J14) | L14: Home Depot | M14: Generic ventilation louver grille | O14: Confirmed | P14: medium | Q14: | Ціна збір: 2026-05-28
A15: 11 | B15: MEP — Water Heater | C15: Water Heater | D15: Pan Drain Termination | E15: End fitting + exterior cap | F15: set | G15: 1 | H15: 1 | I15: 1 | J15: 15 | K15: =IF(OR(H15="",J15="",J15=0),"",H15*J15) | L15: Home Depot | M15: Generic pan drain termination + cap | O15: Confirmed | P15: medium | Q15: ДОДАНО: where pipe ends | ДОДАНО | Ціна збір: 2026-05-28
A16: 12 | B16: MEP — Water Heater | C16: Water Heater | D16: T&P Valve Replacement (Optional) | E16: Часто включений з WH | F16: pcs | G16: 0 | H16: 0 | I16: 1 | J16: 25 | K16: =IF(OR(H16="",J16="",J16=0),"",H16*J16) | L16: Home Depot | M16: Watts T&P relief valve replacement | O16: Optional | P16: medium | Q16: ДОДАНО | ДОДАНО: usually included з WH | Ціна збір: 2026-05-28
A17: 13 | B17: MEP — Water Heater | C17: Water Heater | D17: Dielectric Union Fittings | E17: Required для steel/copper joint | F17: pcs | G17: 1 | H17: 2 | I17: 2 | J17: 7 | K17: =IF(OR(H17="",J17="",J17=0),"",H17*J17) | L17: Home Depot | M17: Watts dielectric union 3/4" | O17: Confirmed | P17: medium | Q17: ДОДАНО | ДОДАНО: per piece, qty 2 | Ціна збір: 2026-05-28
... A21: 17 | B21: MEP — Water Heater | C21: Cross-ref | D21: WH Electrical Whip / Hardwire (Phase 6) | E21: Phase 6 — не дублювати | F21: — | G21: 0 | H21: 0 | I21: 0 | J21: 0 | K21: =IF(OR(H21="",J21="",J21=0),"",H21*J21) | L21: — | M21: Cross-ref Phase 6 — qty 0 | O21: Confirmed | P21: high | Q21: ДОДАНО (review): WH typically hardwired через Phase 6 r9 240V cable + r6 30A breaker | ДОДАНО (review): WH electrical у Phase 6 | Ціна збір: 2026-05-28
C23: ПІДСУМОК ФАЗИ | K23: =SUM(K5:K21)

Sheet 17_Appliances
A1: Phase 16 — Appliances (§28)
A2: 5 kitchen + washer + dryer + stacking kit
A4: # | B4: Phase | C4: Категорія | D4: Item / Material | E4: Spec / Опис | F4: Unit | G4: Qty (Low) | H4: Qty (Mid) | I4: Qty (High) | J4: Unit Price ($) | K4: Total ($) | L4: Source | M4: SKU / Model | N4: URL | O4: Status | P4: Confidence | Q4: Notes
A5: 1 | B5: Appliances | C5: Kitchen | D5: Refrigerator 24" compact | E5: Frigidaire FFTR1022QS 10 cu ft або equivalent | F5: pcs | G5: 1 | H5: 1 | I5: 1 | J5: 500 | K5: =IF(OR(H5="",J5="",J5=0),"",H5*J5) | L5: Best Buy / Amazon / HD | M5: Frigidaire FFTR1022QS 24" compact fridge | O5: Confirmed | P5: medium | Q5: 24" compact | $400-650 range. 10 cu ft compact | Ціна збір: 2026-05-28
A6: 2 | B6: Appliances | C6: Kitchen | D6: Electric Range 24" | E6: Frigidaire FFEH2422US або similar | F6: pcs | G6: 1 | H6: 1 | I6: 1 | J6: 650 | K6: =IF(OR(H6="",J6="",J6=0),"",H6*J6) | L6: Best Buy / Home Depot | M6: Frigidaire FFEH2422US 24" electric range | N6: https://www.homedepot.com/p/Frigidaire-24-in-1-9-cu-ft-4-Burner-Element-Freestanding-Electric-Range-with-Manual-Clean-in-Stainless-Steel-FFEH2422US/309052067 | O6: Confirmed | P6: medium | Q6: $500-800 range | Ціна збір: 2026-05-28
A7: 3 | B7: Appliances | C7: Kitchen | D7: Dishwasher 24" (or 18") | E7: Bosch 100 series 24" baseline. 18" compact if kitchen tight (8.5 LF) | F7: pcs | G7: 1 | H7: 1 | I7: 1 | J7: 600 | K7: =IF(OR(H7="",J7="",J7=0),"",H7*J7) | L7: Best Buy / Home Depot | M7: Bosch 100 series 24" compact dishwasher | O7: Confirmed | P7: medium | Q7: Verify final size — 18" alternative for tight one-wall kitchen | $450-900 range. Bosch quiet | Ціна збір: 2026-05-28
A8: 4 | B8: Appliances | C8: Kitchen | D8: Microwave / Range Hood Combo | E8: OTR (over-the-range) з vent fan | F8: pcs | G8: 1 | H8: 1 | I8: 1 | J8: 300 | K8: =IF(OR(H8="",J8="",J8=0),"",H8*J8) | L8: Best Buy / Amazon | M8: GE JVM3160DFBB OTR microwave/hood | O8: Confirmed | P8: medium | Q8: Needs ductwork (r13) | $200-400 range | Ціна збір: 2026-05-28
A9: 5 | B9: Appliances | C9: Kitchen | D9: Garbage Disposal | E9: InSinkErator Badger 1/3 HP — Optional | F9: pcs | G9: 0 | H9: 0 | I9: 1 | J9: 115 | K9: =IF(OR(H9="",J9="",J9=0),"",H9*J9) | L9: Home Depot | M9: InSinkErator Badger 1/3 HP disposal | O9: Optional | P9: medium | Q9: Per ТЗ §28.1 optional | Qty 0 baseline — Optional per ТЗ | Ціна збір: 2026-05-28
A10: 6 | B10: Appliances | C10: Laundry | D10: Compact Washer 24" | E10: Bosch 500 series WAT28402UC or equivalent | F10: pcs | G10: 1 | H10: 1 | I10: 1 | J10: 1000 | K10: =IF(OR(H10="",J10="",J10=0),"",H10*J10) | L10: Special Order | M10: Bosch 500 WAT28402UC 24" front-load | O10: Confirmed | P10: medium | Q10: Special Order. Lead 4-6 weeks. Model availability TBD — use equivalent current model | Special Order. $850-1,200 range | Ціна збір: 2026-05-28
A11: 7 | B11: Appliances | C11: Laundry | D11: Ventless Compact Dryer 24" | E11: Bosch 500 series heat pump or equivalent | F11: pcs | G11: 1 | H11: 1 | I11: 1 | J11: 1400 | K11: =IF(OR(H11="",J11="",J11=0),"",H11*J11) | L11: Special Order | M11: Bosch 500 WTG86402UC ventless heat pump | O11: Confirmed | P11: medium | Q11: Special Order. Ventless. Availability TBD — use equivalent | Special Order. $1,200-1,700 range | Ціна збір: 2026-05-28
A12: 8 | B12: Appliances | C12: Laundry | D12: Stacking Kit | E12: Brand-matched з washer/dryer | F12: pcs | G12: 1 | H12: 1 | I12: 1 | J12: 90 | K12: =IF(OR(H12="",J12="",J12=0),"",H12*J12) | L12: Best Buy / Amazon | M12: Bosch stacking kit WTZ20410 | O12: Confirmed | P12: medium | Q12: Brand-matched | Ціна збір: 2026-05-28
A13: 9 | B13: Appliances | C13: Kitchen Install | D13: Range Hood Ductwork + Cap | E13: 4" або 6" round duct + exterior cap | F13: set | G13: 1 | H13: 1 | I13: 1 | J13: 50 | K13: =IF(OR(H13="",J13="",J13=0),"",H13*J13) | L13: Home Depot | M13: Generic 4" round duct + exterior cap | O13: Confirmed | P13: medium | Q13: ДОДАНО: vent microwave/hood до outside | ДОДАНО: microwave/hood vent | Ціна збір: 2026-05-28
A14: 10 | B14: Appliances | C14: Kitchen Install | D14: Disposal Installation Kit (Optional) | E14: Drain + flange + plug cord | F14: set | G14: 0 | H14: 0 | I14: 1 | J14: 30 | K14: =IF(OR(H14="",J14="",J14=0),"",H14*J14) | L14: Home Depot | M14: Generic disposal install kit (Optional) | O14: Optional | P14: medium | Q14: ДОДАНО: tied до disposal r9 | ДОДАНО | Ціна збір: 2026-05-28
A15: 11 | B15: Appliances | C15: Kitchen Install | D15: Disposal Air Switch (Optional) | E15: Counter-mounted alternative до wall switch | F15: pcs | G15: 0 | H15: 0 | I15: 1 | J15: 35 | K15: =IF(OR(H15="",J15="",J15=0),"",H15*J15) | L15: Home Depot | M15: Generic disposal air switch (Optional) | O15: Optional | P15: medium | Q15: ДОДАНО: CA Code alt | ДОДАНО | Ціна збір: 2026-05-28
A16: 12 | B16: Appliances | C16: Appliance Install | D16: Range Power Cord | E16: 14-50R baseline | F16: pcs | G16: 1 | H16: 1 | I16: 1 | J16: 25 | K16: =IF(OR(H16="",J16="",J16=0),"",H16*J16) | L16: Home Depot | M16: Generic 14-50R range power cord 6 ft | O16: Confirmed | P16: medium | Q16: Final cord type TBD by selected range specs | ДОДАНО | Ціна збір: 2026-05-28
A17: 13 | B17: Appliances | C17: Appliance Install | D17: Dryer Power Cord | E17: 3 or 4-prong | F17: pcs | G17: 1 | H17: 1 | I17: 1 | J17: 25 | K17: =IF(OR(H17="",J17="",J17=0),"",H17*J17) | L17: Home Depot | M17: Generic 4-prong dryer cord | O17: Confirmed | P17: medium | Q17: Final cord type TBD by selected dryer specs | ДОДАНО | Ціна збір: 2026-05-28
A18: 14 | B18: Appliances | C18: Kitchen Install | D18: Dishwasher Installation Kit | E18: Water line + power cord + drain connection | F18: set | G18: 1 | H18: 1 | I18: 1 | J18: 25 | K18: =IF(OR(H18="",J18="",J18=0),"",H18*J18) | L18: Home Depot | M18: Generic dishwasher install kit | O18: Confirmed | P18: medium | Q18: ДОДАНО (review): often sold separately | ДОДАНО (review): water line + cord + drain | Ціна збір: 2026-05-28
... A21: 17 | B21: Appliances | C21: Kitchen Install | D21: OTR Microwave Duct Adapter + Foil Tape | E21: Rectangular-to-round adapter + foil tape + clamps | F21: set | G21: 1 | H21: 1 | I21: 1 | J21: 20 | K21: =IF(OR(H21="",J21="",J21=0),"",H21*J21) | L21: Home Depot | M21: Generic OTR rectangular-to-round adapter + tape | O21: Confirmed | P21: medium | Q21: ДОДАНО (review) | ДОДАНО (review) | Ціна збір: 2026-05-28
C23: ПІДСУМОК ФАЗИ | K23: =SUM(K5:K21)

Sheet 18_Furniture_IKEA
A1: Phase 17 — Furniture (§29)
A2: Living + Bedroom + Dining IKEA
A4: # | B4: Phase | C4: Категорія | D4: Item / Material | E4: Spec / Опис | F4: Unit | G4: Qty (Low) | H4: Qty (Mid) | I4: Qty (High) | J4: Unit Price ($) | K4: Total ($) | L4: Source | M4: SKU / Model | N4: URL | O4: Status | P4: Confidence | Q4: Notes
A5: 1 | B5: Furniture | C5: Living Room | D5: Sofa / Sleeper Sofa | E5: FRIHETEN sleeper, Faringe light gray | F5: pcs | G5: 1 | H5: 1 | I5: 1 | J5: 899 | K5: =IF(OR(H5="",J5="",J5=0),"",H5*J5) | L5: IKEA | M5: IKEA 405.512.31 — FRIHETEN | N5: https://www.ikea.com/us/en/p/friheten-sleeper-sofa-faringe-light-gray-40551231/ | O5: Confirmed | P5: high | Q5: Living Room | FRIHETEN sleeper Faringe light gray, 88⅝×41⅜. Queen bed 78×56. Alt: LYCKSELE LÖVÅS Ransta natural $499 (twin) | Ціна збір: 2026-05-28
A6: 2 | B6: Furniture | C6: Living Room | D6: Coffee Table | E6: LACK 35⅜, white stained oak | F6: pcs | G6: 1 | H6: 1 | I6: 1 | J6: 29.99 | K6: =IF(OR(H6="",J6="",J6=0),"",H6*J6) | L6: IKEA | M6: IKEA 503.190.29 — LACK | N6: https://www.ikea.com/us/en/p/lack-coffee-table-white-stained-oak-effect-50319029/ | O6: Confirmed | P6: high | Q6: Living Room | LACK 35⅜×21⅝, white stained oak effect | Ціна збір: 2026-05-28
A7: 3 | B7: Furniture | C7: Living Room | D7: TV Bench / Media Unit | E7: BESTÅ 47¼ white stained oak | F7: pcs | G7: 1 | H7: 1 | I7: 1 | J7: 75 | K7: =IF(OR(H7="",J7="",J7=0),"",H7*J7) | L7: IKEA | M7: IKEA 005.760.02 — BESTÅ | N7: https://www.ikea.com/us/en/p/besta-tv-unit-white-stained-oak-effect-00576002/ | O7: Confirmed | P7: high | Q7: Living Room | BESTÅ 47¼", white stained oak. До TV 45". Якщо TV 55" — обрати 70⅞" | Ціна збір: 2026-05-28
A8: 4 | B8: Furniture | C8: Living Room | D8: Storage Cabinet | E8: KALLAX 2x2 white stained oak | F8: pcs | G8: 1 | H8: 1 | I8: 1 | J8: 44.99 | K8: =IF(OR(H8="",J8="",J8=0),"",H8*J8) | L8: IKEA | M8: IKEA 603.245.20 — KALLAX 2x2 | N8: https://www.ikea.com/us/en/p/kallax-shelf-unit-white-stained-oak-effect-60324520/ | O8: Confirmed | P8: high | Q8: Living Room | KALLAX 2x2 30⅛", white stained oak | Ціна збір: 2026-05-28
A9: 5 | B9: Furniture | C9: Living Room | D9: Rug | E9: LOHALS jute 5'3×7'7 | F9: pcs | G9: 1 | H9: 1 | I9: 1 | J9: 129.99 | K9: =IF(OR(H9="",J9="",J9=0),"",H9*J9) | L9: IKEA | M9: IKEA 502.773.93 — LOHALS | N9: https://www.ikea.com/us/en/p/lohals-rug-flatwoven-natural-50277393/ | O9: Confirmed | P9: high | Q9: Living Room | LOHALS jute 5'3×7'7, natural | Ціна збір: 2026-05-28
A10: 6 | B10: Furniture | C10: Living Room | D10: Curtains + Blinds combo | E10: RITVA pair + TRETUR roller | F10: set | G10: 1 | H10: 1 | I10: 1 | J10: 104.98 | K10: =IF(OR(H10="",J10="",J10=0),"",H10*J10) | L10: IKEA | M10: IKEA 405.564.17 (RITVA) + 803.804.64 (TRETUR) | N10: https://www.ikea.com/us/en/p/ritva-curtains-with-tie-backs-1-pair-white-40556417/ | O10: Confirmed | P10: medium | Q10: French door + window | Combo: RITVA 57×84 pair $34.99 на French door + TRETUR roller 48×76¾ $69.99 на вікно | Ціна збір: 2026-05-28
A11: 7 | B11: Furniture | C11: Living Room | D11: Floor Lamp | E11: VIDJA white | F11: pcs | G11: 1 | H11: 1 | I11: 1 | J11: 69.99 | K11: =IF(OR(H11="",J11="",J11=0),"",H11*J11) | L11: IKEA | M11: IKEA 103.092.06 — VIDJA | N11: https://www.ikea.com/us/en/p/vidja-floor-lamp-white-10309206/ | O11: Confirmed | P11: high | Q11: Living Room | VIDJA white floor lamp | Ціна збір: 2026-05-28
A12: 8 | B12: Furniture | C12: Bedroom | D12: Full Bed Frame | E12: IKEA MALM Full white з LÖNSET slatted base | F12: pcs | G12: 1 | H12: 1 | I12: 1 | J12: 329 | K12: =IF(OR(H12="",J12="",J12=0),"",H12*J12) | L12: IKEA | M12: IKEA MALM Full з LÖNSET base | N12: https://www.ikea.com/us/en/p/malm-bed-frame-white-loenset-s39019169/ | O12: Confirmed | P12: high | Q12: 54×75. LÖNSET base included | $329 з slatted base included | Ціна збір: 2026-05-28
A13: 9 | B13: Furniture | C13: Bedroom | D13: Full Mattress | E13: IKEA HÖVÅG/MORGEDAL Full (HAFSLO discontinued US) | F13: pcs | G13: 1 | H13: 1 | I13: 1 | J13: 250 | K13: =IF(OR(H13="",J13="",J13=0),"",H13*J13) | L13: IKEA | M13: IKEA HÖVÅG/MORGEDAL Full mattress | O13: Confirmed | P13: medium | Q13: 54×75 | HAFSLO discontinued. HÖVÅG spring $299, MORGEDAL foam $229. Mid $250 | Ціна збір: 2026-05-28
A14: 10 | B14: Furniture | C14: Bedroom | D14: Nightstands | E14: IKEA MALM 2-drawer × 2 | F14: pcs | G14: 1 | H14: 2 | I14: 2 | J14: 80 | K14: =IF(OR(H14="",J14="",J14=0),"",H14*J14) | L14: IKEA | M14: IKEA MALM 2-drawer nightstand | O14: Confirmed | P14: medium | Q14: Per pc | Ціна збір: 2026-05-28
A15: 11 | B15: Furniture | C15: Bedroom | D15: Dresser / Small Storage | E15: IKEA MALM 4-drawer | F15: pcs | G15: 1 | H15: 1 | I15: 1 | J15: 179 | K15: =IF(OR(H15="",J15="",J15=0),"",H15*J15) | L15: IKEA | M15: IKEA MALM 4-drawer dresser | O15: Confirmed | P15: medium | Q15: | Ціна збір: 2026-05-28
A16: 12 | B16: Furniture | C16: Bedroom | D16: Bedside Lamps | E16: IKEA NYFORS/MELODI table lamps × 2 | F16: pcs | G16: 1 | H16: 2 | I16: 2 | J16: 30 | K16: =IF(OR(H16="",J16="",J16=0),"",H16*J16) | L16: IKEA | M16: IKEA NYFORS/MELODI table lamp | O16: Confirmed | P16: medium | Q16: Per pc | Ціна збір: 2026-05-28
A17: 13 | B17: Furniture | C17: Bedroom | D17: Window Covering (bedroom) | E17: RITVA panels (matched Living combo) | F17: set | G17: 1 | H17: 1 | I17: 1 | J17: 35 | K17: =IF(OR(H17="",J17="",J17=0),"",H17*J17) | L17: IKEA | M17: IKEA RITVA curtain pair | O17: Confirmed | P17: medium | Q17: Same as Living combo | Ціна збір: 2026-05-28
A18: 14 | B18: Furniture | C18: Dining | D18: Round Dining Table | E18: 30-35" IKEA KRAGSTA round або equivalent | F18: pcs | G18: 1 | H18: 1 | I18: 1 | J18: 130 | K18: =IF(OR(H18="",J18="",J18=0),"",H18*J18) | L18: IKEA | M18: IKEA KRAGSTA round dining table 35" | O18: Confirmed | P18: medium | Q18: DOCKSTA 41" alt $179 | Ціна збір: 2026-05-28
A19: 15 | B19: Furniture | C19: Dining | D19: Dining Chairs | E19: IKEA TEODORES × 3 mid-priced | F19: pcs | G19: 2 | H19: 3 | I19: 4 | J19: 60 | K19: =IF(OR(H19="",J19="",J19=0),"",H19*J19) | L19: IKEA | M19: IKEA TEODORES dining chair | O19: Confirmed | P19: medium | Q19: Per chair. JANINGE alt $79 | Ціна збір: 2026-05-28
A20: 16 | B20: Furniture | C20: Dining | D20: Pendant Light | E20: IKEA FOTO Optional | F20: pcs | G20: 0 | H20: 1 | I20: 1 | J20: 50 | K20: =IF(OR(H20="",J20="",J20=0),"",H20*J20) | L20: IKEA / Home Depot | M20: IKEA FOTO pendant light (Optional) | O20: Optional | P20: medium | Q20: Qty 0 baseline | Ціна збір: 2026-05-28
A21: 17 | B21: Furniture | C21: Bathroom Storage | D21: Bathroom / Utility Storage | E21: Per §29.5: cabinet + shelves + organizers — Mid 1 | F21: set | G21: 0 | H21: 1 | I21: 1 | J21: 80 | K21: =IF(OR(H21="",J21="",J21=0),"",H21*J21) | L21: IKEA | M21: IKEA bathroom storage cabinet + shelves | O21: Confirmed | P21: medium | Q21: Per ТЗ §29.5. Mid підвищено 0→1 (review) | Per §29.5. Mid підвищено 0→1 (review) | Ціна збір: 2026-05-28
A22: 18 | B22: Furniture | C22: Soft Goods | D22: Curtain Rods / Brackets / Rings | E22: Hardware для всіх curtain panels | F22: set | G22: 1 | H22: 1 | I22: 2 | J22: 25 | K22: =IF(OR(H22="",J22="",J22=0),"",H22*J22) | L22: IKEA / Home Depot | M22: IKEA RÄCKA curtain rod + brackets set | O22: Confirmed | P22: medium | Q22: ДОДАНО (review): high priority | ДОДАНО (review) | Ціна збір: 2026-05-28
A23: 19 | B23: Furniture | C23: Soft Goods | D23: Kitchen Window Covering | E23: RITVA panels або roller blind | F23: set | G23: 1 | H23: 1 | I23: 1 | J23: 35 | K23: =IF(OR(H23="",J23="",J23=0),"",H23*J23) | L23: IKEA | M23: IKEA RITVA panels for kitchen window | O23: Confirmed | P23: medium | Q23: ДОДАНО (review) | ДОДАНО (review) | Ціна збір: 2026-05-28
A24: 20 | B24: Furniture | C24: Soft Goods | D24: Bathroom Window Covering | E24: Roller blind privacy | F24: set | G24: 1 | H24: 1 | I24: 1 | J24: 35 | K24: =IF(OR(H24="",J24="",J24=0),"",H24*J24) | L24: IKEA | M24: IKEA TUPPLUR roller blind for bathroom | O24: Confirmed | P24: medium | Q24: ДОДАНО (review) | ДОДАНО (review): privacy | Ціна збір: 2026-05-28
... A31: 27 | B31: Furniture | C31: Bathroom Storage | D31: Bath Mat + Towels (Optional) | E31: Bathroom textiles allowance | F31: set | G31: 0 | H31: 0 | I31: 1 | J31: 40 | K31: =IF(OR(H31="",J31="",J31=0),"",H31*J31) | L31: IKEA / Amazon | M31: Bath mat + towels set (Optional) | O31: Optional | P31: medium | Q31: ДОДАНО (review) | ДОДАНО (review) | Ціна збір: 2026-05-28
C33: ПІДСУМОК ФАЗИ | K33: =SUM(K5:K31)

Sheet 19_Special_Orders
A1: Cross-reference — Special Orders (§31.5)
A2: Special items з lead times 4-12 weeks
A4: # | B4: Phase | C4: Категорія | D4: Item / Material | E4: Spec / Опис | F4: Unit | G4: Qty (Low) | H4: Qty (Mid) | I4: Qty (High) | J4: Unit Price ($) | K4: Total ($) | L4: Source | M4: SKU / Model | N4: URL | O4: Status | P4: Confidence | Q4: Notes
A5: 1 | B5: Special Order | C5: Doors | D5: Backyard French Door | E5: Glazed, exterior | F5: pcs | G5: 1 | H5: 1 | I5: 1 | K5: =IF(OR(H5="",J5="",J5=0),"",H5*J5) | L5: Special Order | O5: Confirmed | Q5: → Лист #05. Lead time 4-8 weeks
A6: 2 | B6: Special Order | C6: Doors | D6: Folding / Panel Door System 8 ft | E6: Між bedroom і living | F6: system | G6: 1 | H6: 1 | I6: 1 | K6: =IF(OR(H6="",J6="",J6=0),"",H6*J6) | L6: Special Order | O6: Confirmed | Q6: → Лист #05. Lead 6-10 weeks
A7: 3 | B7: Special Order | C7: HVAC | D7: Mini-split Outdoor Condenser | E7: Multi-zone | F7: pcs | G7: 1 | H7: 1 | I7: 1 | K7: =IF(OR(H7="",J7="",J7=0),"",H7*J7) | L7: Special Order | O7: Confirmed | Q7: → Лист #08. Lead 4-8 weeks
A8: 4 | B8: Special Order | C8: HVAC | D8: Mini-split Indoor Units (2) | E8: Wall-mounted | F8: pcs | G8: 2 | H8: 2 | I8: 2 | K8: =IF(OR(H8="",J8="",J8=0),"",H8*J8) | L8: Special Order | O8: Confirmed | Q8: → Лист #08
A9: 5 | B9: Special Order | C9: Laundry | D9: Compact Washer 24" | E9: Stacked | F9: pcs | G9: 1 | H9: 1 | I9: 1 | K9: =IF(OR(H9="",J9="",J9=0),"",H9*J9) | L9: Special Order | O9: Confirmed | Q9: → Лист #17. Lead 4-6 weeks
A10: 6 | B10: Special Order | C10: Laundry | D10: Ventless Compact Dryer 24" | E10: Heat pump/condenser | F10: pcs | G10: 1 | H10: 1 | I10: 1 | K10: =IF(OR(H10="",J10="",J10=0),"",H10*J10) | L10: Special Order | O10: Confirmed | Q10: → Лист #17
A11: 7 | B11: Special Order | C11: Water Heater | D11: Electric Tank Water Heater 20-30 gal | F11: pcs | G11: 1 | H11: 1 | I11: 1 | K11: =IF(OR(H11="",J11="",J11=0),"",H11*J11) | L11: Home Depot / specialty | O11: Confirmed | Q11: → Лист #16. Можна купити stock
C13: ПІДСУМОК ФАЗИ | K13: =SUM(K5:K11)

Sheet 20_Verification_Items
A1: Cross-reference — Verification Items (§33)
A2: 26 пунктів must-verify-before-ordering
A4: # | B4: Phase | C4: Категорія | D4: Item / Material | E4: Spec / Опис | F4: Unit | G4: Qty (Low) | H4: Qty (Mid) | I4: Qty (High) | J4: Unit Price ($) | K4: Total ($) | L4: Source | M4: SKU / Model | N4: URL | O4: Status | P4: Confidence | Q4: Notes
A5: 1 | B5: Verification | C5: Field | D5: Exact field dimensions of garage | E5: Total ADU footprint | F5: — | G5: 0 | H5: 0 | I5: 0 | K5: =IF(OR(H5="",J5="",J5=0),"",H5*J5) | L5: Field measurement | O5: TBD | Q5: ТЗ §33.1
A6: 2 | B6: Verification | C6: Field | D6: Exact wall thicknesses | E6: Interior + exterior | F6: — | G6: 0 | H6: 0 | I6: 0 | K6: =IF(OR(H6="",J6="",J6=0),"",H6*J6) | L6: Field measurement | O6: TBD | Q6: ТЗ §33.2
A7: 3 | B7: Verification | C7: Field | D7: Exact interior wall layout | F7: — | G7: 0 | H7: 0 | I7: 0 | K7: =IF(OR(H7="",J7="",J7=0),"",H7*J7) | L7: Field measurement | O7: TBD | Q7: ТЗ §33.3
A8: 4 | B8: Verification | C8: Field | D8: Exact bathroom size after laundry/utility | F8: — | G8: 0 | H8: 0 | I8: 0 | K8: =IF(OR(H8="",J8="",J8=0),"",H8*J8) | L8: Field measurement | O8: TBD | Q8: ТЗ §33.4
A9: 5 | B9: Verification | C9: Field | D9: Exact location of stacked washer/dryer | F9: — | G9: 0 | H9: 0 | I9: 0 | K9: =IF(OR(H9="",J9="",J9=0),"",H9*J9) | L9: Field measurement | O9: TBD | Q9: ТЗ §33.5
A10: 6 | B10: Verification | C10: Field | D10: Exact utility closet size & location | F10: — | G10: 0 | H10: 0 | I10: 0 | K10: =IF(OR(H10="",J10="",J10=0),"",H10*J10) | L10: Field measurement | O10: TBD | Q10: ТЗ §33.6
A11: 7 | B11: Verification | C11: Specs | D11: Electric tank water heater size | E11: 20 vs 30 gal | F11: — | G11: 0 | H11: 0 | I11: 0 | K11: =IF(OR(H11="",J11="",J11=0),"",H11*J11) | L11: Specification | O11: TBD | Q11: ТЗ §33.7
A12: 8 | B12: Verification | C12: Specs | D12: Exact washer/dryer model | E12: Особисто per brand | F12: — | G12: 0 | H12: 0 | I12: 0 | K12: =IF(OR(H12="",J12="",J12=0),"",H12*J12) | L12: Specification | O12: TBD | Q12: ТЗ §33.8
A13: 9 | B13: Verification | C13: Specs | D13: Mini-split model + BTU sizing | E13: HVAC load calc | F13: — | G13: 0 | H13: 0 | I13: 0 | K13: =IF(OR(H13="",J13="",J13=0),"",H13*J13) | L13: Specification | O13: TBD | Q13: ТЗ §33.9
A14: 10 | B14: Verification | C14: Specs | D14: Kitchen cabinet layout from IKEA planner | F14: — | G14: 0 | H14: 0 | I14: 0 | K14: =IF(OR(H14="",J14="",J14=0),"",H14*J14) | L14: IKEA Planner | O14: TBD | Q14: ТЗ §33.10
A15: 11 | B15: Verification | C15: Specs | D15: Exact appliance dimensions | F15: — | G15: 0 | H15: 0 | I15: 0 | K15: =IF(OR(H15="",J15="",J15=0),"",H15*J15) | L15: Specification | O15: TBD | Q15: ТЗ §33.11
A16: 12 | B16: Verification | C16: Openings | D16: Exact window sizes | E16: 3 вікна | F16: — | G16: 0 | H16: 0 | I16: 0 | K16: =IF(OR(H16="",J16="",J16=0),"",H16*J16) | L16: Field + Spec | O16: TBD | Q16: ТЗ §33.12
A17: 13 | B17: Verification | C17: Openings | D17: Exact French door size | F17: — | G17: 0 | H17: 0 | I17: 0 | K17: =IF(OR(H17="",J17="",J17=0),"",H17*J17) | L17: Field + Spec | O17: TBD | Q17: ТЗ §33.13
A18: 14 | B18: Verification | C18: Openings | D18: Exact main entry door size | F18: — | G18: 0 | H18: 0 | I18: 0 | K18: =IF(OR(H18="",J18="",J18=0),"",H18*J18) | L18: Field + Spec | O18: TBD | Q18: ТЗ §33.14
A19: 15 | B19: Verification | C19: Openings | D19: Folding/panel system product + RO | F19: — | G19: 0 | H19: 0 | I19: 0 | K19: =IF(OR(H19="",J19="",J19=0),"",H19*J19) | L19: Spec | O19: TBD | Q19: ТЗ §33.15
A20: 16 | B20: Verification | C20: Openings | D20: Closet sliding door size | F20: — | G20: 0 | H20: 0 | I20: 0 | K20: =IF(OR(H20="",J20="",J20=0),"",H20*J20) | L20: Field + Spec | O20: TBD | Q20: ТЗ §33.16
A21: 17 | B21: Verification | C21: MEP | D21: Sewer route + slope verification | E21: 1/4" per ft min | F21: — | G21: 0 | H21: 0 | I21: 0 | K21: =IF(OR(H21="",J21="",J21=0),"",H21*J21) | L21: Site survey | O21: TBD | Q21: ТЗ §33.17
A22: 18 | B22: Verification | C22: MEP | D22: Water supply route | F22: — | G22: 0 | H22: 0 | I22: 0 | K22: =IF(OR(H22="",J22="",J22=0),"",H22*J22) | L22: Site survey | O22: TBD | Q22: ТЗ §33.18
A23: 19 | B23: Verification | C23: MEP | D23: Electrical route | E23: Underground or overhead | F23: — | G23: 0 | H23: 0 | I23: 0 | K23: =IF(OR(H23="",J23="",J23=0),"",H23*J23) | L23: Site survey | O23: TBD | Q23: ТЗ §33.19
A24: 20 | B24: Verification | C24: MEP | D24: Existing main electrical panel capacity | E24: Amperage | F24: — | G24: 0 | H24: 0 | I24: 0 | K24: =IF(OR(H24="",J24="",J24=0),"",H24*J24) | L24: Electrician | O24: TBD | Q24: ТЗ §33.20
A25: 21 | B25: Verification | C25: MEP | D25: Required ADU subpanel amperage | E25: 100A vs 125A | F25: — | G25: 0 | H25: 0 | I25: 0 | K25: =IF(OR(H25="",J25="",J25=0),"",H25*J25) | L25: Electrician | O25: TBD | Q25: ТЗ §33.21
A26: 22 | B26: Verification | C26: Floor | D26: Floor slab leveling needed? | F26: — | G26: 0 | H26: 0 | I26: 0 | K26: =IF(OR(H26="",J26="",J26=0),"",H26*J26) | L26: Field inspection | O26: TBD | Q26: ТЗ §33.22
A27: 23 | B27: Verification | C27: Floor | D27: Moisture mitigation over slab? | E27: Vapor barrier sufficient? | F27: — | G27: 0 | H27: 0 | I27: 0 | K27: =IF(OR(H27="",J27="",J27=0),"",H27*J27) | L27: Field inspection | O27: TBD | Q27: ТЗ §33.23
A28: 24 | B28: Verification | C28: Bath | D28: Additional waterproofing in wet zones? | F28: — | G28: 0 | H28: 0 | I28: 0 | K28: =IF(OR(H28="",J28="",J28=0),"",H28*J28) | L28: Spec | O28: TBD | Q28: ТЗ §33.24
A29: 25 | B29: Verification | C29: Framing | D29: Structural headers for exterior openings? | E29: Engineer review | F29: — | G29: 0 | H29: 0 | I29: 0 | K29: =IF(OR(H29="",J29="",J29=0),"",H29*J29) | L29: Engineering | O29: TBD | Q29: ТЗ §33.25
A30: 26 | B30: Verification | C30: Code | D30: Menlo Park / CA code requirements | E30: Fire, energy, vent, safety | F30: — | G30: 0 | H30: 0 | I30: 0 | K30: =IF(OR(H30="",J30="",J30=0),"",H30*J30) | L30: Code review | O30: TBD | Q30: ТЗ §33.26
C32: ПІДСУМОК ФАЗИ | K32: =SUM(K5:K30)
